Workbook

Sheet 车次台账
A1: 车次台账（导出 2026-09-21 13:26，共 101 车，不含作废） 表头颜色：蓝=基本信息 绿=利润 黄=利润过程参数 紫=票款 灰=其他；净利润 = 毛服务费 + 量补金额 − 垫资成本 − 调货人提成 − 其他成本
A2: 车次ID | B2: 结算日期 | C2: 车号/船号 | D2: 车/船 | E2: 路径 | F2: 链条 | G2: 调货人 | H2: 供货厂/车队 | I2: 票源方 | J2: 状态 | K2: 结算吨位(吨) | L2: 结算金额(元) | M2: 净利润(元) | N2: 单吨利润(元/吨) | O2: 留存利润(元)·不计入净利润 | P2: 服务费单价(元/吨) | Q2: 毛服务费(元) | R2: 量补单价(元/吨) | S2: 量补金额(元) | T2: 对外结算点位(%) | U2: 给客户付(元) | V2: 垫资费单价(元/吨) | W2: 垫资费(元) | X2: 前端开票金额(元) | Y2: 票源成本点位(%) | Z2: 前端实付(元) | AA2: 垫资成本(元)·配票=个人垫资 | AB2: 提成单价(元/吨) | AC2: 调货人提成(元) | AD2: 其他成本(元)·含切割费 | AE2: 本车改过的费率 | AF2: 开票路径 | AG2: 票额(估)(元) | AH2: 进项 | AI2: 销项→欧冶 | AJ2: 欧冶回款 | AK2: 付票源 | AL2: 到客户账户 | AM2: 提成已付(元) | AN2: 接单日期 | AO2: 结算月份 | AP2: 扣杂(吨) | AQ2: 结算单号 | AR2: 钢厂 | AS2: 户头 | AT2: 司机 | AU2: 备注
A3: 1 | B3: 46253 | C3: 苏DBB772 | D3: 车 | E3: 配票/反向 | F3: 配票 | G3: 林凯 | H3: 林凯车队 | I3: 俊兴 | J3: 已开票 | K3: 73.58 | L3: 168498.2 | M3: =Q3+S3-AA3-AC3-AD3 | N3: =IF(K3=0,0,M3/K3) | O3: 0 | Q3: 0 | R3: 20 | S3: 1471.6 | T3: 14 | U3: 144908.45 | V3: 23 | W3: 1692.34 | X3: 166805.86 | Y3: 13.5 | Z3: 144287.07 | AA3: 621.3831 | AB3: 5 | AC3: 367.9 | AD3: 0 | AF3: 我们配票（经俊兴） | AG3: 166805.86 | AH3: — | AI3: 按状态视为已完成(历史) | AJ3: 待登记 | AK3: — | AL3: 未开始(前一环节未完成) | AM3: 0 | AN3: 46253 | AO3: 2026-08 | AP3: 0.9 | AQ3: 台账历史数据-已出结算单（具体单号未录入） | AR3: 华西特钢 | AS3: 华西-欧冶户头 | AU3: 由台账 Excel 历史数据自动导入（8.19付款明细-欧冶物宝1.xlsx 第5行），日期为过磅日期近似值 [原货主:林凯]
A4: 2 | B4: 46254 | C4: 苏DFM060 | D4: 车 | E4: 配票/反向 | F4: 配票 | G4: 林凯 | H4: 林凯车队 | I4: 俊兴 | J4: 已开票 | K4: 34.8 | L4: 84564 | M4: =Q4+S4-AA4-AC4-AD4 | N4: =IF(K4=0,0,M4/K4) | O4: 0 | Q4: 0 | R4: 20 | S4: 696 | T4: 14 | U4: 72725.04 | V4: 23 | W4: 800.4 | X4: 83763.6 | Y4: 13.5 | Z4: 72455.514 | AA4: 269.526 | AB4: 5 | AC4: 174 | AD4: 0 | AF4: 我们配票（经俊兴） | AG4: 83763.6 | AH4: — | AI4: 按状态视为已完成(历史) | AJ4: 待登记 | AK4: — | AL4: 未开始(前一环节未完成) | AM4: 0 | AN4: 46254 | AO4: 2026-08 | AP4: 0.5 | AQ4: 台账历史数据-已出结算单（具体单号未录入） | AR4: 华西特钢 | AS4: 华西-欧冶户头 | AU4: 由台账 Excel 历史数据自动导入（8.19付款明细-欧冶物宝1.xlsx 第6行），日期为过磅日期近似值 [原货主:林凯]
A5: 3 | B5: 46255 | C5: 苏DBB772 | D5: 车 | E5: 配票/反向 | F5: 配票 | G5: 林凯 | H5: 林凯车队 | I5: 俊兴 | J5: 已开票 | K5: 81.16 | L5: 201276.8 | M5: =Q5+S5-AA5-AC5-AD5 | N5: =IF(K5=0,0,M5/K5) | O5: 0 | Q5: 0 | R5: 20 | S5: 1623.2 | T5: 14 | U5: 173098.05 | V5: 23 | W5: 1866.68 | X5: 199410.12 | Y5: 13.5 | Z5: 172489.75 | AA5: 608.2942 | AB5: 5 | AC5: 405.8 | AD5: 0 | AF5: 我们配票（经俊兴） | AG5: 199410.12 | AH5: — | AI5: 按状态视为已完成(历史) | AJ5: 待登记 | AK5: — | AL5: 未开始(前一环节未完成) | AM5: 0 | AN5: 46255 | AO5: 2026-08 | AP5: 0.8 | AQ5: 台账历史数据-已出结算单（具体单号未录入） | AR5: 华西特钢 | AS5: 华西-欧冶户头 | AU5: 由台账 Excel 历史数据自动导入（8.19付款明细-欧冶物宝1.xlsx 第7行），日期为过磅日期近似值 [原货主:林凯]
A6: 4 | B6: 46255 | C6: 皖M2A505 | D6: 车 | E6: 配票/反向 | F6: 配票 | H6: 俊兴 | I6: 俊兴 | J6: 已开票 | K6: 36.36 | L6: 83264.4 | M6: =Q6+S6-AA6-AC6-AD6 | N6: =IF(K6=0,0,M6/K6) | O6: 0 | Q6: 0 | R6: 20 | S6: 727.2 | T6: 14 | U6: 71607.384 | V6: 23 | W6: 836.28 | X6: 82428.12 | Y6: 13.5 | Z6: 71300.324 | AA6: 307.0602 | AB6: 0 | AC6: 0 | AD6: 0 | AF6: 我们配票（经俊兴） | AG6: 82428.12 | AH6: — | AI6: 按状态视为已完成(历史) | AJ6: 待登记 | AK6: — | AL6: 未开始(前一环节未完成) | AM6: 0 | AN6: 46255 | AO6: 2026-08 | AP6: 0.3 | AQ6: 台账历史数据-已出结算单（具体单号未录入） | AR6: 华西特钢 | AS6: 华西-欧冶户头 | AU6: 由台账 Excel 历史数据自动导入（8.19付款明细-欧冶物宝1.xlsx 第8行），日期为过磅日期近似值
A7: 5 | B7: 46255 | C7: 苏EQB977 | D7: 车 | E7: 配票/反向 | F7: 配票 | H7: 俊兴 | I7: 俊兴 | J7: 已开票 | K7: 32.94 | L7: 75432.6 | M7: =Q7+S7-AA7-AC7-AD7 | N7: =IF(K7=0,0,M7/K7) | O7: 0 | Q7: 0 | R7: 20 | S7: 658.8 | T7: 14 | U7: 64872.036 | V7: 23 | W7: 757.62 | X7: 74674.98 | Y7: 13.5 | Z7: 64593.858 | AA7: 278.1783 | AB7: 0 | AC7: 0 | AD7: 0 | AF7: 我们配票（经俊兴） | AG7: 74674.98 | AH7: — | AI7: 按状态视为已完成(历史) | AJ7: 待登记 | AK7: — | AL7: 未开始(前一环节未完成) | AM7: 0 | AN7: 46255 | AO7: 2026-08 | AP7: 0.3 | AQ7: 台账历史数据-已出结算单（具体单号未录入） | AR7: 华西特钢 | AS7: 华西-欧冶户头 | AU7: 由台账 Excel 历史数据自动导入（8.19付款明细-欧冶物宝1.xlsx 第9行），日期为过磅日期近似值
A8: 6 | B8: 46255 | C8: 苏BUK952 | D8: 车 | E8: 配票/反向 | F8: 配票 | G8: 林凯 | H8: 林凯车队 | I8: 俊兴 | J8: 已开票 | K8: 24.41 | L8: 59023.38 | M8: =Q8+S8-AA8-AC8-AD8 | N8: =IF(K8=0,0,M8/K8) | O8: 0 | Q8: 0 | R8: 20 | S8: 488.2 | T8: 14 | U8: 50760.107 | V8: 23 | W8: 561.43 | X8: 58461.95 | Y8: 13.5 | Z8: 50569.587 | AA8: 190.52005 | AB8: 5 | AC8: 122.05 | AD8: 0 | AF8: 我们配票（经俊兴） | AG8: 58461.95 | AH8: — | AI8: 按状态视为已完成(历史) | AJ8: 待登记 | AK8: — | AL8: 未开始(前一环节未完成) | AM8: 0 | AN8: 46255 | AO8: 2026-08 | AP8: 0.25 | AQ8: 台账历史数据-已出结算单（具体单号未录入） | AR8: 华西特钢 | AS8: 华西-欧冶户头 | AU8: 由台账 Excel 历史数据自动导入（8.19付款明细-欧冶物宝1.xlsx 第10行），日期为过磅日期近似值 [原货主:林凯]
A9: 7 | B9: 46256 | C9: 苏DBB772 | D9: 车 | E9: 配票/反向 | F9: 配票 | G9: 林凯 | H9: 林凯车队 | I9: 俊兴 | J9: 已开票 | K9: 69.5 | L9: 159155 | M9: =Q9+S9-AA9-AC9-AD9 | N9: =IF(K9=0,0,M9/K9) | O9: 0 | Q9: 0 | R9: 20 | S9: 1390 | T9: 14 | U9: 136873.3 | V9: 23 | W9: 1598.5 | X9: 157556.5 | Y9: 13.5 | Z9: 136286.37 | AA9: 586.9275 | AB9: 5 | AC9: 347.5 | AD9: 0 | AF9: 我们配票（经俊兴） | AG9: 157556.5 | AH9: — | AI9: 按状态视为已完成(历史) | AJ9: 待登记 | AK9: — | AL9: 未开始(前一环节未完成) | AM9: 0 | AN9: 46256 | AO9: 2026-08 | AP9: 1.4 | AQ9: 台账历史数据-已出结算单（具体单号未录入） | AR9: 华西特钢 | AS9: 华西-欧冶户头 | AU9: 由台账 Excel 历史数据自动导入（8.19付款明细-欧冶物宝1.xlsx 第12行），日期为过磅日期近似值 [原货主:林凯]
A10: 8 | B10: 46256 | C10: 苏E9W908 | D10: 车 | E10: 配票/反向 | F10: 配票 | G10: 邓晶焱 | H10: 邓晶焱车队 | I10: 俊兴 | J10: 已开票 | K10: 39.16 | L10: 91242.8 | M10: =Q10+S10-AA10-AC10-AD10 | N10: =IF(K10=0,0,M10/K10) | O10: 0 | Q10: 0 | R10: 20 | S10: 783.2 | T10: 14 | U10: 78468.808 | V10: 23 | W10: 900.68 | X10: 90342.12 | Y10: 13.5 | Z10: 78145.934 | AA10: 322.8742 | AB10: 0 | AC10: 0 | AD10: 0 | AF10: 我们配票（经俊兴） | AG10: 90342.12 | AH10: — | AI10: 按状态视为已完成(历史) | AJ10: 待登记 | AK10: — | AL10: 未开始(前一环节未完成) | AM10: 0 | AN10: 46256 | AO10: 2026-08 | AP10: 1 | AQ10: 台账历史数据-已出结算单（具体单号未录入） | AR10: 华西特钢 | AS10: 华西-欧冶户头 | AU10: 由台账 Excel 历史数据自动导入（8.19付款明细-欧冶物宝1.xlsx 第13行），日期为过磅日期近似值
A11: 9 | B11: 46256 | C11: 苏MAK862 | D11: 车 | E11: 配票/反向 | F11: 配票 | H11: 俊兴 | I11: 俊兴 | J11: 已开票 | K11: 34.24 | L11: 78409.6 | M11: =Q11+S11-AA11-AC11-AD11 | N11: =IF(K11=0,0,M11/K11) | O11: 0 | Q11: 0 | R11: 20 | S11: 684.8 | T11: 14 | U11: 67432.256 | V11: 23 | W11: 787.52 | X11: 77622.08 | Y11: 13.5 | Z11: 67143.099 | AA11: 289.1568 | AB11: 0 | AC11: 0 | AD11: 0 | AF11: 我们配票（经俊兴） | AG11: 77622.08 | AH11: — | AI11: 按状态视为已完成(历史) | AJ11: 待登记 | AK11: — | AL11: 未开始(前一环节未完成) | AM11: 0 | AN11: 46256 | AO11: 2026-08 | AP11: 0.6 | AQ11: 台账历史数据-已出结算单（具体单号未录入） | AR11: 华西特钢 | AS11: 华西-欧冶户头 | AU11: 由台账 Excel 历史数据自动导入（8.19付款明细-欧冶物宝1.xlsx 第14行），日期为过磅日期近似值
A12: 10 | B12: 46259 | C12: 苏DBE075 | D12: 车 | E12: 配票/反向 | F12: 配票 | G12: 林凯 | H12: 林凯车队 | I12: 俊兴 | J12: 已开票 | K12: 81 | L12: 184032 | M12: =Q12+S12-AA12-AC12-AD12 | N12: =IF(K12=0,0,M12/K12) | O12: 0 | Q12: 0 | R12: 20 | S12: 1620 | T12: 14 | U12: 158267.52 | V12: 23 | W12: 1863 | X12: 182169 | Y12: 13.5 | Z12: 157576.18 | AA12: 691.335 | AB12: 5 | AC12: 405 | AD12: 0 | AF12: 我们配票（经俊兴） | AG12: 182169 | AH12: — | AI12: 按状态视为已完成(历史) | AJ12: 待登记 | AK12: — | AL12: 未开始(前一环节未完成) | AM12: 0 | AN12: 46259 | AO12: 2026-08 | AP12: 1.2 | AQ12: 台账历史数据-已出结算单（具体单号未录入） | AR12: 华西特钢 | AS12: 华西-欧冶户头 | AU12: 由台账 Excel 历史数据自动导入（8.19付款明细-欧冶物宝1.xlsx 第15行），日期为过磅日期近似值 [原货主:林凯]
A13: 11 | B13: 46261 | C13: 苏淮货16776 | D13: 船 | E13: 配票/反向 | F13: 配票 | H13: 俊兴 | I13: 俊兴 | J13: 已开票 | K13: 560.39 | L13: 1344115.9 | M13: =Q13+S13-AA13-AC13-AD13 | N13: =IF(K13=0,0,M13/K13) | O13: 0 | Q13: 0 | R13: 25 | S13: 14009.75 | T13: 14 | U13: 1155939.7 | V13: 23 | W13: 12888.97 | X13: 1331226.9 | Y13: 13.5 | Z13: 1151511.3 | AA13: 4428.3796 | AB13: 0 | AC13: 0 | AD13: 0 | AF13: 我们配票（经俊兴） | AG13: 1331226.9 | AH13: — | AI13: 按状态视为已完成(历史) | AJ13: 待登记 | AK13: — | AL13: 未开始(前一环节未完成) | AM13: 0 | AN13: 46261 | AO13: 2026-08 | AP13: 0 | AQ13: 台账历史数据-已出结算单（具体单号未录入） | AR13: 华西特钢 | AS13: 华西-欧冶户头 | AU13: 由台账 Excel 历史数据自动导入（8.19付款明细-欧冶物宝1.xlsx 第17行），日期为过磅日期近似值
A14: 12 | B14: 46261 | C14: 苏NEX375 | D14: 车 | E14: 配票/反向 | F14: 配票 | G14: 林凯 | H14: 林凯车队 | I14: 俊兴 | J14: 已开票 | K14: 40.27 | L14: 93426.4 | M14: =Q14+S14-AA14-AC14-AD14 | N14: =IF(K14=0,0,M14/K14) | O14: 0 | Q14: 0 | R14: 25 | S14: 1006.75 | T14: 14 | U14: 80346.704 | V14: 23 | W14: 926.21 | X14: 92500.19 | Y14: 13.5 | Z14: 80012.664 | AA14: 334.03965 | AB14: 5 | AC14: 201.35 | AD14: 0 | AF14: 我们配票（经俊兴） | AG14: 92500.19 | AH14: — | AI14: 按状态视为已完成(历史) | AJ14: 待登记 | AK14: — | AL14: 未开始(前一环节未完成) | AM14: 0 | AN14: 46261 | AO14: 2026-08 | AP14: 0.45 | AQ14: 台账历史数据-已出结算单（具体单号未录入） | AR14: 华西特钢 | AS14: 华西-欧冶户头 | AU14: 由台账 Excel 历史数据自动导入（8.19付款明细-欧冶物宝1.xlsx 第18行），日期为过磅日期近似值 [原货主:林凯]
A15: 13 | B15: 46261 | C15: 苏DFM060 | D15: 车 | E15: 配票/反向 | F15: 配票 | G15: 林凯 | H15: 林凯车队 | I15: 俊兴 | J15: 已开票 | K15: 34.3 | L15: 84206.5 | M15: =Q15+S15-AA15-AC15-AD15 | N15: =IF(K15=0,0,M15/K15) | O15: 0 | Q15: 0 | R15: 25 | S15: 857.5 | T15: 14 | U15: 72417.59 | V15: 23 | W15: 788.9 | X15: 83417.6 | Y15: 13.5 | Z15: 72156.224 | AA15: 261.366 | AB15: 5 | AC15: 171.5 | AD15: 0 | AF15: 我们配票（经俊兴） | AG15: 83417.6 | AH15: — | AI15: 按状态视为已完成(历史) | AJ15: 待登记 | AK15: — | AL15: 未开始(前一环节未完成) | AM15: 0 | AN15: 46261 | AO15: 2026-08 | AP15: 0.2 | AQ15: 台账历史数据-已出结算单（具体单号未录入） | AR15: 华西特钢 | AS15: 华西-欧冶户头 | AU15: 由台账 Excel 历史数据自动导入（8.19付款明细-欧冶物宝1.xlsx 第19行），日期为过磅日期近似值 [原货主:林凯]
A16: 14 | B16: 46261 | C16: 苏DBB772 | D16: 车 | E16: 配票/反向 | F16: 配票 | G16: 林凯 | H16: 君盛 | I16: 俊兴 | J16: 已开票 | K16: 66.22 | L16: 148332.8 | M16: =Q16+S16-AA16-AC16-AD16 | N16: =IF(K16=0,0,M16/K16) | O16: 0 | Q16: 0 | R16: 25 | S16: 1655.5 | T16: 14 | U16: 127566.21 | V16: 23 | W16: 1523.06 | X16: 146809.74 | Y16: 13.5 | Z16: 126990.43 | AA16: 575.7829 | AB16: 5 | AC16: 331.1 | AD16: 0 | AF16: 供货厂自带票（带票带货） | AG16: 146809.74 | AH16: — | AI16: 按状态视为已完成(历史) | AJ16: 待登记 | AK16: — | AL16: — | AM16: 0 | AN16: 46261 | AO16: 2026-08 | AP16: 1 | AQ16: 台账历史数据-已出结算单（具体单号未录入） | AR16: 华西特钢 | AS16: 华西-欧冶户头 | AU16: 由台账 Excel 历史数据自动导入（8.19付款明细-欧冶物宝1.xlsx 第21行），日期为过磅日期近似值 [原货主:林凯]
A17: 15 | B17: 46261 | C17: 苏BDK567 | D17: 车 | E17: 配票/反向 | F17: 配票 | G17: 林凯 | H17: 林凯车队 | I17: 俊兴 | J17: 已开票 | K17: 32.05 | L17: 78682.75 | M17: =Q17+S17-AA17-AC17-AD17 | N17: =IF(K17=0,0,M17/K17) | O17: 0 | Q17: 0 | R17: 25 | S17: 801.25 | T17: 14 | U17: 67667.165 | V17: 23 | W17: 737.15 | X17: 77945.6 | Y17: 13.5 | Z17: 67422.944 | AA17: 244.221 | AB17: 5 | AC17: 160.25 | AD17: 0 | AF17: 我们配票（经俊兴） | AG17: 77945.6 | AH17: — | AI17: 按状态视为已完成(历史) | AJ17: 待登记 | AK17: — | AL17: 未开始(前一环节未完成) | AM17: 0 | AN17: 46261 | AO17: 2026-08 | AP17: 0.25 | AQ17: 台账历史数据-已出结算单（具体单号未录入） | AR17: 华西特钢 | AS17: 华西-欧冶户头 | AU17: 由台账 Excel 历史数据自动导入（8.19付款明细-欧冶物宝1.xlsx 第22行），日期为过磅日期近似值 [原货主:林凯]
A18: 16 | B18: 46261 | C18: 苏BZP839 | D18: 车 | E18: 配票/反向 | F18: 配票 | G18: 林凯 | H18: 林凯车队 | I18: 俊兴 | J18: 已开票 | K18: 28.47 | L18: 68569.64 | M18: =Q18+S18-AA18-AC18-AD18 | N18: =IF(K18=0,0,M18/K18) | O18: 0 | Q18: 0 | R18: 25 | S18: 711.75 | T18: 14 | U18: 58969.89 | V18: 23 | W18: 654.81 | X18: 67914.83 | Y18: 13.5 | Z18: 58746.328 | AA18: 223.06245 | AB18: 5 | AC18: 142.35 | AD18: 100 | AF18: 我们配票（经俊兴） | AG18: 67914.83 | AH18: — | AI18: 按状态视为已完成(历史) | AJ18: 待登记 | AK18: — | AL18: 未开始(前一环节未完成) | AM18: 0 | AN18: 46261 | AO18: 2026-08 | AP18: 0.45 | AQ18: 台账历史数据-已出结算单（具体单号未录入） | AR18: 华西特钢 | AS18: 华西-欧冶户头 | AU18: 由台账 Excel 历史数据自动导入（8.19付款明细-欧冶物宝1.xlsx 第24行），日期为过磅日期近似值 [原货主:林凯]
A19: 17 | B19: 46261 | C19: 苏NEV615 | D19: 车 | E19: 配票/反向 | F19: 配票 | H19: 俊兴 | I19: 俊兴 | J19: 已开票 | K19: 38.78 | L19: 89969.6 | M19: =Q19+S19-AA19-AC19-AD19 | N19: =IF(K19=0,0,M19/K19) | O19: 0 | Q19: 0 | R19: 25 | S19: 969.5 | T19: 14 | U19: 77373.856 | V19: 23 | W19: 891.94 | X19: 89077.66 | Y19: 13.5 | Z19: 77052.176 | AA19: 321.6801 | AB19: 0 | AC19: 0 | AD19: 0 | AF19: 我们配票（经俊兴） | AG19: 89077.66 | AH19: — | AI19: 按状态视为已完成(历史) | AJ19: 待登记 | AK19: — | AL19: 未开始(前一环节未完成) | AM19: 0 | AN19: 46261 | AO19: 2026-08 | AP19: 0.5 | AQ19: 台账历史数据-已出结算单（具体单号未录入） | AR19: 华西特钢 | AS19: 华西-欧冶户头 | AU19: 由台账 Excel 历史数据自动导入（8.19付款明细-欧冶物宝1.xlsx 第26行），日期为过磅日期近似值
A20: 18 | B20: 46261 | C20: 苏ERS080 | D20: 车 | E20: 配票/反向 | F20: 配票 | G20: 林凯 | H20: 林凯车队 | I20: 俊兴 | J20: 已开票 | K20: 48.38 | L20: 116112 | M20: =Q20+S20-AA20-AC20-AD20 | N20: =IF(K20=0,0,M20/K20) | O20: 0 | Q20: 0 | R20: 25 | S20: 1209.5 | T20: 14 | U20: 99856.32 | V20: 23 | W20: 1112.74 | X20: 114999.26 | Y20: 13.5 | Z20: 99474.36 | AA20: 381.9601 | AB20: 5 | AC20: 241.9 | AD20: 0 | AF20: 我们配票（经俊兴） | AG20: 114999.26 | AH20: — | AI20: 按状态视为已完成(历史) | AJ20: 待登记 | AK20: — | AL20: 未开始(前一环节未完成) | AM20: 0 | AN20: 46261 | AO20: 2026-08 | AP20: 0.3 | AQ20: 台账历史数据-已出结算单（具体单号未录入） | AR20: 华西特钢 | AS20: 华西-欧冶户头 | AU20: 由台账 Excel 历史数据自动导入（8.19付款明细-欧冶物宝1.xlsx 第27行），日期为过磅日期近似值 [原货主:林凯]
A21: 19 | B21: 46261 | C21: 鲁济宁货4095 | D21: 船 | E21: 配票/反向 | F21: 配票 | H21: 俊兴 | I21: 俊兴 | J21: 已开票 | K21: 518.48 | L21: 1271259 | M21: =Q21+S21-AA21-AC21-AD21 | N21: =IF(K21=0,0,M21/K21) | O21: 0 | Q21: 0 | R21: 25 | S21: 12962 | T21: 14 | U21: 1093282.7 | V21: 23 | W21: 11925.04 | X21: 1259333.9 | Y21: 13.5 | Z21: 1089323.8 | AA21: 3958.8648 | AB21: 0 | AC21: 0 | AD21: 0 | AF21: 我们配票（经俊兴） | AG21: 1259333.9 | AH21: — | AI21: 按状态视为已完成(历史) | AJ21: 待登记 | AK21: — | AL21: 未开始(前一环节未完成) | AM21: 0 | AN21: 46261 | AO21: 2026-08 | AP21: 0 | AQ21: 台账历史数据-已出结算单（具体单号未录入） | AR21: 华西特钢 | AS21: 华西-欧冶户头 | AU21: 由台账 Excel 历史数据自动导入（8.19付款明细-欧冶物宝1.xlsx 第29行），日期为过磅日期近似值
A22: 20 | B22: 46262 | C22: 苏DBE075 | D22: 车 | E22: 配票/反向 | F22: 配票 | G22: 林凯 | H22: 林凯车队 | I22: 俊兴 | J22: 已开票 | K22: 38.2 | L22: 88624 | M22: =Q22+S22-AA22-AC22-AD22 | N22: =IF(K22=0,0,M22/K22) | O22: 0 | Q22: 0 | R22: 25 | S22: 955 | T22: 14 | U22: 76216.64 | V22: 23 | W22: 878.6 | X22: 87745.4 | Y22: 13.5 | Z22: 75899.771 | AA22: 316.869 | AB22: 5 | AC22: 191 | AD22: 0 | AF22: 我们配票（经俊兴） | AG22: 87745.4 | AH22: — | AI22: 按状态视为已完成(历史) | AJ22: 待登记 | AK22: — | AL22: 未开始(前一环节未完成) | AM22: 0 | AN22: 46262 | AO22: 2026-08 | AP22: 0.2 | AQ22: 台账历史数据-已出结算单（具体单号未录入） | AR22: 华西特钢 | AS22: 华西-欧冶户头 | AU22: 由台账 Excel 历史数据自动导入（8.19付款明细-欧冶物宝1.xlsx 第30行），日期为过磅日期近似值 [原货主:林凯]
A23: 21 | B23: 46262 | C23: 苏DBX137 | D23: 车 | E23: 配票/反向 | F23: 配票 | G23: 林凯 | H23: 林凯车队 | I23: 俊兴 | J23: 已开票 | K23: 18.52 | L23: 44448 | M23: =Q23+S23-AA23-AC23-AD23 | N23: =IF(K23=0,0,M23/K23) | O23: 0 | Q23: 0 | R23: 25 | S23: 463 | T23: 14 | U23: 38225.28 | V23: 23 | W23: 425.96 | X23: 44022.04 | Y23: 13.5 | Z23: 38079.065 | AA23: 146.2154 | AB23: 5 | AC23: 92.6 | AD23: 0 | AF23: 我们配票（经俊兴） | AG23: 44022.04 | AH23: — | AI23: 按状态视为已完成(历史) | AJ23: 待登记 | AK23: — | AL23: 未开始(前一环节未完成) | AM23: 0 | AN23: 46262 | AO23: 2026-08 | AP23: 0.3 | AQ23: 台账历史数据-已出结算单（具体单号未录入） | AR23: 华西特钢 | AS23: 华西-欧冶户头 | AU23: 由台账 Excel 历史数据自动导入（8.19付款明细-欧冶物宝1.xlsx 第31行），日期为过磅日期近似值 [原货主:林凯]
A24: 22 | B24: 46262 | C24: 苏DFB287 | D24: 车 | E24: 配票/反向 | F24: 配票 | G24: 林凯 | H24: 林凯车队 | I24: 俊兴 | J24: 已开票 | K24: 81.9 | L24: 191646 | M24: =Q24+S24-AA24-AC24-AD24 | N24: =IF(K24=0,0,M24/K24) | O24: 0 | Q24: 0 | R24: 25 | S24: 2047.5 | T24: 14 | U24: 164815.56 | V24: 23 | W24: 1883.7 | X24: 189762.3 | Y24: 13.5 | Z24: 164144.39 | AA24: 671.1705 | AB24: 5 | AC24: 409.5 | AD24: 0 | AF24: 我们配票（经俊兴） | AG24: 189762.3 | AH24: — | AI24: 按状态视为已完成(历史) | AJ24: 待登记 | AK24: — | AL24: 未开始(前一环节未完成) | AM24: 0 | AN24: 46262 | AO24: 2026-08 | AP24: 0.6 | AQ24: 台账历史数据-已出结算单（具体单号未录入） | AR24: 华西特钢 | AS24: 华西-欧冶户头 | AU24: 由台账 Excel 历史数据自动导入（8.19付款明细-欧冶物宝1.xlsx 第32行），日期为过磅日期近似值 [原货主:林凯]
A25: 23 | B25: 46262 | C25: 苏DFM060 | D25: 车 | E25: 配票/反向 | F25: 配票 | G25: 林凯 | H25: 林凯车队 | I25: 俊兴 | J25: 已开票 | K25: 55.18 | L25: 130224.8 | M25: =Q25+S25-AA25-AC25-AD25 | N25: =IF(K25=0,0,M25/K25) | O25: 0 | Q25: 0 | R25: 25 | S25: 1379.5 | T25: 14 | U25: 111993.33 | V25: 23 | W25: 1269.14 | X25: 128955.66 | Y25: 13.5 | Z25: 111546.65 | AA25: 446.6821 | AB25: 5 | AC25: 275.9 | AD25: 0 | AF25: 我们配票（经俊兴） | AG25: 128955.66 | AH25: — | AI25: 按状态视为已完成(历史) | AJ25: 待登记 | AK25: — | AL25: 未开始(前一环节未完成) | AM25: 0 | AN25: 46262 | AO25: 2026-08 | AP25: 0.5 | AQ25: 台账历史数据-已出结算单（具体单号未录入） | AR25: 华西特钢 | AS25: 华西-欧冶户头 | AU25: 由台账 Excel 历史数据自动导入（8.19付款明细-欧冶物宝1.xlsx 第34行），日期为过磅日期近似值 [原货主:林凯]
A26: 24 | B26: 46262 | C26: 苏DBB772 | D26: 车 | E26: 配票/反向 | F26: 配票 | G26: 林凯 | H26: 林凯车队 | I26: 俊兴 | J26: 已开票 | K26: 63.16 | L26: 153352.48 | M26: =Q26+S26-AA26-AC26-AD26 | N26: =IF(K26=0,0,M26/K26) | O26: 0 | Q26: 0 | R26: 25 | S26: 1579 | T26: 14 | U26: 131883.13 | V26: 23 | W26: 1452.68 | X26: 151899.8 | Y26: 13.5 | Z26: 131393.33 | AA26: 489.8058 | AB26: 5 | AC26: 315.8 | AD26: 0 | AF26: 我们配票（经俊兴） | AG26: 151899.8 | AH26: — | AI26: 按状态视为已完成(历史) | AJ26: 待登记 | AK26: — | AL26: 未开始(前一环节未完成) | AM26: 0 | AN26: 46262 | AO26: 2026-08 | AP26: 0.5 | AQ26: 台账历史数据-已出结算单（具体单号未录入） | AR26: 华西特钢 | AS26: 华西-欧冶户头 | AU26: 由台账 Excel 历史数据自动导入（8.19付款明细-欧冶物宝1.xlsx 第35行），日期为过磅日期近似值 [原货主:林凯]
A27: 25 | B27: 46262 | C27: 苏BDK567 | D27: 车 | E27: 配票/反向 | F27: 配票 | G27: 林凯 | H27: 林凯车队 | I27: 俊兴 | J27: 已开票 | K27: 34.22 | L27: 83496.8 | M27: =Q27+S27-AA27-AC27-AD27 | N27: =IF(K27=0,0,M27/K27) | O27: 0 | Q27: 0 | R27: 25 | S27: 855.5 | T27: 14 | U27: 71807.248 | V27: 23 | W27: 787.06 | X27: 82709.74 | Y27: 13.5 | Z27: 71543.925 | AA27: 263.3229 | AB27: 5 | AC27: 171.1 | AD27: 0 | AF27: 我们配票（经俊兴） | AG27: 82709.74 | AH27: — | AI27: 按状态视为已完成(历史) | AJ27: 待登记 | AK27: — | AL27: 未开始(前一环节未完成) | AM27: 0 | AN27: 46262 | AO27: 2026-08 | AP27: 0.3 | AQ27: 台账历史数据-已出结算单（具体单号未录入） | AR27: 华西特钢 | AS27: 华西-欧冶户头 | AU27: 由台账 Excel 历史数据自动导入（8.19付款明细-欧冶物宝1.xlsx 第37行），日期为过磅日期近似值 [原货主:林凯]
A28: 26 | B28: 46262 | C28: 苏BUK952 | D28: 车 | E28: 配票/反向 | F28: 配票 | G28: 林凯 | H28: 林凯车队 | I28: 俊兴 | J28: 已开票 | K28: 27.22 | L28: 66416.8 | M28: =Q28+S28-AA28-AC28-AD28 | N28: =IF(K28=0,0,M28/K28) | O28: 0 | Q28: 0 | R28: 25 | S28: 680.5 | T28: 14 | U28: 57118.448 | V28: 23 | W28: 626.06 | X28: 65790.74 | Y28: 13.5 | Z28: 56908.99 | AA28: 209.4579 | AB28: 5 | AC28: 136.1 | AD28: 0 | AF28: 我们配票（经俊兴） | AG28: 65790.74 | AH28: — | AI28: 按状态视为已完成(历史) | AJ28: 待登记 | AK28: — | AL28: 未开始(前一环节未完成) | AM28: 0 | AN28: 46262 | AO28: 2026-08 | AP28: 0.2 | AQ28: 台账历史数据-已出结算单（具体单号未录入） | AR28: 华西特钢 | AS28: 华西-欧冶户头 | AU28: 由台账 Excel 历史数据自动导入（8.19付款明细-欧冶物宝1.xlsx 第38行），日期为过磅日期近似值 [原货主:林凯]
A29: 27 | B29: 46262 | C29: 皖KQ1052 | D29: 车 | E29: 配票/反向 | F29: 配票 | H29: 俊兴 | I29: 俊兴 | J29: 已开票 | K29: 34.49 | L29: 80430.68 | M29: =Q29+S29-AA29-AC29-AD29 | N29: =IF(K29=0,0,M29/K29) | O29: 0 | Q29: 0 | R29: 25 | S29: 862.25 | T29: 14 | U29: 69170.385 | V29: 23 | W29: 793.27 | X29: 79637.41 | Y29: 13.5 | Z29: 68886.36 | AA29: 284.02515 | AB29: 0 | AC29: 0 | AD29: 0 | AF29: 我们配票（经俊兴） | AG29: 79637.41 | AH29: — | AI29: 按状态视为已完成(历史) | AJ29: 待登记 | AK29: — | AL29: 未开始(前一环节未完成) | AM29: 0 | AN29: 46262 | AO29: 2026-08 | AP29: 0.35 | AQ29: 台账历史数据-已出结算单（具体单号未录入） | AR29: 华西特钢 | AS29: 华西-欧冶户头 | AU29: 由台账 Excel 历史数据自动导入（8.19付款明细-欧冶物宝1.xlsx 第39行），日期为过磅日期近似值
A30: 28 | B30: 46262 | C30: 苏DBE075 | D30: 车 | E30: 配票/反向 | F30: 配票 | G30: 林凯 | H30: 林凯车队 | I30: 俊兴 | J30: 已开票 | K30: 67.8 | L30: 151872 | M30: =Q30+S30-AA30-AC30-AD30 | N30: =IF(K30=0,0,M30/K30) | O30: 0 | Q30: 0 | R30: 25 | S30: 1695 | T30: 14 | U30: 130609.92 | V30: 23 | W30: 1559.4 | X30: 150312.6 | Y30: 13.5 | Z30: 130020.4 | AA30: 589.521 | AB30: 5 | AC30: 339 | AD30: 0 | AF30: 我们配票（经俊兴） | AG30: 150312.6 | AH30: — | AI30: 按状态视为已完成(历史) | AJ30: 待登记 | AK30: — | AL30: 未开始(前一环节未完成) | AM30: 0 | AN30: 46262 | AO30: 2026-08 | AP30: 1.9 | AQ30: 台账历史数据-已出结算单（具体单号未录入） | AR30: 华西特钢 | AS30: 华西-欧冶户头 | AU30: 由台账 Excel 历史数据自动导入（8.19付款明细-欧冶物宝1.xlsx 第41行），日期为过磅日期近似值 [原货主:林凯]
A31: 29 | B31: 46262 | C31: 冀A224E6 | D31: 车 | E31: 配票/反向 | F31: 配票 | G31: 林凯 | H31: 林凯车队 | I31: 俊兴 | J31: 已开票 | K31: 29 | L31: 71369 | M31: =Q31+S31-AA31-AC31-AD31 | N31: =IF(K31=0,0,M31/K31) | O31: 0 | Q31: 0 | R31: 25 | S31: 725 | T31: 14 | U31: 61377.34 | V31: 23 | W31: 667 | X31: 70702 | Y31: 13.5 | Z31: 61157.23 | AA31: 220.11 | AB31: 5 | AC31: 145 | AD31: 0 | AF31: 我们配票（经俊兴） | AG31: 70702 | AH31: — | AI31: 按状态视为已完成(历史) | AJ31: 待登记 | AK31: — | AL31: 未开始(前一环节未完成) | AM31: 0 | AN31: 46262 | AO31: 2026-08 | AP31: 0.4 | AQ31: 台账历史数据-已出结算单（具体单号未录入） | AR31: 华西特钢 | AS31: 华西-欧冶户头 | AU31: 由台账 Excel 历史数据自动导入（8.19付款明细-欧冶物宝1.xlsx 第42行），日期为过磅日期近似值 [原货主:林凯]
A32: 30 | B32: 46262 | C32: 苏BWX568 | D32: 车 | E32: 配票/反向 | F32: 配票 | G32: 林凯 | H32: 林凯车队 | I32: 俊兴 | J32: 已开票 | K32: 32.52 | L32: 78048 | M32: =Q32+S32-AA32-AC32-AD32 | N32: =IF(K32=0,0,M32/K32) | O32: 0 | Q32: 0 | R32: 25 | S32: 813 | T32: 14 | U32: 67121.28 | V32: 23 | W32: 747.96 | X32: 77300.04 | Y32: 13.5 | Z32: 66864.535 | AA32: 256.7454 | AB32: 5 | AC32: 162.6 | AD32: 0 | AF32: 我们配票（经俊兴） | AG32: 77300.04 | AH32: — | AI32: 按状态视为已完成(历史) | AJ32: 待登记 | AK32: — | AL32: 未开始(前一环节未完成) | AM32: 0 | AN32: 46262 | AO32: 2026-08 | AP32: 0.7 | AQ32: 台账历史数据-已出结算单（具体单号未录入） | AR32: 华西特钢 | AS32: 华西-欧冶户头 | AU32: 由台账 Excel 历史数据自动导入（8.19付款明细-欧冶物宝1.xlsx 第44行），日期为过磅日期近似值 [原货主:林凯]
A33: 31 | B33: 46263 | C33: 苏DBB772 | D33: 车 | E33: 配票/反向 | F33: 配票 | G33: 林凯 | H33: 林凯车队 | I33: 俊兴 | J33: 已开票 | K33: 81.36 | L33: 204213.6 | M33: =Q33+S33-AA33-AC33-AD33 | N33: =IF(K33=0,0,M33/K33) | O33: 0 | Q33: 0 | R33: 25 | S33: 2034 | T33: 14 | U33: 175623.7 | V33: 23 | W33: 1871.28 | X33: 202342.32 | Y33: 13.5 | Z33: 175026.11 | AA33: 597.5892 | AB33: 5 | AC33: 406.8 | AD33: 0 | AF33: 我们配票（经俊兴） | AG33: 202342.32 | AH33: — | AI33: 按状态视为已完成(历史) | AJ33: 待登记 | AK33: — | AL33: 未开始(前一环节未完成) | AM33: 0 | AN33: 46263 | AO33: 2026-08 | AP33: 0.7 | AQ33: 台账历史数据-已出结算单（具体单号未录入） | AR33: 华西特钢 | AS33: 华西-欧冶户头 | AU33: 由台账 Excel 历史数据自动导入（8.19付款明细-欧冶物宝1.xlsx 第45行），日期为过磅日期近似值 [原货主:林凯]
A34: 32 | B34: 46263 | C34: 苏ERS080 | D34: 车 | E34: 配票/反向 | F34: 配票 | G34: 林凯 | H34: 林凯车队 | I34: 俊兴 | J34: 已开票 | K34: 48.75 | L34: 117000 | M34: =Q34+S34-AA34-AC34-AD34 | N34: =IF(K34=0,0,M34/K34) | O34: 0 | Q34: 0 | R34: 25 | S34: 1218.75 | T34: 14 | U34: 100620 | V34: 23 | W34: 1121.25 | X34: 115878.75 | Y34: 13.5 | Z34: 100235.12 | AA34: 384.88125 | AB34: 5 | AC34: 243.75 | AD34: 0 | AF34: 我们配票（经俊兴） | AG34: 115878.75 | AH34: — | AI34: 按状态视为已完成(历史) | AJ34: 待登记 | AK34: — | AL34: 未开始(前一环节未完成) | AM34: 0 | AN34: 46263 | AO34: 2026-08 | AP34: 0.45 | AQ34: 台账历史数据-已出结算单（具体单号未录入） | AR34: 华西特钢 | AS34: 华西-欧冶户头 | AU34: 由台账 Excel 历史数据自动导入（8.19付款明细-欧冶物宝1.xlsx 第46行），日期为过磅日期近似值 [原货主:林凯]
A35: 33 | B35: 46263 | C35: 苏DBE075 | D35: 车 | E35: 配票/反向 | F35: 配票 | G35: 林凯 | H35: 林凯车队 | I35: 俊兴 | J35: 已开票 | K35: 79.68 | L35: 199996.8 | M35: =Q35+S35-AA35-AC35-AD35 | N35: =IF(K35=0,0,M35/K35) | O35: 0 | Q35: 0 | R35: 25 | S35: 1992 | T35: 14 | U35: 171997.25 | V35: 23 | W35: 1832.64 | X35: 198164.16 | Y35: 13.5 | Z35: 171412 | AA35: 585.2496 | AB35: 5 | AC35: 398.4 | AD35: 0 | AF35: 我们配票（经俊兴） | AG35: 198164.16 | AH35: — | AI35: 按状态视为已完成(历史) | AJ35: 待登记 | AK35: — | AL35: 未开始(前一环节未完成) | AM35: 0 | AN35: 46263 | AO35: 2026-08 | AP35: 0.7 | AQ35: 台账历史数据-已出结算单（具体单号未录入） | AR35: 华西特钢 | AS35: 华西-欧冶户头 | AU35: 由台账 Excel 历史数据自动导入（8.19付款明细-欧冶物宝1.xlsx 第47行），日期为过磅日期近似值 [原货主:林凯]
A36: 34 | B36: 46263 | C36: 冀A224E6 | D36: 车 | E36: 配票/反向 | F36: 配票 | H36: 俊兴 | I36: 俊兴 | J36: 已开票 | K36: 20 | L36: 48800 | M36: =Q36+S36-AA36-AC36-AD36 | N36: =IF(K36=0,0,M36/K36) | O36: 0 | Q36: 0 | R36: 25 | S36: 500 | T36: 14 | U36: 41968 | V36: 23 | W36: 460 | X36: 48340 | Y36: 13.5 | Z36: 41814.1 | AA36: 153.9 | AB36: 0 | AC36: 0 | AD36: 0 | AF36: 我们配票（经俊兴） | AG36: 48340 | AH36: — | AI36: 按状态视为已完成(历史) | AJ36: 待登记 | AK36: — | AL36: 未开始(前一环节未完成) | AM36: 0 | AN36: 46263 | AO36: 2026-08 | AP36: 0.4 | AQ36: 台账历史数据-已出结算单（具体单号未录入） | AR36: 华西特钢 | AS36: 华西-欧冶户头 | AU36: 由台账 Excel 历史数据自动导入（8.19付款明细-欧冶物宝1.xlsx 第48行），日期为过磅日期近似值
A37: 35 | B37: 46263 | C37: 苏AE8896 | D37: 车 | E37: 配票/反向 | F37: 配票 | H37: 俊兴 | I37: 俊兴 | J37: 已开票 | K37: 39.96 | L37: 93186.72 | M37: =Q37+S37-AA37-AC37-AD37 | N37: =IF(K37=0,0,M37/K37) | O37: 0 | Q37: 0 | R37: 25 | S37: 999 | T37: 14 | U37: 80140.579 | V37: 23 | W37: 919.08 | X37: 92267.64 | Y37: 13.5 | Z37: 79811.509 | AA37: 329.0706 | AB37: 0 | AC37: 0 | AD37: 0 | AF37: 我们配票（经俊兴） | AG37: 92267.64 | AH37: — | AI37: 按状态视为已完成(历史) | AJ37: 待登记 | AK37: — | AL37: 未开始(前一环节未完成) | AM37: 0 | AN37: 46263 | AO37: 2026-08 | AP37: 0.4 | AQ37: 台账历史数据-已出结算单（具体单号未录入） | AR37: 华西特钢 | AS37: 华西-欧冶户头 | AU37: 由台账 Excel 历史数据自动导入（8.19付款明细-欧冶物宝1.xlsx 第49行），日期为过磅日期近似值
A38: 36 | B38: 46263 | C38: 苏DBB772 | D38: 车 | E38: 配票/反向 | F38: 配票 | G38: 林凯 | H38: 林凯车队 | I38: 俊兴 | J38: 已开票 | K38: 66.06 | L38: 147974.4 | M38: =Q38+S38-AA38-AC38-AD38 | N38: =IF(K38=0,0,M38/K38) | O38: 0 | Q38: 0 | R38: 25 | S38: 1651.5 | T38: 14 | U38: 127257.98 | V38: 23 | W38: 1519.38 | X38: 146455.02 | Y38: 13.5 | Z38: 126683.59 | AA38: 574.3917 | AB38: 5 | AC38: 330.3 | AD38: 0 | AF38: 我们配票（经俊兴） | AG38: 146455.02 | AH38: — | AI38: 按状态视为已完成(历史) | AJ38: 待登记 | AK38: — | AL38: 未开始(前一环节未完成) | AM38: 0 | AN38: 46263 | AO38: 2026-08 | AP38: 0.6 | AQ38: 台账历史数据-已出结算单（具体单号未录入） | AR38: 华西特钢 | AS38: 华西-欧冶户头 | AU38: 由台账 Excel 历史数据自动导入（8.19付款明细-欧冶物宝1.xlsx 第51行），日期为过磅日期近似值 [原货主:林凯]
A39: 37 | B39: 46264 | C39: 苏DBE075 | D39: 车 | E39: 配票/反向 | F39: 配票 | G39: 林凯 | H39: 林凯车队 | I39: 俊兴 | J39: 已开票 | K39: 81.92 | L39: 205619.2 | M39: =Q39+S39-AA39-AC39-AD39 | N39: =IF(K39=0,0,M39/K39) | O39: 0 | Q39: 0 | R39: 25 | S39: 2048 | T39: 14 | U39: 176832.51 | V39: 23 | W39: 1884.16 | X39: 203735.04 | Y39: 13.5 | Z39: 176230.81 | AA39: 601.7024 | AB39: 5 | AC39: 409.6 | AD39: 0 | AF39: 我们配票（经俊兴） | AG39: 203735.04 | AH39: — | AI39: 按状态视为已完成(历史) | AJ39: 待登记 | AK39: — | AL39: 未开始(前一环节未完成) | AM39: 0 | AN39: 46264 | AO39: 2026-08 | AP39: 0.8 | AQ39: 台账历史数据-已出结算单（具体单号未录入） | AR39: 华西特钢 | AS39: 华西-欧冶户头 | AU39: 由台账 Excel 历史数据自动导入（8.19付款明细-欧冶物宝1.xlsx 第52行），日期为过磅日期近似值 [原货主:林凯]
A40: 38 | B40: 46264 | C40: 苏DBE961 | D40: 车 | E40: 配票/反向 | F40: 配票 | H40: 俊兴 | I40: 俊兴 | J40: 已开票 | K40: 78.64 | L40: 181501.12 | M40: =Q40+S40-AA40-AC40-AD40 | N40: =IF(K40=0,0,M40/K40) | O40: 0 | Q40: 0 | R40: 25 | S40: 1966 | T40: 14 | U40: 156090.96 | V40: 23 | W40: 1808.72 | X40: 179692.4 | Y40: 13.5 | Z40: 155433.93 | AA40: 657.0372 | AB40: 0 | AC40: 0 | AD40: 0 | AF40: 我们配票（经俊兴） | AG40: 179692.4 | AH40: — | AI40: 按状态视为已完成(历史) | AJ40: 待登记 | AK40: — | AL40: 未开始(前一环节未完成) | AM40: 0 | AN40: 46264 | AO40: 2026-08 | AP40: 0.6 | AQ40: 台账历史数据-已出结算单（具体单号未录入） | AR40: 华西特钢 | AS40: 华西-欧冶户头 | AU40: 由台账 Excel 历史数据自动导入（8.19付款明细-欧冶物宝1.xlsx 第53行），日期为过磅日期近似值
A41: 39 | B41: 46264 | C41: 苏DFB287 | D41: 车 | E41: 配票/反向 | F41: 配票 | H41: 俊兴 | I41: 俊兴 | J41: 已开票 | K41: 83.26 | L41: 192164.08 | M41: =Q41+S41-AA41-AC41-AD41 | N41: =IF(K41=0,0,M41/K41) | O41: 0 | Q41: 0 | R41: 25 | S41: 2081.5 | T41: 14 | U41: 165261.11 | V41: 23 | W41: 1914.98 | X41: 190249.1 | Y41: 13.5 | Z41: 164565.47 | AA41: 695.6373 | AB41: 0 | AC41: 0 | AD41: 0 | AF41: 我们配票（经俊兴） | AG41: 190249.1 | AH41: — | AI41: 按状态视为已完成(历史) | AJ41: 待登记 | AK41: — | AL41: 未开始(前一环节未完成) | AM41: 0 | AN41: 46264 | AO41: 2026-08 | AP41: 0.6 | AQ41: 台账历史数据-已出结算单（具体单号未录入） | AR41: 华西特钢 | AS41: 华西-欧冶户头 | AU41: 由台账 Excel 历史数据自动导入（8.19付款明细-欧冶物宝1.xlsx 第55行），日期为过磅日期近似值
A42: 40 | B42: 46264 | C42: 苏BTQ938 | D42: 车 | E42: 配票/反向 | F42: 配票 | G42: 李涛 | H42: 李涛车队 | I42: 俊兴 | J42: 已开票 | K42: 32.42 | L42: 77808 | M42: =Q42+S42-AA42-AC42-AD42 | N42: =IF(K42=0,0,M42/K42) | O42: 0 | Q42: 0 | R42: 25 | S42: 810.5 | T42: 14 | U42: 66914.88 | V42: 23 | W42: 745.66 | X42: 77062.34 | Y42: 13.5 | Z42: 66658.924 | AA42: 255.9559 | AB42: 0 | AC42: 0 | AD42: 0 | AF42: 我们配票（经俊兴） | AG42: 77062.34 | AH42: — | AI42: 按状态视为已完成(历史) | AJ42: 待登记 | AK42: — | AL42: 未开始(前一环节未完成) | AM42: 0 | AN42: 46264 | AO42: 2026-08 | AP42: 0.5 | AQ42: 台账历史数据-已出结算单（具体单号未录入） | AR42: 华西特钢 | AS42: 华西-欧冶户头 | AU42: 由台账 Excel 历史数据自动导入（8.19付款明细-欧冶物宝1.xlsx 第57行），日期为过磅日期近似值 [原货主:李涛]
A43: 41 | B43: 46264 | C43: 皖SB2849 | D43: 车 | E43: 配票/反向 | F43: 配票 | G43: 林凯 | H43: 林凯车队 | I43: 俊兴 | J43: 已开票 | K43: 43.34 | L43: 101068.88 | M43: =Q43+S43-AA43-AC43-AD43 | N43: =IF(K43=0,0,M43/K43) | O43: 0 | Q43: 0 | R43: 25 | S43: 1083.5 | T43: 14 | U43: 86919.237 | V43: 23 | W43: 996.82 | X43: 100072.06 | Y43: 13.5 | Z43: 86562.332 | AA43: 356.9049 | AB43: 5 | AC43: 216.7 | AD43: 0 | AF43: 我们配票（经俊兴） | AG43: 100072.06 | AH43: — | AI43: 按状态视为已完成(历史) | AJ43: 待登记 | AK43: — | AL43: 未开始(前一环节未完成) | AM43: 0 | AN43: 46264 | AO43: 2026-08 | AP43: 0.9 | AQ43: 台账历史数据-已出结算单（具体单号未录入） | AR43: 华西特钢 | AS43: 华西-欧冶户头 | AU43: 由台账 Excel 历史数据自动导入（8.19付款明细-欧冶物宝1.xlsx 第58行），日期为过磅日期近似值 [原货主:林凯]
A44: 42 | B44: 46264 | C44: 苏DBB772 | D44: 车 | E44: 配票/反向 | F44: 配票 | G44: 林凯 | H44: 林凯车队 | I44: 俊兴 | J44: 已开票 | K44: 83.78 | L44: 211125.6 | M44: =Q44+S44-AA44-AC44-AD44 | N44: =IF(K44=0,0,M44/K44) | O44: 0 | Q44: 0 | R44: 25 | S44: 2094.5 | T44: 14 | U44: 181568.02 | V44: 23 | W44: 1926.94 | X44: 209198.66 | Y44: 13.5 | Z44: 180956.84 | AA44: 611.1751 | AB44: 5 | AC44: 418.9 | AD44: 0 | AF44: 我们配票（经俊兴） | AG44: 209198.66 | AH44: — | AI44: 按状态视为已完成(历史) | AJ44: 待登记 | AK44: — | AL44: 未开始(前一环节未完成) | AM44: 0 | AN44: 46264 | AO44: 2026-08 | AP44: 0.4 | AQ44: 台账历史数据-已出结算单（具体单号未录入） | AR44: 华西特钢 | AS44: 华西-欧冶户头 | AU44: 由台账 Excel 历史数据自动导入（8.19付款明细-欧冶物宝1.xlsx 第60行），日期为过磅日期近似值 [原货主:林凯]
A45: 43 | B45: 46264 | C45: 冀A224E6 | D45: 车 | E45: 配票/反向 | F45: 配票 | H45: 俊兴 | I45: 俊兴 | J45: 已开票 | K45: 46.28 | L45: 107924.96 | M45: =Q45+S45-AA45-AC45-AD45 | N45: =IF(K45=0,0,M45/K45) | O45: 0 | Q45: 0 | R45: 25 | S45: 1157 | T45: 14 | U45: 92815.466 | V45: 23 | W45: 1064.44 | X45: 106860.52 | Y45: 13.5 | Z45: 92434.35 | AA45: 381.1158 | AB45: 0 | AC45: 0 | AD45: 0 | AF45: 我们配票（经俊兴） | AG45: 106860.52 | AH45: — | AI45: 按状态视为已完成(历史) | AJ45: 待登记 | AK45: — | AL45: 未开始(前一环节未完成) | AM45: 0 | AN45: 46264 | AO45: 2026-08 | AP45: 0.5 | AQ45: 台账历史数据-已出结算单（具体单号未录入） | AR45: 华西特钢 | AS45: 华西-欧冶户头 | AU45: 由台账 Excel 历史数据自动导入（8.19付款明细-欧冶物宝1.xlsx 第61行），日期为过磅日期近似值
A46: 44 | B46: 46264 | C46: 苏DBB772 | D46: 车 | E46: 配票/反向 | F46: 配票 | G46: 林凯 | H46: 林凯车队 | I46: 俊兴 | J46: 已开票 | K46: 67.96 | L46: 152230.4 | M46: =Q46+S46-AA46-AC46-AD46 | N46: =IF(K46=0,0,M46/K46) | O46: 0 | Q46: 0 | R46: 25 | S46: 1699 | T46: 14 | U46: 130918.14 | V46: 23 | W46: 1563.08 | X46: 150667.32 | Y46: 13.5 | Z46: 130327.23 | AA46: 590.9122 | AB46: 5 | AC46: 339.8 | AD46: 0 | AF46: 我们配票（经俊兴） | AG46: 150667.32 | AH46: — | AI46: 按状态视为已完成(历史) | AJ46: 待登记 | AK46: — | AL46: 未开始(前一环节未完成) | AM46: 0 | AN46: 46264 | AO46: 2026-08 | AP46: 0.7 | AQ46: 台账历史数据-已出结算单（具体单号未录入） | AR46: 华西特钢 | AS46: 华西-欧冶户头 | AU46: 由台账 Excel 历史数据自动导入（8.19付款明细-欧冶物宝1.xlsx 第63行），日期为过磅日期近似值 [原货主:林凯]
A47: 45 | B47: 46265 | C47: 苏DFM060 | D47: 车 | E47: 配票/反向 | F47: 配票 | G47: 林凯 | H47: 林凯车队 | I47: 益周 | J47: 已开票 | K47: 25.12 | L47: 60288 | M47: =Q47+S47-AA47-AC47-AD47 | N47: =IF(K47=0,0,M47/K47) | O47: 417.97168 | Q47: 0 | R47: 25 | S47: 628 | T47: 14 | U47: 51847.68 | V47: 23 | W47: 577.76 | X47: 59710.24 | Y47: 13.5 | Z47: 51649.358 | AA47: 198.3224 | AB47: 5 | AC47: 125.6 | AD47: 0 | AF47: 我们配票（经俊兴） | AG47: 59710.24 | AH47: 按状态视为已完成(历史) | AI47: 按状态视为已完成(历史) | AJ47: 待登记 | AK47: 未开始(前一环节未完成) | AL47: 未开始(前一环节未完成) | AM47: 0 | AN47: 46265 | AO47: 2026-08 | AP47: 0.5 | AQ47: 台账历史数据-已出结算单（具体单号未录入） | AR47: 华西特钢 | AS47: 华西-欧冶户头 | AU47: 由台账 Excel 历史数据自动导入（8.19付款明细-欧冶物宝1.xlsx 第64行），日期为过磅日期近似值 [原货主:林凯]
A48: 46 | B48: 46265 | C48: 冀A224E6 | D48: 车 | E48: 配票/反向 | F48: 配票 | G48: 林凯 | H48: 林凯车队 | I48: 益周 | J48: 已开票 | K48: 29.08 | L48: 71216.92 | M48: =Q48+S48-AA48-AC48-AD48 | N48: =IF(K48=0,0,M48/K48) | O48: 493.83656 | Q48: 0 | R48: 25 | S48: 727 | T48: 14 | U48: 61246.551 | V48: 23 | W48: 668.84 | X48: 70548.08 | Y48: 13.5 | Z48: 61024.089 | AA48: 222.462 | AB48: 5 | AC48: 145.4 | AD48: 0 | AF48: 我们配票（经俊兴） | AG48: 70548.08 | AH48: 按状态视为已完成(历史) | AI48: 按状态视为已完成(历史) | AJ48: 待登记 | AK48: 未开始(前一环节未完成) | AL48: 未开始(前一环节未完成) | AM48: 0 | AN48: 46265 | AO48: 2026-08 | AP48: 0.2 | AQ48: 台账历史数据-已出结算单（具体单号未录入） | AR48: 华西特钢 | AS48: 华西-欧冶户头 | AU48: 由台账 Excel 历史数据自动导入（8.19付款明细-欧冶物宝1.xlsx 第65行），日期为过磅日期近似值 [原货主:林凯]
A49: 47 | B49: 46265 | C49: 苏DFM060 | D49: 车 | E49: 配票/反向 | F49: 配票 | G49: 林凯 | H49: 林凯车队 | I49: 益周 | J49: 已开票 | K49: 56.78 | L49: 137407.6 | M49: =Q49+S49-AA49-AC49-AD49 | N49: =IF(K49=0,0,M49/K49) | O49: 952.71162 | Q49: 0 | R49: 25 | S49: 1419.5 | T49: 14 | U49: 118170.54 | V49: 23 | W49: 1305.94 | X49: 136101.66 | Y49: 13.5 | Z49: 117727.94 | AA49: 442.6001 | AB49: 5 | AC49: 283.9 | AD49: 0 | AF49: 我们配票（经俊兴） | AG49: 136101.66 | AH49: 按状态视为已完成(历史) | AI49: 按状态视为已完成(历史) | AJ49: 待登记 | AK49: 未开始(前一环节未完成) | AL49: 未开始(前一环节未完成) | AM49: 0 | AN49: 46265 | AO49: 2026-08 | AP49: 0.5 | AQ49: 台账历史数据-已出结算单（具体单号未录入） | AR49: 华西特钢 | AS49: 华西-欧冶户头 | AU49: 由台账 Excel 历史数据自动导入（8.19付款明细-欧冶物宝1.xlsx 第67行），日期为过磅日期近似值 [原货主:林凯]
A50: 48 | B50: 46265 | C50: 苏DBB772 | D50: 车 | E50: 配票/反向 | F50: 配票 | G50: 林凯 | H50: 林凯车队 | I50: 益周 | J50: 已开票 | K50: 80.96 | L50: 203209.6 | M50: =Q50+S50-AA50-AC50-AD50 | N50: =IF(K50=0,0,M50/K50) | O50: 1409.4326 | Q50: 0 | R50: 25 | S50: 2024 | T50: 14 | U50: 174760.26 | V50: 23 | W50: 1862.08 | X50: 201347.52 | Y50: 13.5 | Z50: 174165.6 | AA50: 594.6512 | AB50: 5 | AC50: 404.8 | AD50: 0 | AF50: 我们配票（经俊兴） | AG50: 201347.52 | AH50: 按状态视为已完成(历史) | AI50: 按状态视为已完成(历史) | AJ50: 待登记 | AK50: 未开始(前一环节未完成) | AL50: 未开始(前一环节未完成) | AM50: 0 | AN50: 46265 | AO50: 2026-08 | AP50: 0.8 | AQ50: 台账历史数据-已出结算单（具体单号未录入） | AR50: 华西特钢 | AS50: 华西-欧冶户头 | AU50: 由台账 Excel 历史数据自动导入（8.19付款明细-欧冶物宝1.xlsx 第69行），日期为过磅日期近似值 [原货主:林凯]
A51: 49 | B51: 46265 | C51: 苏DBB772 | D51: 车 | E51: 配票/反向 | F51: 配票 | G51: 林凯 | H51: 林凯车队 | I51: 益周 | J51: 已开票 | K51: 69.66 | L51: 156038.4 | M51: =Q51+S51-AA51-AC51-AD51 | N51: =IF(K51=0,0,M51/K51) | O51: 1081.0535 | Q51: 0 | R51: 25 | S51: 1741.5 | T51: 14 | U51: 134193.02 | V51: 23 | W51: 1602.18 | X51: 154436.22 | Y51: 13.5 | Z51: 133587.33 | AA51: 605.6937 | AB51: 5 | AC51: 348.3 | AD51: 0 | AF51: 我们配票（经俊兴） | AG51: 154436.22 | AH51: 按状态视为已完成(历史) | AI51: 按状态视为已完成(历史) | AJ51: 待登记 | AK51: 未开始(前一环节未完成) | AL51: 未开始(前一环节未完成) | AM51: 0 | AN51: 46265 | AO51: 2026-08 | AP51: 1.4 | AQ51: 台账历史数据-已出结算单（具体单号未录入） | AR51: 华西特钢 | AS51: 华西-欧冶户头 | AU51: 由台账 Excel 历史数据自动导入（8.19付款明细-欧冶物宝1.xlsx 第70行），日期为过磅日期近似值 [原货主:林凯]
A52: 50 | B52: 46266 | C52: 苏ERS080 | D52: 车 | E52: 配票/反向 | F52: 配票 | G52: 林凯 | H52: 林凯车队 | I52: 益周 | J52: 已开票 | K52: 49.1 | L52: 117840 | M52: =Q52+S52-AA52-AC52-AD52 | N52: =IF(K52=0,0,M52/K52) | O52: 816.9749 | Q52: 0 | R52: 25 | S52: 1227.5 | T52: 14 | U52: 101342.4 | V52: 23 | W52: 1129.3 | X52: 116710.7 | Y52: 13.5 | Z52: 100954.76 | AA52: 387.6445 | AB52: 5 | AC52: 245.5 | AD52: 0 | AF52: 我们配票（经俊兴） | AG52: 116710.7 | AH52: 按状态视为已完成(历史) | AI52: 按状态视为已完成(历史) | AJ52: 待登记 | AK52: 未开始(前一环节未完成) | AL52: 未开始(前一环节未完成) | AM52: 0 | AN52: 46266 | AO52: 2026-09 | AP52: 0.4 | AQ52: 台账历史数据-已出结算单（具体单号未录入） | AR52: 华西特钢 | AS52: 华西-欧冶户头 | AU52: 由台账 Excel 历史数据自动导入（8.19付款明细-欧冶物宝1.xlsx 第71行），日期为过磅日期近似值 [原货主:林凯]
A53: 51 | B53: 46266 | C53: 苏DFM060 | D53: 车 | E53: 配票/反向 | F53: 配票 | G53: 林凯 | H53: 林凯车队 | I53: 益周 | J53: 已开票 | K53: 25.96 | L53: 61265.6 | M53: =Q53+S53-AA53-AC53-AD53 | N53: =IF(K53=0,0,M53/K53) | O53: 424.67964 | Q53: 0 | R53: 25 | S53: 649 | T53: 14 | U53: 52688.416 | V53: 23 | W53: 597.08 | X53: 60668.52 | Y53: 13.5 | Z53: 52478.27 | AA53: 210.1462 | AB53: 5 | AC53: 129.8 | AD53: 0 | AF53: 我们配票（经俊兴） | AG53: 60668.52 | AH53: 按状态视为已完成(历史) | AI53: 按状态视为已完成(历史) | AJ53: 待登记 | AK53: 未开始(前一环节未完成) | AL53: 未开始(前一环节未完成) | AM53: 0 | AN53: 46266 | AO53: 2026-09 | AP53: 0.3 | AQ53: 台账历史数据-已出结算单（具体单号未录入） | AR53: 华西特钢 | AS53: 华西-欧冶户头 | AU53: 由台账 Excel 历史数据自动导入（8.19付款明细-欧冶物宝1.xlsx 第72行），日期为过磅日期近似值 [原货主:林凯]
A54: 52 | B54: 46266 | C54: 苏DBX137 | D54: 车 | E54: 配票/反向 | F54: 配票 | G54: 林凯 | H54: 林凯车队 | I54: 益周 | J54: 已开票 | K54: 47.51 | L54: 110793.32 | M54: =Q54+S54-AA54-AC54-AD54 | N54: =IF(K54=0,0,M54/K54) | O54: 767.90413 | Q54: 0 | R54: 25 | S54: 1187.75 | T54: 14 | U54: 95282.255 | V54: 23 | W54: 1092.73 | X54: 109700.59 | Y54: 13.5 | Z54: 94891.01 | AA54: 391.24485 | AB54: 5 | AC54: 237.55 | AD54: 0 | AF54: 我们配票（经俊兴） | AG54: 109700.59 | AH54: 按状态视为已完成(历史) | AI54: 按状态视为已完成(历史) | AJ54: 待登记 | AK54: 未开始(前一环节未完成) | AL54: 未开始(前一环节未完成) | AM54: 0 | AN54: 46266 | AO54: 2026-09 | AP54: 0.35 | AQ54: 台账历史数据-已出结算单（具体单号未录入） | AR54: 华西特钢 | AS54: 华西-欧冶户头 | AU54: 由台账 Excel 历史数据自动导入（8.19付款明细-欧冶物宝1.xlsx 第74行），日期为过磅日期近似值 [原货主:林凯]
A55: 53 | B55: 46266 | C55: 苏DBB772 | D55: 车 | E55: 配票/反向 | F55: 配票 | G55: 林凯 | H55: 林凯车队 | I55: 益周 | J55: 已开票 | K55: 70.76 | L55: 158502.4 | M55: =Q55+S55-AA55-AC55-AD55 | N55: =IF(K55=0,0,M55/K55) | O55: 1098.1244 | Q55: 0 | R55: 25 | S55: 1769 | T55: 14 | U55: 136312.06 | V55: 23 | W55: 1627.48 | X55: 156874.92 | Y55: 13.5 | Z55: 135696.81 | AA55: 615.2582 | AB55: 5 | AC55: 353.8 | AD55: 0 | AF55: 我们配票（经俊兴） | AG55: 156874.92 | AH55: 按状态视为已完成(历史) | AI55: 按状态视为已完成(历史) | AJ55: 待登记 | AK55: 未开始(前一环节未完成) | AL55: 未开始(前一环节未完成) | AM55: 0 | AN55: 46266 | AO55: 2026-09 | AP55: 1.4 | AQ55: 台账历史数据-已出结算单（具体单号未录入） | AR55: 华西特钢 | AS55: 华西-欧冶户头 | AU55: 由台账 Excel 历史数据自动导入（8.19付款明细-欧冶物宝1.xlsx 第76行），日期为过磅日期近似值 [原货主:林凯]
A56: 54 | B56: 46266 | C56: 通海机9998 | D56: 船 | E56: 配票/反向 | F56: 配票 | H56: 俊兴 | I56: 俊兴 | J56: 已开票 | K56: 481.77 | L56: 1181813.6 | M56: =Q56+S56-AA56-AC56-AD56 | N56: =IF(K56=0,0,M56/K56) | O56: 0 | Q56: 0 | R56: 25 | S56: 12044.25 | T56: 14 | U56: 1016359.7 | V56: 23 | W56: 11080.71 | X56: 1170732.9 | Y56: 13.5 | Z56: 1012683.9 | AA56: 3675.7462 | AB56: 0 | AC56: 0 | AD56: 0 | AF56: 我们配票（经俊兴） | AG56: 1170732.9 | AH56: — | AI56: 按状态视为已完成(历史) | AJ56: 待登记 | AK56: — | AL56: 未开始(前一环节未完成) | AM56: 0 | AN56: 46266 | AO56: 2026-09 | AP56: 0 | AQ56: 台账历史数据-已出结算单（具体单号未录入） | AR56: 华西特钢 | AS56: 华西-欧冶户头 | AU56: 由台账 Excel 历史数据自动导入（8.19付款明细-欧冶物宝1.xlsx 第77行），日期为过磅日期近似值
A57: 55 | B57: 46267 | C57: 苏BXT103 | D57: 车 | E57: 配票/反向 | F57: 配票 | G57: 闫东朋 | H57: 闫东朋车队 | I57: 俊兴 | J57: 已开票 | K57: 56.14 | L57: 132939.52 | M57: =Q57+S57-AA57-AC57-AD57 | N57: =IF(K57=0,0,M57/K57) | O57: 0 | Q57: 0 | R57: 25 | S57: 1403.5 | T57: 14 | U57: 114327.99 | V57: 23 | W57: 1291.22 | X57: 131648.3 | Y57: 13.5 | Z57: 113875.78 | AA57: 452.2077 | AB57: 0 | AC57: 0 | AD57: 0 | AF57: 我们配票（经俊兴） | AG57: 131648.3 | AH57: — | AI57: 按状态视为已完成(历史) | AJ57: 待登记 | AK57: — | AL57: 未开始(前一环节未完成) | AM57: 0 | AN57: 46267 | AO57: 2026-09 | AP57: 0.5 | AQ57: 台账历史数据-已出结算单（具体单号未录入） | AR57: 华西特钢 | AS57: 华西-欧冶户头 | AU57: 由台账 Excel 历史数据自动导入（8.19付款明细-欧冶物宝1.xlsx 第78行），日期为过磅日期近似值 [原货主:闫东鹏，识别为调货人闫东朋(同音疑似同一人，待用户确认)]
A58: 56 | B58: 46268 | C58: 苏NER821 | D58: 车 | E58: 配票/反向 | F58: 配票 | G58: 李涛 | H58: 李涛车队 | I58: 俊兴 | J58: 已开票 | K58: 35.72 | L58: 86442.4 | M58: =Q58+S58-AA58-AC58-AD58 | N58: =IF(K58=0,0,M58/K58) | O58: 0 | Q58: 0 | R58: 25 | S58: 893 | T58: 14 | U58: 74340.464 | V58: 23 | W58: 821.56 | X58: 85620.84 | Y58: 13.5 | Z58: 74062.027 | AA58: 278.4374 | AB58: 0 | AC58: 0 | AD58: 0 | AF58: 我们配票（经俊兴） | AG58: 85620.84 | AH58: — | AI58: 按状态视为已完成(历史) | AJ58: 待登记 | AK58: — | AL58: 未开始(前一环节未完成) | AM58: 0 | AN58: 46268 | AO58: 2026-09 | AP58: 0.3 | AQ58: 台账历史数据-已出结算单（具体单号未录入） | AR58: 华西特钢 | AS58: 华西-欧冶户头 | AU58: 由台账 Excel 历史数据自动导入（8.19付款明细-欧冶物宝1.xlsx 第80行），日期为过磅日期近似值 [原货主:李涛]
A59: 57 | B59: 46268 | C59: 苏兴达货8566 | D59: 船 | E59: 配票/反向 | F59: 配票 | H59: 俊兴 | I59: 煌烽 | J59: 已开票 | K59: 560.21 | L59: 1381864.1 | M59: =Q59+S59-AA59-AC59-AD59 | N59: =IF(K59=0,0,M59/K59) | O59: 0 | Q59: 0 | R59: 25 | S59: 14005.25 | T59: 14 | U59: 1188403.2 | V59: 23 | W59: 12884.83 | X59: 1368979.3 | Y59: 13.2 | Z59: 1188274 | AA59: 129.11924 | AB59: 0 | AC59: 0 | AD59: 0 | AF59: 我们配票（经俊兴） | AG59: 1368979.3 | AH59: 按状态视为已完成(历史) | AI59: 按状态视为已完成(历史) | AJ59: 待登记 | AK59: 未开始(前一环节未完成) | AL59: 未开始(前一环节未完成) | AM59: 0 | AN59: 46268 | AO59: 2026-09 | AP59: 0 | AQ59: 台账历史数据-已出结算单（具体单号未录入） | AR59: 华西特钢 | AS59: 华西-欧冶户头 | AU59: 由台账 Excel 历史数据自动导入（8.19付款明细-欧冶物宝1.xlsx 第81行），日期为过磅日期近似值
A60: 58 | B60: 46269 | C60: 皖SG1123 | D60: 车 | E60: 配票/反向 | F60: 配票 | G60: 李涛 | H60: 李涛车队 | I60: 益周 | J60: 已开票 | K60: 38.07 | L60: 91748.7 | M60: =Q60+S60-AA60-AC60-AD60 | N60: =IF(K60=0,0,M60/K60) | O60: 636.11163 | Q60: 0 | R60: 25 | S60: 951.75 | T60: 14 | U60: 78903.882 | V60: 23 | W60: 875.61 | X60: 90873.09 | Y60: 13.5 | Z60: 78605.223 | AA60: 298.65915 | AB60: 0 | AC60: 0 | AD60: 0 | AF60: 我们配票（经俊兴） | AG60: 90873.09 | AH60: 按状态视为已完成(历史) | AI60: 按状态视为已完成(历史) | AJ60: 待登记 | AK60: 未开始(前一环节未完成) | AL60: 未开始(前一环节未完成) | AM60: 0 | AN60: 46269 | AO60: 2026-09 | AP60: 0.35 | AQ60: 台账历史数据-已出结算单（具体单号未录入） | AR60: 华西特钢 | AS60: 华西-欧冶户头 | AU60: 由台账 Excel 历史数据自动导入（8.19付款明细-欧冶物宝1.xlsx 第82行），日期为过磅日期近似值 [原货主:李涛]
A61: 59 | B61: 46269 | C61: 皖LE9644 | D61: 车 | E61: 配票/反向 | F61: 配票 | G61: 李涛 | H61: 李涛车队 | I61: 益周 | J61: 已开票 | K61: 35.28 | L61: 68714.8 | M61: =Q61+S61-AA61-AC61-AD61 | N61: =IF(K61=0,0,M61/K61) | O61: 475.32352 | Q61: 0 | R61: 25 | S61: 882 | T61: 14 | U61: 59094.728 | V61: 23 | W61: 811.44 | X61: 67903.36 | Y61: 13.5 | Z61: 58736.406 | AA61: 358.3216 | AB61: 0 | AC61: 0 | AD61: 0 | AF61: 我们配票（经俊兴） | AG61: 67903.36 | AH61: 按状态视为已完成(历史) | AI61: 按状态视为已完成(历史) | AJ61: 待登记 | AK61: 未开始(前一环节未完成) | AL61: 未开始(前一环节未完成) | AM61: 0 | AN61: 46269 | AO61: 2026-09 | AP61: 0.3 | AQ61: 台账历史数据-已出结算单（具体单号未录入） | AR61: 华西特钢 | AS61: 华西-欧冶户头 | AU61: 由台账 Excel 历史数据自动导入（8.19付款明细-欧冶物宝1.xlsx 第83行），日期为过磅日期近似值 [原货主:李涛]；【2026-09-17更正】原切割费16310元实为钢厂含税罚款，应由供应商/货主承担(转付时按不含税金额从供应商货款中扣除)，不计入本公司利润成本，已用other_cost=-16310冲抵
A62: 60 | B62: 46269 | C62: 苏K66529 | D62: 车 | E62: 配票/反向 | F62: 配票 | G62: 陈杰 | H62: 陈杰车队 | I62: 益周 | J62: 已开票 | K62: 39.12 | L62: 89584.8 | M62: =Q62+S62-AA62-AC62-AD62 | N62: =IF(K62=0,0,M62/K62) | O62: 620.79528 | Q62: 0 | R62: 25 | S62: 978 | T62: 14 | U62: 77042.928 | V62: 23 | W62: 899.76 | X62: 88685.04 | Y62: 13.5 | Z62: 76712.56 | AA62: 330.3684 | AB62: 0 | AC62: 0 | AD62: 0 | AF62: 我们配票（经俊兴） | AG62: 88685.04 | AH62: 按状态视为已完成(历史) | AI62: 按状态视为已完成(历史) | AJ62: 待登记 | AK62: 未开始(前一环节未完成) | AL62: 未开始(前一环节未完成) | AM62: 0 | AN62: 46269 | AO62: 2026-09 | AP62: 1 | AQ62: 台账历史数据-已出结算单（具体单号未录入） | AR62: 华西特钢 | AS62: 华西-欧冶户头 | AU62: 由台账 Excel 历史数据自动导入（8.19付款明细-欧冶物宝1.xlsx 第84行），日期为过磅日期近似值 [原货主:陈杰]
A63: 61 | B63: 46270 | C63: 皖城兴货688 | D63: 船 | E63: 配票/反向 | F63: 配票 | G63: 林凯 | H63: 林凯车队 | I63: 益周 | J63: 已开票 | K63: 719.14 | L63: 1823625.4 | M63: =Q63+S63-AA63-AC63-AD63 | N63: =IF(K63=0,0,M63/K63) | O63: 12649.596 | Q63: 0 | R63: 25 | S63: 17978.5 | T63: 14 | U63: 1568317.8 | V63: 23 | W63: 16540.22 | X63: 1807085.2 | Y63: 13.5 | Z63: 1563128.7 | AA63: 5189.1633 | AB63: 0 | AC63: 0 | AD63: 0 | AF63: 我们配票（经俊兴） | AG63: 1807085.2 | AH63: 按状态视为已完成(历史) | AI63: 按状态视为已完成(历史) | AJ63: 待登记 | AK63: 未开始(前一环节未完成) | AL63: 未开始(前一环节未完成) | AM63: 0 | AN63: 46270 | AO63: 2026-09 | AP63: 0 | AQ63: 台账历史数据-已出结算单（具体单号未录入） | AR63: 华西特钢 | AS63: 华西-欧冶户头 | AU63: 由台账 Excel 历史数据自动导入（8.19付款明细-欧冶物宝1.xlsx 第85行），日期为过磅日期近似值 [原货主:林凯]
A64: 62 | B64: 46272 | C64: 鲁济宁货1567 | D64: 船 | E64: 配票/反向 | F64: 配票 | G64: 林凯 | H64: 林凯车队 | I64: 煌烽 | J64: 已结算 | K64: 613.8 | L64: 1467823.1 | M64: =Q64+S64-AA64-AC64-AD64 | N64: =IF(K64=0,0,M64/K64) | O64: 0 | Q64: 0 | R64: 25 | S64: 15345 | T64: 14 | U64: 1262327.9 | V64: 23 | W64: 14117.4 | X64: 1453705.7 | Y64: 13.2 | Z64: 1261816.5 | AA64: 511.3184 | AB64: 0 | AC64: 0 | AD64: 0 | AF64: 我们配票（经俊兴） | AG64: 1453705.7 | AH64: 待登记 | AI64: 待登记 | AJ64: 未开始(前一环节未完成) | AK64: 未开始(前一环节未完成) | AL64: 未开始(前一环节未完成) | AM64: 0 | AN64: 46272 | AO64: 2026-09 | AP64: 0 | AQ64: 台账历史数据-已出结算单（具体单号未录入） | AR64: 华西特钢 | AS64: 华西-欧冶户头 | AU64: 由台账 Excel 历史数据自动导入（8.19付款明细-欧冶物宝1.xlsx 第86行），日期为过磅日期近似值 [原货主:林凯]
A65: 63 | B65: 46275 | C65: 苏DBE075 | D65: 车 | E65: 带票带货 | F65: 户头通道 | G65: 林凯 | H65: 君盛 | I65: 俊兴 | J65: 已结算 | K65: 82.26 | L65: 208117.8 | M65: =Q65+S65-AA65-AC65-AD65 | N65: =IF(K65=0,0,M65/K65) | O65: 0 | P65: 40 | Q65: 3290.4 | R65: 25 | S65: 2056.5 | V65: 23 | W65: 1891.98 | AA65: 1891.98 | AB65: 15 | AC65: 1233.9 | AD65: 0 | AF65: 我们配票（经俊兴） | AG65: 206225.82 | AH65: — | AI65: 待登记 | AJ65: 未开始(前一环节未完成) | AK65: — | AL65: 未开始(前一环节未完成) | AM65: 0 | AN65: 46275 | AO65: 2026-09 | AP65: 0.3 | AQ65: 台账历史数据-已出结算单（具体单号未录入） | AR65: 华西特钢 | AS65: 华西-欧冶户头 | AU65: 由台账 Excel 历史数据自动导入（8.19付款明细-欧冶物宝1.xlsx 第87行），日期为过磅日期近似值 [原货主:林凯]
A66: 64 | B66: 46276 | C66: 苏DBB772 | D66: 车 | E66: 带票带货 | F66: 户头通道 | G66: 林凯 | H66: 君盛 | I66: 俊兴 | J66: 已结算 | K66: 82.2 | L66: 207966 | M66: =Q66+S66-AA66-AC66-AD66 | N66: =IF(K66=0,0,M66/K66) | O66: 0 | P66: 40 | Q66: 3288 | R66: 25 | S66: 2055 | V66: 23 | W66: 1890.6 | AA66: 1890.6 | AB66: 15 | AC66: 1233 | AD66: 0 | AF66: 我们配票（经俊兴） | AG66: 206075.4 | AH66: — | AI66: 待登记 | AJ66: 未开始(前一环节未完成) | AK66: — | AL66: 未开始(前一环节未完成) | AM66: 0 | AN66: 46276 | AO66: 2026-09 | AP66: 0.4 | AQ66: 台账历史数据-已出结算单（具体单号未录入） | AR66: 华西特钢 | AS66: 华西-欧冶户头 | AU66: 由台账 Excel 历史数据自动导入（8.19付款明细-欧冶物宝1.xlsx 第88行），日期为过磅日期近似值 [原货主:林凯]
A67: 65 | B67: 46277 | C67: 苏DBE961 | D67: 车 | E67: 带票带货 | F67: 户头通道 | G67: 林凯 | H67: 力拓 | I67: 俊兴 | J67: 已结算 | K67: 79.76 | L67: 181852.8 | M67: =Q67+S67-AA67-AC67-AD67 | N67: =IF(K67=0,0,M67/K67) | O67: 0 | P67: 40 | Q67: 3190.4 | R67: 25 | S67: 1994 | V67: 23 | W67: 1834.48 | AA67: 1834.48 | AB67: 15 | AC67: 1196.4 | AD67: 0 | AF67: 我们配票（经俊兴） | AG67: 180018.32 | AH67: — | AI67: 待登记 | AJ67: 未开始(前一环节未完成) | AK67: — | AL67: 未开始(前一环节未完成) | AM67: 0 | AN67: 46277 | AO67: 2026-09 | AP67: 2.1 | AQ67: 台账历史数据-已出结算单（具体单号未录入） | AR67: 华西特钢 | AS67: 华西-欧冶户头 | AU67: 由台账 Excel 历史数据自动导入（8.19付款明细-欧冶物宝1.xlsx 第89行），日期为过磅日期近似值 [原货主:林凯]
A68: 66 | B68: 46277 | C68: 苏DBE075 | D68: 车 | E68: 带票带货 | F68: 户头通道 | G68: 林凯 | H68: 𠓾景通 | I68: 俊兴 | J68: 已结算 | K68: 78.04 | L68: 200062.8 | M68: =Q68+S68-AA68-AC68-AD68 | N68: =IF(K68=0,0,M68/K68) | O68: 0 | P68: 40 | Q68: 3121.6 | R68: 25 | S68: 1951 | V68: 23 | W68: 1794.92 | AA68: 1794.92 | AB68: 15 | AC68: 1170.6 | AD68: 500 | AF68: 我们配票（经俊兴） | AG68: 198267.88 | AH68: — | AI68: 待登记 | AJ68: 未开始(前一环节未完成) | AK68: — | AL68: 未开始(前一环节未完成) | AM68: 0 | AN68: 46277 | AO68: 2026-09 | AP68: 0.6 | AQ68: 台账历史数据-已出结算单（具体单号未录入） | AR68: 华西特钢 | AS68: 华西-欧冶户头 | AU68: 由台账 Excel 历史数据自动导入（8.19付款明细-欧冶物宝1.xlsx 第90行），日期为过磅日期近似值 [原货主:林凯]
A69: 67 | B69: 46277 | C69: 皖F30399 | D69: 车 | E69: 配票/反向 | F69: 配票 | G69: 邓晶焱 | H69: 邓晶焱车队 | I69: 俊兴 | J69: 已结算 | K69: 39.17 | L69: 94008 | M69: =Q69+S69-AA69-AC69-AD69 | N69: =IF(K69=0,0,M69/K69) | O69: 0 | Q69: 0 | R69: 25 | S69: 979.25 | T69: 14 | U69: 80846.88 | V69: 23 | W69: 900.91 | X69: 93107.09 | Y69: 13.5 | Z69: 80537.633 | AA69: 309.24715 | AB69: 0 | AC69: 0 | AD69: 0 | AF69: 我们配票（经俊兴） | AG69: 93107.09 | AH69: — | AI69: 待登记 | AJ69: 未开始(前一环节未完成) | AK69: — | AL69: 未开始(前一环节未完成) | AM69: 0 | AN69: 46277 | AO69: 2026-09 | AP69: 0.55 | AQ69: 台账历史数据-已出结算单（具体单号未录入） | AR69: 华西特钢 | AS69: 华西-欧冶户头 | AU69: 由台账 Excel 历史数据自动导入（8.19付款明细-欧冶物宝1.xlsx 第91行），日期为过磅日期近似值 [原货主:邓晶焱]
A70: 68 | B70: 46277 | C70: 苏DBE075 | D70: 车 | E70: 带票带货 | F70: 户头通道 | G70: 林凯 | H70: 君盛 | I70: 俊兴 | J70: 已结算 | K70: 65.44 | L70: 147240 | M70: =Q70+S70-AA70-AC70-AD70 | N70: =IF(K70=0,0,M70/K70) | O70: 0 | P70: 40 | Q70: 2617.6 | R70: 25 | S70: 1636 | V70: 23 | W70: 1505.12 | AA70: 1505.12 | AB70: 15 | AC70: 981.6 | AD70: 0 | AF70: 我们配票（经俊兴） | AG70: 145734.88 | AH70: — | AI70: 待登记 | AJ70: 未开始(前一环节未完成) | AK70: — | AL70: 未开始(前一环节未完成) | AM70: 0 | AN70: 46277 | AO70: 2026-09 | AP70: 2 | AQ70: 台账历史数据-已出结算单（具体单号未录入） | AR70: 华西特钢 | AS70: 华西-欧冶户头 | AU70: 由台账 Excel 历史数据自动导入（8.19付款明细-欧冶物宝1.xlsx 第92行），日期为过磅日期近似值 [原货主:林凯]
A71: 69 | B71: 46279 | C71: 苏DBB772 | D71: 车 | E71: 配票/反向 | F71: 配票 | G71: 林凯 | H71: 林凯车队 | I71: 俊兴 | J71: 已结算 | K71: 60.9 | L71: 137025 | M71: =Q71+S71-AA71-AC71-AD71 | N71: =IF(K71=0,0,M71/K71) | O71: 0 | Q71: 0 | R71: 25 | S71: 1522.5 | T71: 14 | U71: 117841.5 | V71: 23 | W71: 1400.7 | X71: 135624.3 | Y71: 13.5 | Z71: 117315.02 | AA71: 526.4805 | AB71: 0 | AC71: 0 | AD71: 0 | AF71: 我们配票（经俊兴） | AG71: 135624.3 | AH71: — | AI71: 待登记 | AJ71: 未开始(前一环节未完成) | AK71: — | AL71: 未开始(前一环节未完成) | AM71: 0 | AN71: 46279 | AO71: 2026-09 | AP71: 1.7 | AQ71: 台账历史数据-已出结算单（具体单号未录入） | AR71: 华西特钢 | AS71: 华西-欧冶户头 | AU71: 由台账 Excel 历史数据自动导入（8.19付款明细-欧冶物宝1.xlsx 第93行），日期为过磅日期近似值 [原货主:林凯]
A72: 70 | B72: 46279 | C72: 苏DBE961 | D72: 车 | E72: 带票带货 | F72: 户头通道 | G72: 林凯 | H72: 力拓 | I72: 俊兴 | J72: 已结算 | K72: 75.88 | L72: 191976.4 | M72: =Q72+S72-AA72-AC72-AD72 | N72: =IF(K72=0,0,M72/K72) | O72: 0 | P72: 40 | Q72: 3035.2 | R72: 25 | S72: 1897 | V72: 23 | W72: 1745.24 | AA72: 1745.24 | AB72: 15 | AC72: 1138.2 | AD72: 0 | AF72: 我们配票（经俊兴） | AG72: 190231.16 | AH72: — | AI72: 待登记 | AJ72: 未开始(前一环节未完成) | AK72: — | AL72: 未开始(前一环节未完成) | AM72: 0 | AN72: 46279 | AO72: 2026-09 | AP72: 0.7 | AQ72: 台账历史数据-已出结算单（具体单号未录入） | AR72: 华西特钢 | AS72: 华西-欧冶户头 | AU72: 由台账 Excel 历史数据自动导入（8.19付款明细-欧冶物宝1.xlsx 第94行），日期为过磅日期近似值 [原货主:林凯]
A73: 71 | B73: 46279 | C73: 鲁DC6106 | D73: 车 | E73: 带票带货 | F73: 户头通道 | G73: 邓晶焱 | H73: 邓晶焱车队 | I73: 煌烽 | J73: 已结算 | K73: 44.52 | L73: 103286.4 | M73: =Q73+S73-AA73-AC73-AD73 | N73: =IF(K73=0,0,M73/K73) | O73: 0 | P73: 18.56 | Q73: 826.2912 | R73: 25 | S73: 1113 | V73: 23 | W73: 1023.96 | AA73: 1023.96 | AB73: 0 | AC73: 0 | AD73: 0 | AF73: 票商/反向 → 供货厂 → 欧冶 | AG73: 102262.44 | AH73: 待登记 | AI73: 待登记 | AJ73: 未开始(前一环节未完成) | AK73: 未开始(前一环节未完成) | AL73: — | AM73: 0 | AN73: 46279 | AO73: 2026-09 | AP73: 0.9 | AQ73: 台账历史数据-已出结算单（具体单号未录入） | AR73: 华西特钢 | AS73: 华西-欧冶户头 | AU73: 由台账 Excel 历史数据自动导入（8.19付款明细-欧冶物宝1.xlsx 第95行），日期为过磅日期近似值 [原货主:邓晶焱]
A74: 72 | B74: 46279 | C74: 苏J19371 | D74: 车 | E74: 带票带货 | F74: 户头通道 | G74: 闫东朋 | H74: 闫东朋车队 | I74: 反向-闫东朋 | J74: 已结算 | K74: 78.36 | L74: 198250.8 | M74: =Q74+S74-AA74-AC74-AD74 | N74: =IF(K74=0,0,M74/K74) | O74: 0 | P74: 28.06 | Q74: 2198.7816 | R74: 25 | S74: 1959 | V74: 23 | W74: 1802.28 | AA74: 1802.28 | AB74: 0 | AC74: 0 | AD74: 0 | AF74: 票商/反向 → 供货厂 → 欧冶 | AG74: 196448.52 | AH74: 待登记 | AI74: 待登记 | AJ74: 未开始(前一环节未完成) | AK74: 未开始(前一环节未完成) | AL74: — | AM74: 0 | AN74: 46279 | AO74: 2026-09 | AP74: 0.5 | AQ74: 台账历史数据-已出结算单（具体单号未录入） | AR74: 华西特钢 | AS74: 华西-欧冶户头 | AU74: 由台账 Excel 历史数据自动导入（8.19付款明细-欧冶物宝1.xlsx 第96行），日期为过磅日期近似值 [原货主:闫东朋]
A75: 73 | B75: 46280 | C75: 苏ELU629 | D75: 车 | E75: 配票/反向 | F75: 配票 | H75: 未填供货厂 | I75: 煌烽 | J75: 已结算 | K75: 34.42 | L75: 82263.8 | M75: =Q75+S75-AA75-AC75-AD75 | N75: =IF(K75=0,0,M75/K75) | O75: 0 | Q75: 0 | R75: 25 | S75: 860.5 | T75: 14 | U75: 70746.868 | V75: 23 | W75: 791.66 | X75: 81472.14 | Y75: 13.2 | Z75: 70717.818 | AA75: 29.05048 | AB75: 0 | AC75: 0 | AD75: 0 | AF75: 我们配票（经俊兴） | AG75: 81472.14 | AH75: 待登记 | AI75: 待登记 | AJ75: 未开始(前一环节未完成) | AK75: 未开始(前一环节未完成) | AL75: 未开始(前一环节未完成) | AM75: 0 | AN75: 46280 | AO75: 2026-09 | AP75: 0.3 | AR75: 华西特钢 | AS75: 华西-欧冶户头 | AU75: 2026-09-18由用户提供的台账数据人工核对后录入（Claude协助整理，用户逐项确认结算模式/供货厂/票源方后导入）
A76: 74 | B76: 46280 | C76: 苏DBE075 | D76: 车 | E76: 带票带货 | F76: 直签带票 | G76: 林凯 | H76: 君盛 | J76: 已结算 | K76: 31.46 | L76: 70785 | M76: =Q76+S76-AA76-AC76-AD76 | N76: =IF(K76=0,0,M76/K76) | O76: 0 | P76: 40 | Q76: 1258.4 | R76: 25 | S76: 786.5 | V76: 23 | W76: 723.58 | AA76: 723.58 | AB76: 15 | AC76: 471.9 | AD76: 0 | AF76: 供货厂自带票（带票带货） | AG76: 70061.42 | AH76: — | AI76: 待登记 | AJ76: 未开始(前一环节未完成) | AK76: — | AL76: — | AM76: 0 | AN76: 46280 | AO76: 2026-09 | AP76: 0.3 | AR76: 华西特钢 | AS76: 华西-欧冶户头 | AU76: 2026-09-18由用户提供的台账数据人工核对后录入（Claude协助整理，用户逐项确认结算模式/供货厂/票源方后导入）
A77: 75 | B77: 46280 | C77: 苏L80153 | D77: 车 | E77: 配票/反向 | F77: 反向 | G77: 闫东朋 | H77: 闫东朋车队 | I77: 反向-闫东朋 | J77: 已结算 | K77: 47.98 | L77: 123308.6 | M77: =Q77+S77-AA77-AC77-AD77 | N77: =IF(K77=0,0,M77/K77) | O77: 0 | Q77: 0 | R77: 25 | S77: 1199.5 | T77: 14 | U77: 106045.4 | V77: 0 | W77: 0 | X77: 123308.6 | Y77: 13.8 | Z77: 106292.01 | AA77: -246.6172 | AB77: 0 | AC77: 0 | AD77: 0 | AF77: 票商/反向 → 供货厂 → 欧冶 | AG77: 123308.6 | AH77: 待登记 | AI77: 待登记 | AJ77: 未开始(前一环节未完成) | AK77: 未开始(前一环节未完成) | AL77: — | AM77: 0 | AN77: 46280 | AO77: 2026-09 | AP77: 0.2 | AR77: 华西特钢 | AS77: 华西-欧冶户头 | AU77: 2026-09-18由用户提供的台账数据人工核对后录入（Claude协助整理，用户逐项确认结算模式/供货厂/票源方后导入）
A78: 76 | B78: 46280 | C78: 苏J19371 | D78: 车 | E78: 配票/反向 | F78: 反向 | G78: 闫东朋 | H78: 闫东朋车队 | I78: 反向-闫东朋 | J78: 已结算 | K78: 79.58 | L78: 199745.8 | M78: =Q78+S78-AA78-AC78-AD78 | N78: =IF(K78=0,0,M78/K78) | O78: 0 | Q78: 0 | R78: 25 | S78: 1989.5 | T78: 14 | U78: 171781.39 | V78: 0 | W78: 0 | X78: 199745.8 | Y78: 13.8 | Z78: 172180.88 | AA78: -399.4916 | AB78: 0 | AC78: 0 | AD78: 0 | AF78: 票商/反向 → 供货厂 → 欧冶 | AG78: 199745.8 | AH78: 待登记 | AI78: 待登记 | AJ78: 未开始(前一环节未完成) | AK78: 未开始(前一环节未完成) | AL78: — | AM78: 0 | AN78: 46280 | AO78: 2026-09 | AP78: 0.4 | AR78: 华西特钢 | AS78: 华西-欧冶户头 | AU78: 2026-09-18由用户提供的台账数据人工核对后录入（Claude协助整理，用户逐项确认结算模式/供货厂/票源方后导入）
A79: 77 | B79: 46280 | C79: 苏CLK667 | D79: 车 | E79: 配票/反向 | F79: 配票 | H79: 未填供货厂 | I79: 煌烽 | J79: 已结算 | K79: 33.02 | L79: 76606.4 | M79: =Q79+S79-AA79-AC79-AD79 | N79: =IF(K79=0,0,M79/K79) | O79: 0 | Q79: 0 | R79: 25 | S79: 825.5 | T79: 14 | U79: 65881.504 | V79: 23 | W79: 759.46 | X79: 75846.94 | Y79: 13.2 | Z79: 65835.144 | AA79: 46.36008 | AB79: 0 | AC79: 0 | AD79: 0 | AF79: 我们配票（经俊兴） | AG79: 75846.94 | AH79: 待登记 | AI79: 待登记 | AJ79: 未开始(前一环节未完成) | AK79: 未开始(前一环节未完成) | AL79: 未开始(前一环节未完成) | AM79: 0 | AN79: 46280 | AO79: 2026-09 | AP79: 0.5 | AR79: 华西特钢 | AS79: 华西-欧冶户头 | AU79: 2026-09-18由用户提供的台账数据人工核对后录入（Claude协助整理，用户逐项确认结算模式/供货厂/票源方后导入）
A80: 78 | B80: 46280 | C80: 苏DBB772 | D80: 车 | E80: 带票带货 | F80: 直签带票 | G80: 林凯 | H80: 𠓾景通 | J80: 已结算 | K80: 71.5 | L80: 169455 | M80: =Q80+S80-AA80-AC80-AD80 | N80: =IF(K80=0,0,M80/K80) | O80: 0 | P80: 40 | Q80: 2860 | R80: 25 | S80: 1787.5 | V80: 23 | W80: 1644.5 | AA80: 1644.5 | AB80: 15 | AC80: 1072.5 | AD80: 0 | AF80: 供货厂自带票（带票带货） | AG80: 167810.5 | AH80: — | AI80: 待登记 | AJ80: 未开始(前一环节未完成) | AK80: — | AL80: — | AM80: 0 | AN80: 46280 | AO80: 2026-09 | AP80: 0.7 | AR80: 华西特钢 | AS80: 华西-欧冶户头 | AU80: 2026-09-18由用户提供的台账数据人工核对后录入（Claude协助整理，用户逐项确认结算模式/供货厂/票源方后导入）
A81: 79 | B81: 46280 | C81: 苏DBE961 | D81: 车 | E81: 带票带货 | F81: 直签带票 | G81: 林凯 | H81: 君盛 | J81: 已结算 | K81: 31.38 | L81: 70605 | M81: =Q81+S81-AA81-AC81-AD81 | N81: =IF(K81=0,0,M81/K81) | O81: 0 | P81: 40 | Q81: 1255.2 | R81: 25 | S81: 784.5 | V81: 23 | W81: 721.74 | AA81: 721.74 | AB81: 15 | AC81: 470.7 | AD81: 0 | AF81: 供货厂自带票（带票带货） | AG81: 69883.26 | AH81: — | AI81: 待登记 | AJ81: 未开始(前一环节未完成) | AK81: — | AL81: — | AM81: 0 | AN81: 46280 | AO81: 2026-09 | AP81: 0.8 | AR81: 华西特钢 | AS81: 华西-欧冶户头 | AU81: 2026-09-18由用户提供的台账数据人工核对后录入（Claude协助整理，用户逐项确认结算模式/供货厂/票源方后导入）
A82: 80 | B82: 46280 | C82: 皖四航6058 | D82: 车 | E82: 配票/反向 | F82: 配票 | H82: 尹鹏飞 | I82: 煌烽 | J82: 已结算 | K82: 589.24 | L82: 1444596.1 | M82: =Q82+S82-AA82-AC82-AD82 | N82: =IF(K82=0,0,M82/K82) | O82: 0 | Q82: 0 | R82: 25 | S82: 14731 | T82: 14 | U82: 1242352.6 | V82: 23 | W82: 13552.52 | X82: 1431043.6 | Y82: 13.2 | Z82: 1242145.8 | AA82: 206.81872 | AB82: 0 | AC82: 0 | AD82: 0 | AF82: 我们配票（经俊兴） | AG82: 1431043.6 | AH82: 待登记 | AI82: 待登记 | AJ82: 未开始(前一环节未完成) | AK82: 未开始(前一环节未完成) | AL82: 未开始(前一环节未完成) | AM82: 0 | AN82: 46280 | AO82: 2026-09 | AP82: 6.92 | AR82: 华西特钢 | AS82: 华西-欧冶户头 | AU82: 2026-09-18由用户提供的台账数据人工核对后录入（Claude协助整理，用户逐项确认结算模式/供货厂/票源方后导入）
A83: 81 | B83: 46281 | C83: 皖SC6167 | D83: 车 | E83: 配票/反向 | F83: 反向 | G83: 闫东朋 | H83: 闫东朋车队 | I83: 反向-闫东朋 | J83: 已结算 | K83: 50.72 | L83: 128017.28 | M83: =Q83+S83-AA83-AC83-AD83 | N83: =IF(K83=0,0,M83/K83) | O83: 0 | Q83: 0 | R83: 25 | S83: 1268 | T83: 14 | U83: 110094.86 | V83: 0 | W83: 0 | X83: 128017.28 | Y83: 13.8 | Z83: 110350.9 | AA83: -256.03456 | AB83: 0 | AC83: 0 | AD83: 0 | AF83: 票商/反向 → 供货厂 → 欧冶 | AG83: 128017.28 | AH83: 待登记 | AI83: 待登记 | AJ83: 未开始(前一环节未完成) | AK83: 未开始(前一环节未完成) | AL83: — | AM83: 0 | AN83: 46281 | AO83: 2026-09 | AP83: 0.5 | AR83: 华西特钢 | AS83: 华西-欧冶户头 | AU83: 2026-09-18由用户提供的台账数据人工核对后录入（Claude协助整理，用户逐项确认结算模式/供货厂/票源方后导入）
A84: 82 | B84: 46281 | C84: 皖AK6033 | D84: 车 | E84: 配票/反向 | F84: 配票 | H84: 未填供货厂 | I84: 煌烽 | J84: 已结算 | K84: 41.42 | L84: 96094.4 | M84: =Q84+S84-AA84-AC84-AD84 | N84: =IF(K84=0,0,M84/K84) | O84: 0 | Q84: 0 | R84: 25 | S84: 1035.5 | T84: 14 | U84: 82641.184 | V84: 23 | W84: 952.66 | X84: 95141.74 | Y84: 13.2 | Z84: 82583.03 | AA84: 58.15368 | AB84: 0 | AC84: 0 | AD84: 0 | AF84: 我们配票（经俊兴） | AG84: 95141.74 | AH84: 待登记 | AI84: 待登记 | AJ84: 未开始(前一环节未完成) | AK84: 未开始(前一环节未完成) | AL84: 未开始(前一环节未完成) | AM84: 0 | AN84: 46281 | AO84: 2026-09 | AP84: 0.6 | AR84: 华西特钢 | AS84: 华西-欧冶户头 | AU84: 2026-09-18由用户提供的台账数据人工核对后录入（Claude协助整理，用户逐项确认结算模式/供货厂/票源方后导入）
A85: 83 | B85: 46282 | C85: 苏DBE075 | D85: 车 | E85: 带票带货 | F85: 直签带票 | G85: 林凯 | H85: 力拓 | J85: 已结算 | K85: 81.46 | L85: 206093.8 | M85: =Q85+S85-AA85-AC85-AD85 | N85: =IF(K85=0,0,M85/K85) | O85: 0 | P85: 40 | Q85: 3258.4 | R85: 25 | S85: 2036.5 | V85: 23 | W85: 1873.58 | AA85: 1873.58 | AB85: 15 | AC85: 1221.9 | AD85: 0 | AF85: 供货厂自带票（带票带货） | AG85: 204220.22 | AH85: — | AI85: 待登记 | AJ85: 未开始(前一环节未完成) | AK85: — | AL85: — | AM85: 0 | AN85: 46282 | AO85: 2026-09 | AP85: 0.4 | AR85: 华西特钢 | AS85: 华西-欧冶户头 | AU85: 2026-09-18由用户提供的台账数据人工核对后录入（Claude协助整理，用户逐项确认结算模式/供货厂/票源方后导入）
A86: 84 | B86: 46282 | C86: 皖AP1626 | D86: 车 | E86: 配票/反向 | F86: 反向 | G86: 闫东朋 | H86: 闫东朋车队 | I86: 反向-闫东朋 | J86: 已结算 | K86: 52 | L86: 126308 | M86: =Q86+S86-AA86-AC86-AD86 | N86: =IF(K86=0,0,M86/K86) | O86: 0 | Q86: 0 | R86: 25 | S86: 1300 | T86: 14 | U86: 108624.88 | V86: 0 | W86: 0 | X86: 126308 | Y86: 13.8 | Z86: 108877.5 | AA86: -252.616 | AB86: 0 | AC86: 0 | AD86: 0 | AF86: 票商/反向 → 供货厂 → 欧冶 | AG86: 126308 | AH86: 待登记 | AI86: 待登记 | AJ86: 未开始(前一环节未完成) | AK86: 未开始(前一环节未完成) | AL86: — | AM86: 0 | AN86: 46282 | AO86: 2026-09 | AP86: 0.9 | AQ86: 台账历史数据-已出结算单（具体单号未录入） | AR86: 华西特钢 | AS86: 华西-欧冶户头 | AU86: 2026-09-18由用户提供的台账数据人工核对后录入（Claude协助整理，用户逐项确认结算模式/供货厂/票源方后导入）
A87: 85 | B87: 46282 | C87: 苏J19371 | D87: 车 | E87: 配票/反向 | F87: 反向 | G87: 闫东朋 | H87: 闫东朋车队 | I87: 反向-闫东朋 | J87: 已结算 | K87: 73.54 | L87: 186056.2 | M87: =Q87+S87-AA87-AC87-AD87 | N87: =IF(K87=0,0,M87/K87) | O87: 0 | Q87: 0 | R87: 25 | S87: 1838.5 | T87: 14 | U87: 160008.33 | V87: 0 | W87: 0 | X87: 186056.2 | Y87: 13.8 | Z87: 160380.44 | AA87: -372.1124 | AB87: 0 | AC87: 0 | AD87: 0 | AF87: 票商/反向 → 供货厂 → 欧冶 | AG87: 186056.2 | AH87: 待登记 | AI87: 待登记 | AJ87: 未开始(前一环节未完成) | AK87: 未开始(前一环节未完成) | AL87: — | AM87: 0 | AN87: 46282 | AO87: 2026-09 | AP87: 0.5 | AR87: 华西特钢 | AS87: 华西-欧冶户头 | AU87: 2026-09-18由用户提供的台账数据人工核对后录入（Claude协助整理，用户逐项确认结算模式/供货厂/票源方后导入）
A88: 86 | B88: 46282 | C88: 苏DBE075 | D88: 车 | E88: 带票带货 | F88: 直签带票 | G88: 林凯 | H88: 君盛 | J88: 已结算 | K88: 29.79 | L88: 68576.58 | M88: =Q88+S88-AA88-AC88-AD88 | N88: =IF(K88=0,0,M88/K88) | O88: 0 | P88: 40 | Q88: 1191.6 | R88: 25 | S88: 744.75 | V88: 23 | W88: 685.17 | AA88: 685.17 | AB88: 15 | AC88: 446.85 | AD88: 0 | AF88: 供货厂自带票（带票带货） | AG88: 67891.41 | AH88: — | AI88: 待登记 | AJ88: 未开始(前一环节未完成) | AK88: — | AL88: — | AM88: 0 | AN88: 46282 | AO88: 2026-09 | AP88: 0.45 | AR88: 华西特钢 | AS88: 华西-欧冶户头 | AU88: 2026-09-18由用户提供的台账数据人工核对后录入（Claude协助整理，用户逐项确认结算模式/供货厂/票源方后导入）
A89: 87 | B89: 46282 | C89: 苏DBB772 | D89: 车 | E89: 带票带货 | F89: 直签带票 | G89: 林凯 | H89: 君盛 | J89: 已结算 | K89: 28.84 | L89: 66389.68 | M89: =Q89+S89-AA89-AC89-AD89 | N89: =IF(K89=0,0,M89/K89) | O89: 0 | P89: 40 | Q89: 1153.6 | R89: 25 | S89: 721 | V89: 23 | W89: 663.32 | AA89: 663.32 | AB89: 15 | AC89: 432.6 | AD89: 0 | AF89: 供货厂自带票（带票带货） | AG89: 65726.36 | AH89: — | AI89: 待登记 | AJ89: 未开始(前一环节未完成) | AK89: — | AL89: — | AM89: 0 | AN89: 46282 | AO89: 2026-09 | AP89: 1.6 | AR89: 华西特钢 | AS89: 华西-欧冶户头 | AU89: 2026-09-18由用户提供的台账数据人工核对后录入（Claude协助整理，用户逐项确认结算模式/供货厂/票源方后导入）
A90: 89 | B90: 46283 | C90: 苏DBB772 | D90: 车 | E90: 带票带货 | F90: 直签带票 | G90: 林凯 | H90: 君盛 | J90: 已结算 | K90: 83.74 | L90: 202650.8 | M90: =Q90+S90-AA90-AC90-AD90 | N90: =IF(K90=0,0,M90/K90) | O90: 0 | P90: 40 | Q90: 3349.6 | R90: 25 | S90: 2093.5 | V90: 23 | W90: 1926.02 | AA90: 1926.02 | AB90: 15 | AC90: 1256.1 | AD90: 0 | AF90: 供货厂自带票（带票带货） | AG90: 200724.78 | AH90: — | AI90: 待登记 | AJ90: 未开始(前一环节未完成) | AK90: — | AL90: — | AM90: 0 | AN90: 46283 | AO90: 2026-09 | AP90: 0.8 | AR90: 华西特钢 | AS90: 华西-欧冶户头 | AU90: 2026-09-21由用户提供的台账数据整理后录入（9/18-9/20批次，Claude协助整理，用户确认）
A91: 90 | B91: 46283 | C91: 苏NEN536 | D91: 车 | E91: 配票/反向 | F91: 配票 | G91: 林凯 | H91: 林凯车队 | I91: 煌烽 | J91: 已结算 | K91: 34.02 | L91: 79266.6 | M91: =Q91+S91-AA91-AC91-AD91 | N91: =IF(K91=0,0,M91/K91) | O91: 0 | Q91: 0 | R91: 25 | S91: 850.5 | T91: 14 | U91: 68169.276 | V91: 23 | W91: 782.46 | X91: 78484.14 | Y91: 13.2 | Z91: 68124.234 | AA91: 45.04248 | AB91: 0 | AC91: 0 | AD91: 0 | AF91: 我们配票（经俊兴） | AG91: 78484.14 | AH91: 待登记 | AI91: 待登记 | AJ91: 未开始(前一环节未完成) | AK91: 未开始(前一环节未完成) | AL91: 未开始(前一环节未完成) | AM91: 0 | AN91: 46283 | AO91: 2026-09 | AP91: 0.5 | AR91: 华西特钢 | AS91: 华西-欧冶户头 | AU91: 2026-09-21由用户提供的台账数据整理后录入（9/18-9/20批次，Claude协助整理，用户确认）
A92: 91 | B92: 46283 | C92: 苏DBE075 | D92: 车 | E92: 带票带货 | F92: 直签带票 | G92: 林凯 | H92: 君盛 | J92: 已结算 | K92: 30.72 | L92: 70717.44 | M92: =Q92+S92-AA92-AC92-AD92 | N92: =IF(K92=0,0,M92/K92) | O92: 0 | P92: 40 | Q92: 1228.8 | R92: 25 | S92: 768 | V92: 23 | W92: 706.56 | AA92: 706.56 | AB92: 15 | AC92: 460.8 | AD92: 0 | AF92: 供货厂自带票（带票带货） | AG92: 70010.88 | AH92: — | AI92: 待登记 | AJ92: 未开始(前一环节未完成) | AK92: — | AL92: — | AM92: 0 | AN92: 46283 | AO92: 2026-09 | AP92: 0.6 | AR92: 华西特钢 | AS92: 华西-欧冶户头 | AU92: 2026-09-21由用户提供的台账数据整理后录入（9/18-9/20批次，Claude协助整理，用户确认）
A93: 92 | B93: 46283 | C93: 苏DBB772 | D93: 车 | E93: 带票带货 | F93: 直签带票 | G93: 林凯 | H93: 君盛 | J93: 已结算 | K93: 31.32 | L93: 72098.64 | M93: =Q93+S93-AA93-AC93-AD93 | N93: =IF(K93=0,0,M93/K93) | O93: 0 | P93: 40 | Q93: 1252.8 | R93: 25 | S93: 783 | V93: 23 | W93: 720.36 | AA93: 720.36 | AB93: 15 | AC93: 469.8 | AD93: 0 | AF93: 供货厂自带票（带票带货） | AG93: 71378.28 | AH93: — | AI93: 待登记 | AJ93: 未开始(前一环节未完成) | AK93: — | AL93: — | AM93: 0 | AN93: 46283 | AO93: 2026-09 | AP93: 0.6 | AR93: 华西特钢 | AS93: 华西-欧冶户头 | AU93: 2026-09-21由用户提供的台账数据整理后录入（9/18-9/20批次，Claude协助整理，用户确认）
A94: 93 | B94: 46283 | C94: 苏通源货6666 | D94: 船 | E94: 配票/反向 | F94: 反向 | H94: 尹鹏飞 | I94: 反向-尹鹏飞 | J94: 已结算 | K94: 646.85 | L94: 1563945.8 | M94: =Q94+S94-AA94-AC94-AD94 | N94: =IF(K94=0,0,M94/K94) | O94: 0 | Q94: 0 | R94: 25 | S94: 16171.25 | T94: 14 | U94: 1344993.4 | V94: 0 | W94: 0 | X94: 1563945.8 | Y94: 13.8 | Z94: 1348121.3 | AA94: -3127.8917 | AB94: 0 | AC94: 0 | AD94: 0 | AF94: 票商/反向 → 供货厂 → 欧冶 | AG94: 1563945.8 | AH94: 待登记 | AI94: 待登记 | AJ94: 未开始(前一环节未完成) | AK94: 未开始(前一环节未完成) | AL94: — | AM94: 0 | AN94: 46283 | AO94: 2026-09 | AP94: 7.97 | AR94: 华西特钢 | AS94: 华西-欧冶户头 | AU94: 2026-09-21由用户提供的台账数据整理后录入（9/18-9/20批次，Claude协助整理，用户确认）
A95: 94 | B95: 46284 | C95: 皖AP7737 | D95: 车 | E95: 配票/反向 | F95: 反向 | G95: 闫东朋 | H95: 闫东朋车队 | I95: 反向-闫东朋 | J95: 已结算 | K95: 30.22 | L95: 75852.2 | M95: =Q95+S95-AA95-AC95-AD95 | N95: =IF(K95=0,0,M95/K95) | O95: 0 | Q95: 0 | R95: 25 | S95: 755.5 | T95: 14 | U95: 65232.892 | V95: 0 | W95: 0 | X95: 75852.2 | Y95: 13.8 | Z95: 65384.596 | AA95: -151.7044 | AB95: 0 | AC95: 0 | AD95: 0 | AF95: 票商/反向 → 供货厂 → 欧冶 | AG95: 75852.2 | AH95: 待登记 | AI95: 待登记 | AJ95: 未开始(前一环节未完成) | AK95: 未开始(前一环节未完成) | AL95: — | AM95: 0 | AN95: 46284 | AO95: 2026-09 | AP95: 0.3 | AR95: 华西特钢 | AS95: 华西-欧冶户头 | AU95: 2026-09-21由用户提供的台账数据整理后录入（9/18-9/20批次，Claude协助整理，用户确认）
A96: 95 | B96: 46284 | C96: 苏GE2356 | D96: 车 | E96: 配票/反向 | F96: 配票 | G96: 林凯 | H96: 林凯车队 | I96: 煌烽 | J96: 已结算 | K96: 33.86 | L96: 78793.8 | M96: =Q96+S96-AA96-AC96-AD96 | N96: =IF(K96=0,0,M96/K96) | O96: 0 | Q96: 0 | R96: 25 | S96: 846.5 | T96: 14 | U96: 67762.668 | V96: 23 | W96: 778.78 | X96: 78015.02 | Y96: 13.2 | Z96: 67717.037 | AA96: 45.63064 | AB96: 0 | AC96: 0 | AD96: 100 | AF96: 我们配票（经俊兴） | AG96: 78015.02 | AH96: 待登记 | AI96: 待登记 | AJ96: 未开始(前一环节未完成) | AK96: 未开始(前一环节未完成) | AL96: 未开始(前一环节未完成) | AM96: 0 | AN96: 46284 | AO96: 2026-09 | AP96: 0.6 | AR96: 华西特钢 | AS96: 华西-欧冶户头 | AU96: 2026-09-21由用户提供的台账数据整理后录入（9/18-9/20批次，Claude协助整理，用户确认）
A97: 96 | B97: 46284 | C97: 苏NHY179 | D97: 车 | E97: 配票/反向 | F97: 配票 | G97: 林凯 | H97: 林凯车队 | I97: 煌烽 | J97: 已结算 | K97: 33.96 | L97: 78619.28 | M97: =Q97+S97-AA97-AC97-AD97 | N97: =IF(K97=0,0,M97/K97) | O97: 0 | Q97: 0 | R97: 25 | S97: 849 | T97: 14 | U97: 67612.581 | V97: 23 | W97: 781.08 | X97: 77838.2 | Y97: 13.2 | Z97: 67563.558 | AA97: 49.0232 | AB97: 0 | AC97: 0 | AD97: 100 | AF97: 我们配票（经俊兴） | AG97: 77838.2 | AH97: 待登记 | AI97: 待登记 | AJ97: 未开始(前一环节未完成) | AK97: 未开始(前一环节未完成) | AL97: 未开始(前一环节未完成) | AM97: 0 | AN97: 46284 | AO97: 2026-09 | AP97: 0.6 | AR97: 华西特钢 | AS97: 华西-欧冶户头 | AU97: 2026-09-21由用户提供的台账数据整理后录入（9/18-9/20批次，Claude协助整理，用户确认）
A98: 97 | B98: 46284 | C98: 皖SG1498 | D98: 车 | E98: 带票带货 | F98: 直签带票 | G98: 林凯 | H98: 兴德 | J98: 已结算 | K98: 30.06 | L98: 75450.6 | M98: =Q98+S98-AA98-AC98-AD98 | N98: =IF(K98=0,0,M98/K98) | O98: 0 | P98: 40 | Q98: 1202.4 | R98: 25 | S98: 751.5 | V98: 23 | W98: 691.38 | AA98: 691.38 | AB98: 15 | AC98: 450.9 | AD98: 0 | AF98: 供货厂自带票（带票带货） | AG98: 74759.22 | AH98: — | AI98: 待登记 | AJ98: 未开始(前一环节未完成) | AK98: — | AL98: — | AM98: 0 | AN98: 46284 | AO98: 2026-09 | AP98: 5.6 | AR98: 华西特钢 | AS98: 华西-欧冶户头 | AU98: 2026-09-21由用户提供的台账数据整理后录入（9/18-9/20批次，Claude协助整理，用户确认）
A99: 98 | B99: 46285 | C99: 苏DBB772 | D99: 车 | E99: 带票带货 | F99: 直签带票 | G99: 林凯 | H99: 君盛 | J99: 已结算 | K99: 32.12 | L99: 73940.24 | M99: =Q99+S99-AA99-AC99-AD99 | N99: =IF(K99=0,0,M99/K99) | O99: 0 | P99: 40 | Q99: 1284.8 | R99: 25 | S99: 803 | V99: 23 | W99: 738.76 | AA99: 738.76 | AB99: 15 | AC99: 481.8 | AD99: 0 | AF99: 供货厂自带票（带票带货） | AG99: 73201.48 | AH99: — | AI99: 待登记 | AJ99: 未开始(前一环节未完成) | AK99: — | AL99: — | AM99: 0 | AN99: 46285 | AO99: 2026-09 | AP99: 0.7 | AR99: 华西特钢 | AS99: 华西-欧冶户头 | AU99: 2026-09-21由用户提供的台账数据整理后录入（9/18-9/20批次，Claude协助整理，用户确认）
A100: 99 | B100: 46285 | C100: 苏DBE075 | D100: 车 | E100: 带票带货 | F100: 直签带票 | G100: 林凯 | H100: 君盛 | J100: 已结算 | K100: 32.72 | L100: 75321.44 | M100: =Q100+S100-AA100-AC100-AD100 | N100: =IF(K100=0,0,M100/K100) | O100: 0 | P100: 40 | Q100: 1308.8 | R100: 25 | S100: 818 | V100: 23 | W100: 752.56 | AA100: 752.56 | AB100: 15 | AC100: 490.8 | AD100: 0 | AF100: 供货厂自带票（带票带货） | AG100: 74568.88 | AH100: — | AI100: 待登记 | AJ100: 未开始(前一环节未完成) | AK100: — | AL100: — | AM100: 0 | AN100: 46285 | AO100: 2026-09 | AP100: 0.6 | AR100: 华西特钢 | AS100: 华西-欧冶户头 | AU100: 2026-09-21由用户提供的台账数据整理后录入（9/18-9/20批次，Claude协助整理，用户确认）
...

Sheet 统计汇总
A1: 统计汇总（导出 2026-09-21 13:26；全部为引用「车次台账」的公式，不含作废）
A3: 一、总体与利润构成
A4: 车次数 | B4: =COUNT('车次台账'!$A$3:$A$103)
A5: 结算吨位(吨) | B5: =SUM('车次台账'!$K$3:$K$103)
A6: 结算金额(元) | B6: =SUM('车次台账'!$L$3:$L$103)
A7: 毛服务费(元) | B7: =SUM('车次台账'!$Q$3:$Q$103)
A8: + 量补金额(元) | B8: =SUM('车次台账'!$S$3:$S$103)
A9: − 垫资成本(元) | B9: =SUM('车次台账'!$AA$3:$AA$103)
A10: − 调货人提成(元) | B10: =SUM('车次台账'!$AC$3:$AC$103)
A11: − 其他成本(元) | B11: =SUM('车次台账'!$AD$3:$AD$103)
A12: 净利润(元)（上面各项加减） | B12: =SUM('车次台账'!$M$3:$M$103)
A13: 单吨利润(元/吨) | B13: =IF(B5=0,0,B12/B5)
A14: 留存利润(元)·专项留存，不计入净利润 | B14: =SUM('车次台账'!$O$3:$O$103)
A16: 二、按路径（带票带货 / 配票·反向）
A17: 名称 | B17: 车次数 | C17: 吨位(吨) | D17: 结算金额(元) | E17: 净利润(元) | F17: 单吨利润(元/吨) | G17: 调货人提成(元) | H17: 留存利润(元)
A18: 配票/反向 | B18: =COUNTIFS('车次台账'!$E$3:$E$103,"配票/反向") | C18: =SUMIFS('车次台账'!$K$3:$K$103,'车次台账'!$E$3:$E$103,"配票/反向") | D18: =SUMIFS('车次台账'!$L$3:$L$103,'车次台账'!$E$3:$E$103,"配票/反向") | E18: =SUMIFS('车次台账'!$M$3:$M$103,'车次台账'!$E$3:$E$103,"配票/反向") | F18: =IF(C18=0,0,E18/C18) | G18: =SUMIFS('车次台账'!$AC$3:$AC$103,'车次台账'!$E$3:$E$103,"配票/反向") | H18: =SUMIFS('车次台账'!$O$3:$O$103,'车次台账'!$E$3:$E$103,"配票/反向")
A19: 带票带货 | B19: =COUNTIFS('车次台账'!$E$3:$E$103,"带票带货") | C19: =SUMIFS('车次台账'!$K$3:$K$103,'车次台账'!$E$3:$E$103,"带票带货") | D19: =SUMIFS('车次台账'!$L$3:$L$103,'车次台账'!$E$3:$E$103,"带票带货") | E19: =SUMIFS('车次台账'!$M$3:$M$103,'车次台账'!$E$3:$E$103,"带票带货") | F19: =IF(C19=0,0,E19/C19) | G19: =SUMIFS('车次台账'!$AC$3:$AC$103,'车次台账'!$E$3:$E$103,"带票带货") | H19: =SUMIFS('车次台账'!$O$3:$O$103,'车次台账'!$E$3:$E$103,"带票带货")
A20: 小计 | B20: =SUM(B18:B19) | C20: =SUM(C18:C19) | D20: =SUM(D18:D19) | E20: =SUM(E18:E19) | F20: =IF(C20=0,0,E20/C20) | G20: =SUM(G18:G19) | H20: =SUM(H18:H19)
A22: 三、按车/船
A23: 名称 | B23: 车次数 | C23: 吨位(吨) | D23: 结算金额(元) | E23: 净利润(元) | F23: 单吨利润(元/吨) | G23: 调货人提成(元) | H23: 留存利润(元)
A24: 车 | B24: =COUNTIFS('车次台账'!$D$3:$D$103,"车") | C24: =SUMIFS('车次台账'!$K$3:$K$103,'车次台账'!$D$3:$D$103,"车") | D24: =SUMIFS('车次台账'!$L$3:$L$103,'车次台账'!$D$3:$D$103,"车") | E24: =SUMIFS('车次台账'!$M$3:$M$103,'车次台账'!$D$3:$D$103,"车") | F24: =IF(C24=0,0,E24/C24) | G24: =SUMIFS('车次台账'!$AC$3:$AC$103,'车次台账'!$D$3:$D$103,"车") | H24: =SUMIFS('车次台账'!$O$3:$O$103,'车次台账'!$D$3:$D$103,"车")
A25: 船 | B25: =COUNTIFS('车次台账'!$D$3:$D$103,"船") | C25: =SUMIFS('车次台账'!$K$3:$K$103,'车次台账'!$D$3:$D$103,"船") | D25: =SUMIFS('车次台账'!$L$3:$L$103,'车次台账'!$D$3:$D$103,"船") | E25: =SUMIFS('车次台账'!$M$3:$M$103,'车次台账'!$D$3:$D$103,"船") | F25: =IF(C25=0,0,E25/C25) | G25: =SUMIFS('车次台账'!$AC$3:$AC$103,'车次台账'!$D$3:$D$103,"船") | H25: =SUMIFS('车次台账'!$O$3:$O$103,'车次台账'!$D$3:$D$103,"船")
A26: 小计 | B26: =SUM(B24:B25) | C26: =SUM(C24:C25) | D26: =SUM(D24:D25) | E26: =SUM(E24:E25) | F26: =IF(C26=0,0,E26/C26) | G26: =SUM(G24:G25) | H26: =SUM(H24:H25)
A28: 四、按链条规则
A29: 名称 | B29: 车次数 | C29: 吨位(吨) | D29: 结算金额(元) | E29: 净利润(元) | F29: 单吨利润(元/吨) | G29: 调货人提成(元) | H29: 留存利润(元)
A30: 反向 | B30: =COUNTIFS('车次台账'!$F$3:$F$103,"反向") | C30: =SUMIFS('车次台账'!$K$3:$K$103,'车次台账'!$F$3:$F$103,"反向") | D30: =SUMIFS('车次台账'!$L$3:$L$103,'车次台账'!$F$3:$F$103,"反向") | E30: =SUMIFS('车次台账'!$M$3:$M$103,'车次台账'!$F$3:$F$103,"反向") | F30: =IF(C30=0,0,E30/C30) | G30: =SUMIFS('车次台账'!$AC$3:$AC$103,'车次台账'!$F$3:$F$103,"反向") | H30: =SUMIFS('车次台账'!$O$3:$O$103,'车次台账'!$F$3:$F$103,"反向")
A31: 户头通道 | B31: =COUNTIFS('车次台账'!$F$3:$F$103,"户头通道") | C31: =SUMIFS('车次台账'!$K$3:$K$103,'车次台账'!$F$3:$F$103,"户头通道") | D31: =SUMIFS('车次台账'!$L$3:$L$103,'车次台账'!$F$3:$F$103,"户头通道") | E31: =SUMIFS('车次台账'!$M$3:$M$103,'车次台账'!$F$3:$F$103,"户头通道") | F31: =IF(C31=0,0,E31/C31) | G31: =SUMIFS('车次台账'!$AC$3:$AC$103,'车次台账'!$F$3:$F$103,"户头通道") | H31: =SUMIFS('车次台账'!$O$3:$O$103,'车次台账'!$F$3:$F$103,"户头通道")
A32: 直签带票 | B32: =COUNTIFS('车次台账'!$F$3:$F$103,"直签带票") | C32: =SUMIFS('车次台账'!$K$3:$K$103,'车次台账'!$F$3:$F$103,"直签带票") | D32: =SUMIFS('车次台账'!$L$3:$L$103,'车次台账'!$F$3:$F$103,"直签带票") | E32: =SUMIFS('车次台账'!$M$3:$M$103,'车次台账'!$F$3:$F$103,"直签带票") | F32: =IF(C32=0,0,E32/C32) | G32: =SUMIFS('车次台账'!$AC$3:$AC$103,'车次台账'!$F$3:$F$103,"直签带票") | H32: =SUMIFS('车次台账'!$O$3:$O$103,'车次台账'!$F$3:$F$103,"直签带票")
A33: 配票 | B33: =COUNTIFS('车次台账'!$F$3:$F$103,"配票") | C33: =SUMIFS('车次台账'!$K$3:$K$103,'车次台账'!$F$3:$F$103,"配票") | D33: =SUMIFS('车次台账'!$L$3:$L$103,'车次台账'!$F$3:$F$103,"配票") | E33: =SUMIFS('车次台账'!$M$3:$M$103,'车次台账'!$F$3:$F$103,"配票") | F33: =IF(C33=0,0,E33/C33) | G33: =SUMIFS('车次台账'!$AC$3:$AC$103,'车次台账'!$F$3:$F$103,"配票") | H33: =SUMIFS('车次台账'!$O$3:$O$103,'车次台账'!$F$3:$F$103,"配票")
A34: 小计 | B34: =SUM(B30:B33) | C34: =SUM(C30:C33) | D34: =SUM(D30:D33) | E34: =SUM(E30:E33) | F34: =IF(C34=0,0,E34/C34) | G34: =SUM(G30:G33) | H34: =SUM(H30:H33)
A36: 五、按调货人 | C36: 没填调货人的车次不在此表
A37: 名称 | B37: 车次数 | C37: 吨位(吨) | D37: 结算金额(元) | E37: 净利润(元) | F37: 单吨利润(元/吨) | G37: 调货人提成(元) | H37: 留存利润(元)
A38: 李涛 | B38: =COUNTIFS('车次台账'!$G$3:$G$103,"李涛") | C38: =SUMIFS('车次台账'!$K$3:$K$103,'车次台账'!$G$3:$G$103,"李涛") | D38: =SUMIFS('车次台账'!$L$3:$L$103,'车次台账'!$G$3:$G$103,"李涛") | E38: =SUMIFS('车次台账'!$M$3:$M$103,'车次台账'!$G$3:$G$103,"李涛") | F38: =IF(C38=0,0,E38/C38) | G38: =SUMIFS('车次台账'!$AC$3:$AC$103,'车次台账'!$G$3:$G$103,"李涛") | H38: =SUMIFS('车次台账'!$O$3:$O$103,'车次台账'!$G$3:$G$103,"李涛")
A39: 林凯 | B39: =COUNTIFS('车次台账'!$G$3:$G$103,"林凯") | C39: =SUMIFS('车次台账'!$K$3:$K$103,'车次台账'!$G$3:$G$103,"林凯") | D39: =SUMIFS('车次台账'!$L$3:$L$103,'车次台账'!$G$3:$G$103,"林凯") | E39: =SUMIFS('车次台账'!$M$3:$M$103,'车次台账'!$G$3:$G$103,"林凯") | F39: =IF(C39=0,0,E39/C39) | G39: =SUMIFS('车次台账'!$AC$3:$AC$103,'车次台账'!$G$3:$G$103,"林凯") | H39: =SUMIFS('车次台账'!$O$3:$O$103,'车次台账'!$G$3:$G$103,"林凯")
A40: 邓晶焱 | B40: =COUNTIFS('车次台账'!$G$3:$G$103,"邓晶焱") | C40: =SUMIFS('车次台账'!$K$3:$K$103,'车次台账'!$G$3:$G$103,"邓晶焱") | D40: =SUMIFS('车次台账'!$L$3:$L$103,'车次台账'!$G$3:$G$103,"邓晶焱") | E40: =SUMIFS('车次台账'!$M$3:$M$103,'车次台账'!$G$3:$G$103,"邓晶焱") | F40: =IF(C40=0,0,E40/C40) | G40: =SUMIFS('车次台账'!$AC$3:$AC$103,'车次台账'!$G$3:$G$103,"邓晶焱") | H40: =SUMIFS('车次台账'!$O$3:$O$103,'车次台账'!$G$3:$G$103,"邓晶焱")
A41: 闫东朋 | B41: =COUNTIFS('车次台账'!$G$3:$G$103,"闫东朋") | C41: =SUMIFS('车次台账'!$K$3:$K$103,'车次台账'!$G$3:$G$103,"闫东朋") | D41: =SUMIFS('车次台账'!$L$3:$L$103,'车次台账'!$G$3:$G$103,"闫东朋") | E41: =SUMIFS('车次台账'!$M$3:$M$103,'车次台账'!$G$3:$G$103,"闫东朋") | F41: =IF(C41=0,0,E41/C41) | G41: =SUMIFS('车次台账'!$AC$3:$AC$103,'车次台账'!$G$3:$G$103,"闫东朋") | H41: =SUMIFS('车次台账'!$O$3:$O$103,'车次台账'!$G$3:$G$103,"闫东朋")
A42: 陈杰 | B42: =COUNTIFS('车次台账'!$G$3:$G$103,"陈杰") | C42: =SUMIFS('车次台账'!$K$3:$K$103,'车次台账'!$G$3:$G$103,"陈杰") | D42: =SUMIFS('车次台账'!$L$3:$L$103,'车次台账'!$G$3:$G$103,"陈杰") | E42: =SUMIFS('车次台账'!$M$3:$M$103,'车次台账'!$G$3:$G$103,"陈杰") | F42: =IF(C42=0,0,E42/C42) | G42: =SUMIFS('车次台账'!$AC$3:$AC$103,'车次台账'!$G$3:$G$103,"陈杰") | H42: =SUMIFS('车次台账'!$O$3:$O$103,'车次台账'!$G$3:$G$103,"陈杰")
A43: 小计 | B43: =SUM(B38:B42) | C43: =SUM(C38:C42) | D43: =SUM(D38:D42) | E43: =SUM(E38:E42) | F43: =IF(C43=0,0,E43/C43) | G43: =SUM(G38:G42) | H43: =SUM(H38:H42)
A45: 六、按供货厂/车队
A46: 名称 | B46: 车次数 | C46: 吨位(吨) | D46: 结算金额(元) | E46: 净利润(元) | F46: 单吨利润(元/吨) | G46: 调货人提成(元) | H46: 留存利润(元)
A47: 俊兴 | B47: =COUNTIFS('车次台账'!$H$3:$H$103,"俊兴") | C47: =SUMIFS('车次台账'!$K$3:$K$103,'车次台账'!$H$3:$H$103,"俊兴") | D47: =SUMIFS('车次台账'!$L$3:$L$103,'车次台账'!$H$3:$H$103,"俊兴") | E47: =SUMIFS('车次台账'!$M$3:$M$103,'车次台账'!$H$3:$H$103,"俊兴") | F47: =IF(C47=0,0,E47/C47) | G47: =SUMIFS('车次台账'!$AC$3:$AC$103,'车次台账'!$H$3:$H$103,"俊兴") | H47: =SUMIFS('车次台账'!$O$3:$O$103,'车次台账'!$H$3:$H$103,"俊兴")
A48: 兴德 | B48: =COUNTIFS('车次台账'!$H$3:$H$103,"兴德") | C48: =SUMIFS('车次台账'!$K$3:$K$103,'车次台账'!$H$3:$H$103,"兴德") | D48: =SUMIFS('车次台账'!$L$3:$L$103,'车次台账'!$H$3:$H$103,"兴德") | E48: =SUMIFS('车次台账'!$M$3:$M$103,'车次台账'!$H$3:$H$103,"兴德") | F48: =IF(C48=0,0,E48/C48) | G48: =SUMIFS('车次台账'!$AC$3:$AC$103,'车次台账'!$H$3:$H$103,"兴德") | H48: =SUMIFS('车次台账'!$O$3:$O$103,'车次台账'!$H$3:$H$103,"兴德")
A49: 力拓 | B49: =COUNTIFS('车次台账'!$H$3:$H$103,"力拓") | C49: =SUMIFS('车次台账'!$K$3:$K$103,'车次台账'!$H$3:$H$103,"力拓") | D49: =SUMIFS('车次台账'!$L$3:$L$103,'车次台账'!$H$3:$H$103,"力拓") | E49: =SUMIFS('车次台账'!$M$3:$M$103,'车次台账'!$H$3:$H$103,"力拓") | F49: =IF(C49=0,0,E49/C49) | G49: =SUMIFS('车次台账'!$AC$3:$AC$103,'车次台账'!$H$3:$H$103,"力拓") | H49: =SUMIFS('车次台账'!$O$3:$O$103,'车次台账'!$H$3:$H$103,"力拓")
A50: 君盛 | B50: =COUNTIFS('车次台账'!$H$3:$H$103,"君盛") | C50: =SUMIFS('车次台账'!$K$3:$K$103,'车次台账'!$H$3:$H$103,"君盛") | D50: =SUMIFS('车次台账'!$L$3:$L$103,'车次台账'!$H$3:$H$103,"君盛") | E50: =SUMIFS('车次台账'!$M$3:$M$103,'车次台账'!$H$3:$H$103,"君盛") | F50: =IF(C50=0,0,E50/C50) | G50: =SUMIFS('车次台账'!$AC$3:$AC$103,'车次台账'!$H$3:$H$103,"君盛") | H50: =SUMIFS('车次台账'!$O$3:$O$103,'车次台账'!$H$3:$H$103,"君盛")
A51: 尹鹏飞 | B51: =COUNTIFS('车次台账'!$H$3:$H$103,"尹鹏飞") | C51: =SUMIFS('车次台账'!$K$3:$K$103,'车次台账'!$H$3:$H$103,"尹鹏飞") | D51: =SUMIFS('车次台账'!$L$3:$L$103,'车次台账'!$H$3:$H$103,"尹鹏飞") | E51: =SUMIFS('车次台账'!$M$3:$M$103,'车次台账'!$H$3:$H$103,"尹鹏飞") | F51: =IF(C51=0,0,E51/C51) | G51: =SUMIFS('车次台账'!$AC$3:$AC$103,'车次台账'!$H$3:$H$103,"尹鹏飞") | H51: =SUMIFS('车次台账'!$O$3:$O$103,'车次台账'!$H$3:$H$103,"尹鹏飞")
A52: 未填供货厂 | B52: =COUNTIFS('车次台账'!$H$3:$H$103,"未填供货厂") | C52: =SUMIFS('车次台账'!$K$3:$K$103,'车次台账'!$H$3:$H$103,"未填供货厂") | D52: =SUMIFS('车次台账'!$L$3:$L$103,'车次台账'!$H$3:$H$103,"未填供货厂") | E52: =SUMIFS('车次台账'!$M$3:$M$103,'车次台账'!$H$3:$H$103,"未填供货厂") | F52: =IF(C52=0,0,E52/C52) | G52: =SUMIFS('车次台账'!$AC$3:$AC$103,'车次台账'!$H$3:$H$103,"未填供货厂") | H52: =SUMIFS('车次台账'!$O$3:$O$103,'车次台账'!$H$3:$H$103,"未填供货厂")
A53: 李涛车队 | B53: =COUNTIFS('车次台账'!$H$3:$H$103,"李涛车队") | C53: =SUMIFS('车次台账'!$K$3:$K$103,'车次台账'!$H$3:$H$103,"李涛车队") | D53: =SUMIFS('车次台账'!$L$3:$L$103,'车次台账'!$H$3:$H$103,"李涛车队") | E53: =SUMIFS('车次台账'!$M$3:$M$103,'车次台账'!$H$3:$H$103,"李涛车队") | F53: =IF(C53=0,0,E53/C53) | G53: =SUMIFS('车次台账'!$AC$3:$AC$103,'车次台账'!$H$3:$H$103,"李涛车队") | H53: =SUMIFS('车次台账'!$O$3:$O$103,'车次台账'!$H$3:$H$103,"李涛车队")
A54: 林凯车队 | B54: =COUNTIFS('车次台账'!$H$3:$H$103,"林凯车队") | C54: =SUMIFS('车次台账'!$K$3:$K$103,'车次台账'!$H$3:$H$103,"林凯车队") | D54: =SUMIFS('车次台账'!$L$3:$L$103,'车次台账'!$H$3:$H$103,"林凯车队") | E54: =SUMIFS('车次台账'!$M$3:$M$103,'车次台账'!$H$3:$H$103,"林凯车队") | F54: =IF(C54=0,0,E54/C54) | G54: =SUMIFS('车次台账'!$AC$3:$AC$103,'车次台账'!$H$3:$H$103,"林凯车队") | H54: =SUMIFS('车次台账'!$O$3:$O$103,'车次台账'!$H$3:$H$103,"林凯车队")
A55: 邓晶焱车队 | B55: =COUNTIFS('车次台账'!$H$3:$H$103,"邓晶焱车队") | C55: =SUMIFS('车次台账'!$K$3:$K$103,'车次台账'!$H$3:$H$103,"邓晶焱车队") | D55: =SUMIFS('车次台账'!$L$3:$L$103,'车次台账'!$H$3:$H$103,"邓晶焱车队") | E55: =SUMIFS('车次台账'!$M$3:$M$103,'车次台账'!$H$3:$H$103,"邓晶焱车队") | F55: =IF(C55=0,0,E55/C55) | G55: =SUMIFS('车次台账'!$AC$3:$AC$103,'车次台账'!$H$3:$H$103,"邓晶焱车队") | H55: =SUMIFS('车次台账'!$O$3:$O$103,'车次台账'!$H$3:$H$103,"邓晶焱车队")
A56: 闫东朋车队 | B56: =COUNTIFS('车次台账'!$H$3:$H$103,"闫东朋车队") | C56: =SUMIFS('车次台账'!$K$3:$K$103,'车次台账'!$H$3:$H$103,"闫东朋车队") | D56: =SUMIFS('车次台账'!$L$3:$L$103,'车次台账'!$H$3:$H$103,"闫东朋车队") | E56: =SUMIFS('车次台账'!$M$3:$M$103,'车次台账'!$H$3:$H$103,"闫东朋车队") | F56: =IF(C56=0,0,E56/C56) | G56: =SUMIFS('车次台账'!$AC$3:$AC$103,'车次台账'!$H$3:$H$103,"闫东朋车队") | H56: =SUMIFS('车次台账'!$O$3:$O$103,'车次台账'!$H$3:$H$103,"闫东朋车队")
A57: 陈杰车队 | B57: =COUNTIFS('车次台账'!$H$3:$H$103,"陈杰车队") | C57: =SUMIFS('车次台账'!$K$3:$K$103,'车次台账'!$H$3:$H$103,"陈杰车队") | D57: =SUMIFS('车次台账'!$L$3:$L$103,'车次台账'!$H$3:$H$103,"陈杰车队") | E57: =SUMIFS('车次台账'!$M$3:$M$103,'车次台账'!$H$3:$H$103,"陈杰车队") | F57: =IF(C57=0,0,E57/C57) | G57: =SUMIFS('车次台账'!$AC$3:$AC$103,'车次台账'!$H$3:$H$103,"陈杰车队") | H57: =SUMIFS('车次台账'!$O$3:$O$103,'车次台账'!$H$3:$H$103,"陈杰车队")
A58: 𠓾景通 | B58: =COUNTIFS('车次台账'!$H$3:$H$103,"𠓾景通") | C58: =SUMIFS('车次台账'!$K$3:$K$103,'车次台账'!$H$3:$H$103,"𠓾景通") | D58: =SUMIFS('车次台账'!$L$3:$L$103,'车次台账'!$H$3:$H$103,"𠓾景通") | E58: =SUMIFS('车次台账'!$M$3:$M$103,'车次台账'!$H$3:$H$103,"𠓾景通") | F58: =IF(C58=0,0,E58/C58) | G58: =SUMIFS('车次台账'!$AC$3:$AC$103,'车次台账'!$H$3:$H$103,"𠓾景通") | H58: =SUMIFS('车次台账'!$O$3:$O$103,'车次台账'!$H$3:$H$103,"𠓾景通")
A59: 小计 | B59: =SUM(B47:B58) | C59: =SUM(C47:C58) | D59: =SUM(D47:D58) | E59: =SUM(E47:E58) | F59: =IF(C59=0,0,E59/C59) | G59: =SUM(G47:G58) | H59: =SUM(H47:H58)
A61: 七、按票源方 | C61: 带票带货(无票源)的车次不在此表
A62: 名称 | B62: 车次数 | C62: 吨位(吨) | D62: 结算金额(元) | E62: 净利润(元) | F62: 单吨利润(元/吨) | G62: 调货人提成(元) | H62: 留存利润(元)
A63: 俊兴 | B63: =COUNTIFS('车次台账'!$I$3:$I$103,"俊兴") | C63: =SUMIFS('车次台账'!$K$3:$K$103,'车次台账'!$I$3:$I$103,"俊兴") | D63: =SUMIFS('车次台账'!$L$3:$L$103,'车次台账'!$I$3:$I$103,"俊兴") | E63: =SUMIFS('车次台账'!$M$3:$M$103,'车次台账'!$I$3:$I$103,"俊兴") | F63: =IF(C63=0,0,E63/C63) | G63: =SUMIFS('车次台账'!$AC$3:$AC$103,'车次台账'!$I$3:$I$103,"俊兴") | H63: =SUMIFS('车次台账'!$O$3:$O$103,'车次台账'!$I$3:$I$103,"俊兴")
A64: 反向-尹鹏飞 | B64: =COUNTIFS('车次台账'!$I$3:$I$103,"反向-尹鹏飞") | C64: =SUMIFS('车次台账'!$K$3:$K$103,'车次台账'!$I$3:$I$103,"反向-尹鹏飞") | D64: =SUMIFS('车次台账'!$L$3:$L$103,'车次台账'!$I$3:$I$103,"反向-尹鹏飞") | E64: =SUMIFS('车次台账'!$M$3:$M$103,'车次台账'!$I$3:$I$103,"反向-尹鹏飞") | F64: =IF(C64=0,0,E64/C64) | G64: =SUMIFS('车次台账'!$AC$3:$AC$103,'车次台账'!$I$3:$I$103,"反向-尹鹏飞") | H64: =SUMIFS('车次台账'!$O$3:$O$103,'车次台账'!$I$3:$I$103,"反向-尹鹏飞")
A65: 反向-闫东朋 | B65: =COUNTIFS('车次台账'!$I$3:$I$103,"反向-闫东朋") | C65: =SUMIFS('车次台账'!$K$3:$K$103,'车次台账'!$I$3:$I$103,"反向-闫东朋") | D65: =SUMIFS('车次台账'!$L$3:$L$103,'车次台账'!$I$3:$I$103,"反向-闫东朋") | E65: =SUMIFS('车次台账'!$M$3:$M$103,'车次台账'!$I$3:$I$103,"反向-闫东朋") | F65: =IF(C65=0,0,E65/C65) | G65: =SUMIFS('车次台账'!$AC$3:$AC$103,'车次台账'!$I$3:$I$103,"反向-闫东朋") | H65: =SUMIFS('车次台账'!$O$3:$O$103,'车次台账'!$I$3:$I$103,"反向-闫东朋")
A66: 煌烽 | B66: =COUNTIFS('车次台账'!$I$3:$I$103,"煌烽") | C66: =SUMIFS('车次台账'!$K$3:$K$103,'车次台账'!$I$3:$I$103,"煌烽") | D66: =SUMIFS('车次台账'!$L$3:$L$103,'车次台账'!$I$3:$I$103,"煌烽") | E66: =SUMIFS('车次台账'!$M$3:$M$103,'车次台账'!$I$3:$I$103,"煌烽") | F66: =IF(C66=0,0,E66/C66) | G66: =SUMIFS('车次台账'!$AC$3:$AC$103,'车次台账'!$I$3:$I$103,"煌烽") | H66: =SUMIFS('车次台账'!$O$3:$O$103,'车次台账'!$I$3:$I$103,"煌烽")
A67: 益周 | B67: =COUNTIFS('车次台账'!$I$3:$I$103,"益周") | C67: =SUMIFS('车次台账'!$K$3:$K$103,'车次台账'!$I$3:$I$103,"益周") | D67: =SUMIFS('车次台账'!$L$3:$L$103,'车次台账'!$I$3:$I$103,"益周") | E67: =SUMIFS('车次台账'!$M$3:$M$103,'车次台账'!$I$3:$I$103,"益周") | F67: =IF(C67=0,0,E67/C67) | G67: =SUMIFS('车次台账'!$AC$3:$AC$103,'车次台账'!$I$3:$I$103,"益周") | H67: =SUMIFS('车次台账'!$O$3:$O$103,'车次台账'!$I$3:$I$103,"益周")
A68: 小计 | B68: =SUM(B63:B67) | C68: =SUM(C63:C67) | D68: =SUM(D63:D67) | E68: =SUM(E63:E67) | F68: =IF(C68=0,0,E68/C68) | G68: =SUM(G63:G67) | H68: =SUM(H63:H67)
A70: 八、按状态
A71: 名称 | B71: 车次数 | C71: 吨位(吨) | D71: 结算金额(元) | E71: 净利润(元) | F71: 单吨利润(元/吨) | G71: 调货人提成(元) | H71: 留存利润(元)
A72: 已结算 | B72: =COUNTIFS('车次台账'!$J$3:$J$103,"已结算") | C72: =SUMIFS('车次台账'!$K$3:$K$103,'车次台账'!$J$3:$J$103,"已结算") | D72: =SUMIFS('车次台账'!$L$3:$L$103,'车次台账'!$J$3:$J$103,"已结算") | E72: =SUMIFS('车次台账'!$M$3:$M$103,'车次台账'!$J$3:$J$103,"已结算") | F72: =IF(C72=0,0,E72/C72) | G72: =SUMIFS('车次台账'!$AC$3:$AC$103,'车次台账'!$J$3:$J$103,"已结算") | H72: =SUMIFS('车次台账'!$O$3:$O$103,'车次台账'!$J$3:$J$103,"已结算")
A73: 已开票 | B73: =COUNTIFS('车次台账'!$J$3:$J$103,"已开票") | C73: =SUMIFS('车次台账'!$K$3:$K$103,'车次台账'!$J$3:$J$103,"已开票") | D73: =SUMIFS('车次台账'!$L$3:$L$103,'车次台账'!$J$3:$J$103,"已开票") | E73: =SUMIFS('车次台账'!$M$3:$M$103,'车次台账'!$J$3:$J$103,"已开票") | F73: =IF(C73=0,0,E73/C73) | G73: =SUMIFS('车次台账'!$AC$3:$AC$103,'车次台账'!$J$3:$J$103,"已开票") | H73: =SUMIFS('车次台账'!$O$3:$O$103,'车次台账'!$J$3:$J$103,"已开票")
A74: 小计 | B74: =SUM(B72:B73) | C74: =SUM(C72:C73) | D74: =SUM(D72:D73) | E74: =SUM(E72:E73) | F74: =IF(C74=0,0,E74/C74) | G74: =SUM(G72:G73) | H74: =SUM(H72:H73)
A76: 九、按结算月份
A77: 月份 | B77: 车次数 | C77: 吨位(吨) | D77: 结算金额(元) | E77: 净利润(元) | F77: 单吨利润(元/吨)
A78: 2026-08 | B78: =COUNTIFS('车次台账'!$AO$3:$AO$103,"2026-08") | C78: =SUMIFS('车次台账'!$K$3:$K$103,'车次台账'!$AO$3:$AO$103,"2026-08") | D78: =SUMIFS('车次台账'!$L$3:$L$103,'车次台账'!$AO$3:$AO$103,"2026-08") | E78: =SUMIFS('车次台账'!$M$3:$M$103,'车次台账'!$AO$3:$AO$103,"2026-08") | F78: =IF(C78=0,0,E78/C78)
A79: 2026-09 | B79: =COUNTIFS('车次台账'!$AO$3:$AO$103,"2026-09") | C79: =SUMIFS('车次台账'!$K$3:$K$103,'车次台账'!$AO$3:$AO$103,"2026-09") | D79: =SUMIFS('车次台账'!$L$3:$L$103,'车次台账'!$AO$3:$AO$103,"2026-09") | E79: =SUMIFS('车次台账'!$M$3:$M$103,'车次台账'!$AO$3:$AO$103,"2026-09") | F79: =IF(C79=0,0,E79/C79)
A81: 十、票款环节（引用「票款追踪」） | C81: 待登记 = 应登记 − 已登记；历史车次未补登批次前，回款环节会显示为待登记
A82: 环节 | B82: 涉及车次 | C82: 应登记(元) | D82: 已登记(元) | E82: 待登记(元) | F82: 待登记车次
A83: 进项 | B83: =COUNTIFS('票款追踪'!$H$2:$H$341,"进项") | C83: =SUMIFS('票款追踪'!$K$2:$K$341,'票款追踪'!$H$2:$H$341,"进项") | D83: =SUMIFS('票款追踪'!$L$2:$L$341,'票款追踪'!$H$2:$H$341,"进项") | E83: =SUMIFS('票款追踪'!$M$2:$M$341,'票款追踪'!$H$2:$H$341,"进项") | F83: =COUNTIFS('票款追踪'!$H$2:$H$341,"进项",'票款追踪'!$M$2:$M$341,">0")
A84: 销项→欧冶 | B84: =COUNTIFS('票款追踪'!$H$2:$H$341,"销项→欧冶") | C84: =SUMIFS('票款追踪'!$K$2:$K$341,'票款追踪'!$H$2:$H$341,"销项→欧冶") | D84: =SUMIFS('票款追踪'!$L$2:$L$341,'票款追踪'!$H$2:$H$341,"销项→欧冶") | E84: =SUMIFS('票款追踪'!$M$2:$M$341,'票款追踪'!$H$2:$H$341,"销项→欧冶") | F84: =COUNTIFS('票款追踪'!$H$2:$H$341,"销项→欧冶",'票款追踪'!$M$2:$M$341,">0")
A85: 欧冶回款 | B85: =COUNTIFS('票款追踪'!$H$2:$H$341,"欧冶回款") | C85: =SUMIFS('票款追踪'!$K$2:$K$341,'票款追踪'!$H$2:$H$341,"欧冶回款") | D85: =SUMIFS('票款追踪'!$L$2:$L$341,'票款追踪'!$H$2:$H$341,"欧冶回款") | E85: =SUMIFS('票款追踪'!$M$2:$M$341,'票款追踪'!$H$2:$H$341,"欧冶回款") | F85: =COUNTIFS('票款追踪'!$H$2:$H$341,"欧冶回款",'票款追踪'!$M$2:$M$341,">0")
A86: 付票源 | B86: =COUNTIFS('票款追踪'!$H$2:$H$341,"付票源") | C86: =SUMIFS('票款追踪'!$K$2:$K$341,'票款追踪'!$H$2:$H$341,"付票源") | D86: =SUMIFS('票款追踪'!$L$2:$L$341,'票款追踪'!$H$2:$H$341,"付票源") | E86: =SUMIFS('票款追踪'!$M$2:$M$341,'票款追踪'!$H$2:$H$341,"付票源") | F86: =COUNTIFS('票款追踪'!$H$2:$H$341,"付票源",'票款追踪'!$M$2:$M$341,">0")
A87: 到客户账户 | B87: =COUNTIFS('票款追踪'!$H$2:$H$341,"到客户账户") | C87: =SUMIFS('票款追踪'!$K$2:$K$341,'票款追踪'!$H$2:$H$341,"到客户账户") | D87: =SUMIFS('票款追踪'!$L$2:$L$341,'票款追踪'!$H$2:$H$341,"到客户账户") | E87: =SUMIFS('票款追踪'!$M$2:$M$341,'票款追踪'!$H$2:$H$341,"到客户账户") | F87: =COUNTIFS('票款追踪'!$H$2:$H$341,"到客户账户",'票款追踪'!$M$2:$M$341,">0")
A89: 十一、调货人提成 应付/已付/未付
A90: 调货人 | B90: 车次数 | C90: 吨位(吨) | D90: 应付提成(元) | E90: 已付(元) | F90: 未付(元)
A91: 李涛 | B91: =COUNTIFS('车次台账'!$G$3:$G$103,"李涛") | C91: =SUMIFS('车次台账'!$K$3:$K$103,'车次台账'!$G$3:$G$103,"李涛") | D91: =SUMIFS('车次台账'!$AC$3:$AC$103,'车次台账'!$G$3:$G$103,"李涛") | E91: =SUMIFS('车次台账'!$AM$3:$AM$103,'车次台账'!$G$3:$G$103,"李涛") | F91: =D91-E91
A92: 林凯 | B92: =COUNTIFS('车次台账'!$G$3:$G$103,"林凯") | C92: =SUMIFS('车次台账'!$K$3:$K$103,'车次台账'!$G$3:$G$103,"林凯") | D92: =SUMIFS('车次台账'!$AC$3:$AC$103,'车次台账'!$G$3:$G$103,"林凯") | E92: =SUMIFS('车次台账'!$AM$3:$AM$103,'车次台账'!$G$3:$G$103,"林凯") | F92: =D92-E92
A93: 邓晶焱 | B93: =COUNTIFS('车次台账'!$G$3:$G$103,"邓晶焱") | C93: =SUMIFS('车次台账'!$K$3:$K$103,'车次台账'!$G$3:$G$103,"邓晶焱") | D93: =SUMIFS('车次台账'!$AC$3:$AC$103,'车次台账'!$G$3:$G$103,"邓晶焱") | E93: =SUMIFS('车次台账'!$AM$3:$AM$103,'车次台账'!$G$3:$G$103,"邓晶焱") | F93: =D93-E93
A94: 闫东朋 | B94: =COUNTIFS('车次台账'!$G$3:$G$103,"闫东朋") | C94: =SUMIFS('车次台账'!$K$3:$K$103,'车次台账'!$G$3:$G$103,"闫东朋") | D94: =SUMIFS('车次台账'!$AC$3:$AC$103,'车次台账'!$G$3:$G$103,"闫东朋") | E94: =SUMIFS('车次台账'!$AM$3:$AM$103,'车次台账'!$G$3:$G$103,"闫东朋") | F94: =D94-E94
A95: 陈杰 | B95: =COUNTIFS('车次台账'!$G$3:$G$103,"陈杰") | C95: =SUMIFS('车次台账'!$K$3:$K$103,'车次台账'!$G$3:$G$103,"陈杰") | D95: =SUMIFS('车次台账'!$AC$3:$AC$103,'车次台账'!$G$3:$G$103,"陈杰") | E95: =SUMIFS('车次台账'!$AM$3:$AM$103,'车次台账'!$G$3:$G$103,"陈杰") | F95: =D95-E95
A97: 十二、质量：各货型（引用「磅重明细」）
A98: 货型 | B98: 吨位(吨) | C98: 金额(元) | D98: 均价(元/吨) | E98: 扣杂(吨)
A99: 中废1 | B99: =SUMIFS('磅重明细'!$L$2:$L$131,'磅重明细'!$J$2:$J$131,"中废1") | C99: =SUMIFS('磅重明细'!$O$2:$O$131,'磅重明细'!$J$2:$J$131,"中废1") | D99: =IF(B99=0,0,C99/B99) | E99: =SUMIFS('磅重明细'!$K$2:$K$131,'磅重明细'!$J$2:$J$131,"中废1")
A100: 中废2 | B100: =SUMIFS('磅重明细'!$L$2:$L$131,'磅重明细'!$J$2:$J$131,"中废2") | C100: =SUMIFS('磅重明细'!$O$2:$O$131,'磅重明细'!$J$2:$J$131,"中废2") | D100: =IF(B100=0,0,C100/B100) | E100: =SUMIFS('磅重明细'!$K$2:$K$131,'磅重明细'!$J$2:$J$131,"中废2")
A101: 剪切中废1 | B101: =SUMIFS('磅重明细'!$L$2:$L$131,'磅重明细'!$J$2:$J$131,"剪切中废1") | C101: =SUMIFS('磅重明细'!$O$2:$O$131,'磅重明细'!$J$2:$J$131,"剪切中废1") | D101: =IF(B101=0,0,C101/B101) | E101: =SUMIFS('磅重明细'!$K$2:$K$131,'磅重明细'!$J$2:$J$131,"剪切中废1")
A102: 小废 | B102: =SUMIFS('磅重明细'!$L$2:$L$131,'磅重明细'!$J$2:$J$131,"小废") | C102: =SUMIFS('磅重明细'!$O$2:$O$131,'磅重明细'!$J$2:$J$131,"小废") | D102: =IF(B102=0,0,C102/B102) | E102: =SUMIFS('磅重明细'!$K$2:$K$131,'磅重明细'!$J$2:$J$131,"小废")
A103: 废钢压块1 | B103: =SUMIFS('磅重明细'!$L$2:$L$131,'磅重明细'!$J$2:$J$131,"废钢压块1") | C103: =SUMIFS('磅重明细'!$O$2:$O$131,'磅重明细'!$J$2:$J$131,"废钢压块1") | D103: =IF(B103=0,0,C103/B103) | E103: =SUMIFS('磅重明细'!$K$2:$K$131,'磅重明细'!$J$2:$J$131,"废钢压块1")
A104: 废钢压块2 | B104: =SUMIFS('磅重明细'!$L$2:$L$131,'磅重明细'!$J$2:$J$131,"废钢压块2") | C104: =SUMIFS('磅重明细'!$O$2:$O$131,'磅重明细'!$J$2:$J$131,"废钢压块2") | D104: =IF(B104=0,0,C104/B104) | E104: =SUMIFS('磅重明细'!$K$2:$K$131,'磅重明细'!$J$2:$J$131,"废钢压块2")
A105: 废钢压块3 | B105: =SUMIFS('磅重明细'!$L$2:$L$131,'磅重明细'!$J$2:$J$131,"废钢压块3") | C105: =SUMIFS('磅重明细'!$O$2:$O$131,'磅重明细'!$J$2:$J$131,"废钢压块3") | D105: =IF(B105=0,0,C105/B105) | E105: =SUMIFS('磅重明细'!$K$2:$K$131,'磅重明细'!$J$2:$J$131,"废钢压块3")
A106: 普通压块 | B106: =SUMIFS('磅重明细'!$L$2:$L$131,'磅重明细'!$J$2:$J$131,"普通压块") | C106: =SUMIFS('磅重明细'!$O$2:$O$131,'磅重明细'!$J$2:$J$131,"普通压块") | D106: =IF(B106=0,0,C106/B106) | E106: =SUMIFS('磅重明细'!$K$2:$K$131,'磅重明细'!$J$2:$J$131,"普通压块")
A107: 未分货型(混料) | B107: =SUMIFS('磅重明细'!$L$2:$L$131,'磅重明细'!$J$2:$J$131,"未分货型(混料)") | C107: =SUMIFS('磅重明细'!$O$2:$O$131,'磅重明细'!$J$2:$J$131,"未分货型(混料)") | D107: =IF(B107=0,0,C107/B107) | E107: =SUMIFS('磅重明细'!$K$2:$K$131,'磅重明细'!$J$2:$J$131,"未分货型(混料)")
A108: 未注明 | B108: =SUMIFS('磅重明细'!$L$2:$L$131,'磅重明细'!$J$2:$J$131,"未注明") | C108: =SUMIFS('磅重明细'!$O$2:$O$131,'磅重明细'!$J$2:$J$131,"未注明") | D108: =IF(B108=0,0,C108/B108) | E108: =SUMIFS('磅重明细'!$K$2:$K$131,'磅重明细'!$J$2:$J$131,"未注明")
A109: 边角料压块1 | B109: =SUMIFS('磅重明细'!$L$2:$L$131,'磅重明细'!$J$2:$J$131,"边角料压块1") | C109: =SUMIFS('磅重明细'!$O$2:$O$131,'磅重明细'!$J$2:$J$131,"边角料压块1") | D109: =IF(B109=0,0,C109/B109) | E109: =SUMIFS('磅重明细'!$K$2:$K$131,'磅重明细'!$J$2:$J$131,"边角料压块1")
A110: 重废1 | B110: =SUMIFS('磅重明细'!$L$2:$L$131,'磅重明细'!$J$2:$J$131,"重废1") | C110: =SUMIFS('磅重明细'!$O$2:$O$131,'磅重明细'!$J$2:$J$131,"重废1") | D110: =IF(B110=0,0,C110/B110) | E110: =SUMIFS('磅重明细'!$K$2:$K$131,'磅重明细'!$J$2:$J$131,"重废1")
A111: 重废2 | B111: =SUMIFS('磅重明细'!$L$2:$L$131,'磅重明细'!$J$2:$J$131,"重废2") | C111: =SUMIFS('磅重明细'!$O$2:$O$131,'磅重明细'!$J$2:$J$131,"重废2") | D111: =IF(B111=0,0,C111/B111) | E111: =SUMIFS('磅重明细'!$K$2:$K$131,'磅重明细'!$J$2:$J$131,"重废2")
A112: 重废3 | B112: =SUMIFS('磅重明细'!$L$2:$L$131,'磅重明细'!$J$2:$J$131,"重废3") | C112: =SUMIFS('磅重明细'!$O$2:$O$131,'磅重明细'!$J$2:$J$131,"重废3") | D112: =IF(B112=0,0,C112/B112) | E112: =SUMIFS('磅重明细'!$K$2:$K$131,'磅重明细'!$J$2:$J$131,"重废3")
...

Sheet 磅重明细
A1: 车次ID | B1: 结算日期 | C1: 车号/船号 | D1: 车/船 | E1: 路径 | F1: 链条 | G1: 调货人 | H1: 供货厂/车队 | I1: 货型大类 | J1: 货型 | K1: 扣杂(吨) | L1: 结算吨数(吨) | M1: 单价(元/吨) | N1: 切割费(元) | O1: 金额(元)
A2: 1 | B2: 46253 | C2: 苏DBB772 | D2: 车 | E2: 配票/反向 | F2: 配票 | G2: 林凯 | H2: 林凯车队 | I2: 废钢压块类 | J2: 废钢压块2 | K2: 0.9 | L2: 73.58 | M2: 2290 | N2: 0 | O2: 168498.2
A3: 2 | B3: 46254 | C3: 苏DFM060 | D3: 车 | E3: 配票/反向 | F3: 配票 | G3: 林凯 | H3: 林凯车队 | I3: 废钢 | J3: 中废1 | K3: 0.5 | L3: 34.8 | M3: 2430 | N3: 0 | O3: 84564
A4: 3 | B4: 46255 | C4: 苏DBB772 | D4: 车 | E4: 配票/反向 | F4: 配票 | G4: 林凯 | H4: 林凯车队 | I4: 铁水罐压块类 | J4: 铁加压块 | K4: 0.8 | L4: 81.16 | M4: 2480 | N4: 0 | O4: 201276.8
A5: 4 | B5: 46255 | C5: 皖M2A505 | D5: 车 | E5: 配票/反向 | F5: 配票 | H5: 俊兴 | I5: 废钢压块类 | J5: 废钢压块2 | K5: 0.3 | L5: 36.36 | M5: 2290 | N5: 0 | O5: 83264.4
A6: 5 | B6: 46255 | C6: 苏EQB977 | D6: 车 | E6: 配票/反向 | F6: 配票 | H6: 俊兴 | I6: 废钢压块类 | J6: 废钢压块2 | K6: 0.3 | L6: 32.94 | M6: 2290 | N6: 0 | O6: 75432.6
A7: 6 | B7: 46255 | C7: 苏BUK952 | D7: 车 | E7: 配票/反向 | F7: 配票 | G7: 林凯 | H7: 林凯车队 | I7: 废钢 | J7: 中废1 | K7: 0.175 | L7: 17.087 | M7: 2430 | N7: 0 | O7: 41521.41
A8: 6 | B8: 46255 | C8: 苏BUK952 | D8: 车 | E8: 配票/反向 | F8: 配票 | G8: 林凯 | H8: 林凯车队 | I8: 废钢 | J8: 中废2 | K8: 0.075 | L8: 7.323 | M8: 2390 | N8: 0 | O8: 17501.97
A9: 7 | B9: 46256 | C9: 苏DBB772 | D9: 车 | E9: 配票/反向 | F9: 配票 | G9: 林凯 | H9: 林凯车队 | I9: 废钢压块类 | J9: 废钢压块2 | K9: 1.4 | L9: 69.5 | M9: 2290 | N9: 0 | O9: 159155
A10: 8 | B10: 46256 | C10: 苏E9W908 | D10: 车 | E10: 配票/反向 | F10: 配票 | G10: 邓晶焱 | H10: 邓晶焱车队 | I10: 废钢压块类 | J10: 废钢压块1 | K10: 1 | L10: 39.16 | M10: 2330 | N10: 0 | O10: 91242.8
A11: 9 | B11: 46256 | C11: 苏MAK862 | D11: 车 | E11: 配票/反向 | F11: 配票 | H11: 俊兴 | I11: 废钢压块类 | J11: 废钢压块2 | K11: 0.6 | L11: 34.24 | M11: 2290 | N11: 0 | O11: 78409.6
A12: 10 | B12: 46259 | C12: 苏DBE075 | D12: 车 | E12: 配票/反向 | F12: 配票 | G12: 林凯 | H12: 林凯车队 | I12: 废钢压块类 | J12: 废钢压块2 | K12: 0.84 | L12: 56.7 | M12: 2260 | N12: 0 | O12: 128142
A13: 10 | B13: 46259 | C13: 苏DBE075 | D13: 车 | E13: 配票/反向 | F13: 配票 | G13: 林凯 | H13: 林凯车队 | I13: 废钢压块类 | J13: 废钢压块3 | K13: 0.36 | L13: 24.3 | M13: 2300 | N13: 0 | O13: 55890
A14: 11 | B14: 46261 | C14: 苏淮货16776 | D14: 船 | E14: 配票/反向 | F14: 配票 | H14: 俊兴 | I14: 历史导入-待归类 | J14: 未注明 | K14: 0 | L14: 560.39 | N14: 0 | O14: 1344115.9
A15: 12 | B15: 46261 | C15: 苏NEX375 | D15: 车 | E15: 配票/反向 | F15: 配票 | G15: 林凯 | H15: 林凯车队 | I15: 废钢压块类 | J15: 废钢压块2 | K15: 0.45 | L15: 40.27 | M15: 2320 | N15: 0 | O15: 93426.4
A16: 13 | B16: 46261 | C16: 苏DFM060 | D16: 车 | E16: 配票/反向 | F16: 配票 | G16: 林凯 | H16: 林凯车队 | I16: 废钢 | J16: 中废1 | K16: 0.1 | L16: 17.15 | M16: 2440 | N16: 0 | O16: 41846
A17: 13 | B17: 46261 | C17: 苏DFM060 | D17: 车 | E17: 配票/反向 | F17: 配票 | G17: 林凯 | H17: 林凯车队 | I17: 废钢 | J17: 剪切中废1 | K17: 0.1 | L17: 17.15 | M17: 2470 | N17: 0 | O17: 42360.5
A18: 14 | B18: 46261 | C18: 苏DBB772 | D18: 车 | E18: 配票/反向 | F18: 配票 | G18: 林凯 | H18: 君盛 | I18: 废钢压块类 | J18: 普通压块 | K18: 1 | L18: 66.22 | M18: 2240 | N18: 0 | O18: 148332.8
A19: 15 | B19: 46261 | C19: 苏BDK567 | D19: 车 | E19: 配票/反向 | F19: 配票 | G19: 林凯 | H19: 林凯车队 | I19: 废钢 | J19: 中废1 | K19: 0.125 | L19: 16.025 | M19: 2440 | N19: 0 | O19: 39101
A20: 15 | B20: 46261 | C20: 苏BDK567 | D20: 车 | E20: 配票/反向 | F20: 配票 | G20: 林凯 | H20: 林凯车队 | I20: 废钢 | J20: 剪切中废1 | K20: 0.125 | L20: 16.025 | M20: 2470 | N20: 0 | O20: 39581.75
A21: 16 | B21: 46261 | C21: 苏BZP839 | D21: 车 | E21: 配票/反向 | F21: 配票 | G21: 林凯 | H21: 林凯车队 | I21: 废钢 | J21: 中废2 | K21: 0.315 | L21: 19.929 | M21: 2400 | N21: 70 | O21: 47759.6
A22: 16 | B22: 46261 | C22: 苏BZP839 | D22: 车 | E22: 配票/反向 | F22: 配票 | G22: 林凯 | H22: 林凯车队 | I22: 废钢 | J22: 中废1 | K22: 0.135 | L22: 8.541 | M22: 2440 | N22: 30 | O22: 20810.04
A23: 17 | B23: 46261 | C23: 苏NEV615 | D23: 车 | E23: 配票/反向 | F23: 配票 | H23: 俊兴 | I23: 废钢压块类 | J23: 废钢压块2 | K23: 0.5 | L23: 38.78 | M23: 2320 | N23: 0 | O23: 89969.6
A24: 18 | B24: 46261 | C24: 苏ERS080 | D24: 车 | E24: 配票/反向 | F24: 配票 | G24: 林凯 | H24: 林凯车队 | I24: 废钢 | J24: 中废1 | K24: 0.15 | L24: 24.19 | M24: 2440 | N24: 0 | O24: 59023.6
A25: 18 | B25: 46261 | C25: 苏ERS080 | D25: 车 | E25: 配票/反向 | F25: 配票 | G25: 林凯 | H25: 林凯车队 | I25: 废钢压块类 | J25: 废钢压块1 | K25: 0.15 | L25: 24.19 | M25: 2360 | N25: 0 | O25: 57088.4
A26: 19 | B26: 46261 | C26: 鲁济宁货4095 | D26: 船 | E26: 配票/反向 | F26: 配票 | H26: 俊兴 | I26: 历史导入-待归类 | J26: 未注明 | K26: 0 | L26: 518.48 | N26: 0 | O26: 1271259
A27: 20 | B27: 46262 | C27: 苏DBE075 | D27: 车 | E27: 配票/反向 | F27: 配票 | G27: 林凯 | H27: 林凯车队 | I27: 废钢压块类 | J27: 废钢压块2 | K27: 0.2 | L27: 38.2 | M27: 2320 | N27: 0 | O27: 88624
A28: 21 | B28: 46262 | C28: 苏DBX137 | D28: 车 | E28: 配票/反向 | F28: 配票 | G28: 林凯 | H28: 林凯车队 | I28: 废钢 | J28: 中废2 | K28: 0.3 | L28: 18.52 | M28: 2400 | N28: 0 | O28: 44448
A29: 22 | B29: 46262 | C29: 苏DFB287 | D29: 车 | E29: 配票/反向 | F29: 配票 | G29: 林凯 | H29: 林凯车队 | I29: 废钢压块类 | J29: 废钢压块2 | K29: 0.3 | L29: 40.95 | M29: 2320 | N29: 0 | O29: 95004
A30: 22 | B30: 46262 | C30: 苏DFB287 | D30: 车 | E30: 配票/反向 | F30: 配票 | G30: 林凯 | H30: 林凯车队 | I30: 废钢压块类 | J30: 废钢压块1 | K30: 0.3 | L30: 40.95 | M30: 2360 | N30: 0 | O30: 96642
A31: 23 | B31: 46262 | C31: 苏DFM060 | D31: 车 | E31: 配票/反向 | F31: 配票 | G31: 林凯 | H31: 林凯车队 | I31: 废钢压块类 | J31: 废钢压块1 | K31: 0.5 | L31: 55.18 | M31: 2360 | N31: 0 | O31: 130224.8
A32: 24 | B32: 46262 | C32: 苏DBB772 | D32: 车 | E32: 配票/反向 | F32: 配票 | G32: 林凯 | H32: 林凯车队 | I32: 废钢 | J32: 中废1 | K32: 0.35 | L32: 44.212 | M32: 2440 | N32: 0 | O32: 107877.28
A33: 24 | B33: 46262 | C33: 苏DBB772 | D33: 车 | E33: 配票/反向 | F33: 配票 | G33: 林凯 | H33: 林凯车队 | I33: 废钢 | J33: 中废2 | K33: 0.15 | L33: 18.948 | M33: 2400 | N33: 0 | O33: 45475.2
A34: 25 | B34: 46262 | C34: 苏BDK567 | D34: 车 | E34: 配票/反向 | F34: 配票 | G34: 林凯 | H34: 林凯车队 | I34: 废钢 | J34: 中废1 | K34: 0.3 | L34: 34.22 | M34: 2440 | N34: 0 | O34: 83496.8
A35: 26 | B35: 46262 | C35: 苏BUK952 | D35: 车 | E35: 配票/反向 | F35: 配票 | G35: 林凯 | H35: 林凯车队 | I35: 废钢 | J35: 中废1 | K35: 0.2 | L35: 27.22 | M35: 2440 | N35: 0 | O35: 66416.8
A36: 27 | B36: 46262 | C36: 皖KQ1052 | D36: 车 | E36: 配票/反向 | F36: 配票 | H36: 俊兴 | I36: 废钢压块类 | J36: 废钢压块2 | K36: 0.245 | L36: 24.143 | M36: 2320 | N36: 0 | O36: 56011.76
A37: 27 | B37: 46262 | C37: 皖KQ1052 | D37: 车 | E37: 配票/反向 | F37: 配票 | H37: 俊兴 | I37: 废钢压块类 | J37: 废钢压块1 | K37: 0.105 | L37: 10.347 | M37: 2360 | N37: 0 | O37: 24418.92
A38: 28 | B38: 46262 | C38: 苏DBE075 | D38: 车 | E38: 配票/反向 | F38: 配票 | G38: 林凯 | H38: 林凯车队 | I38: 废钢压块类 | J38: 普通压块 | K38: 1.9 | L38: 67.8 | M38: 2240 | N38: 0 | O38: 151872
A39: 29 | B39: 46262 | C39: 冀A224E6 | D39: 车 | E39: 配票/反向 | F39: 配票 | G39: 林凯 | H39: 林凯车队 | I39: 废钢 | J39: 剪切中废1 | K39: 0.28 | L39: 20.3 | M39: 2470 | N39: 0 | O39: 50141
A40: 29 | B40: 46262 | C40: 冀A224E6 | D40: 车 | E40: 配票/反向 | F40: 配票 | G40: 林凯 | H40: 林凯车队 | I40: 废钢 | J40: 中废1 | K40: 0.12 | L40: 8.7 | M40: 2440 | N40: 0 | O40: 21228
A41: 30 | B41: 46262 | C41: 苏BWX568 | D41: 车 | E41: 配票/反向 | F41: 配票 | G41: 林凯 | H41: 林凯车队 | I41: 废钢 | J41: 中废2 | K41: 0.7 | L41: 32.52 | M41: 2400 | N41: 0 | O41: 78048
A42: 31 | B42: 46263 | C42: 苏DBB772 | D42: 车 | E42: 配票/反向 | F42: 配票 | G42: 林凯 | H42: 林凯车队 | I42: 铁水罐压块类 | J42: 铁加压块 | K42: 0.7 | L42: 81.36 | M42: 2510 | N42: 0 | O42: 204213.6
A43: 32 | B43: 46263 | C43: 苏ERS080 | D43: 车 | E43: 配票/反向 | F43: 配票 | G43: 林凯 | H43: 林凯车队 | I43: 废钢 | J43: 中废2 | K43: 0.45 | L43: 48.75 | M43: 2400 | N43: 0 | O43: 117000
A44: 33 | B44: 46263 | C44: 苏DBE075 | D44: 车 | E44: 配票/反向 | F44: 配票 | G44: 林凯 | H44: 林凯车队 | I44: 铁水罐压块类 | J44: 铁加压块 | K44: 0.7 | L44: 79.68 | M44: 2510 | N44: 0 | O44: 199996.8
A45: 34 | B45: 46263 | C45: 冀A224E6 | D45: 车 | E45: 配票/反向 | F45: 配票 | H45: 俊兴 | I45: 废钢 | J45: 中废1 | K45: 0.4 | L45: 20 | M45: 2440 | N45: 0 | O45: 48800
A46: 35 | B46: 46263 | C46: 苏AE8896 | D46: 车 | E46: 配票/反向 | F46: 配票 | H46: 俊兴 | I46: 废钢压块类 | J46: 废钢压块2 | K46: 0.28 | L46: 27.972 | M46: 2320 | N46: 0 | O46: 64895.04
A47: 35 | B47: 46263 | C47: 苏AE8896 | D47: 车 | E47: 配票/反向 | F47: 配票 | H47: 俊兴 | I47: 废钢压块类 | J47: 废钢压块1 | K47: 0.12 | L47: 11.988 | M47: 2360 | N47: 0 | O47: 28291.68
A48: 36 | B48: 46263 | C48: 苏DBB772 | D48: 车 | E48: 配票/反向 | F48: 配票 | G48: 林凯 | H48: 林凯车队 | I48: 废钢压块类 | J48: 普通压块 | K48: 0.6 | L48: 66.06 | M48: 2240 | N48: 0 | O48: 147974.4
A49: 37 | B49: 46264 | C49: 苏DBE075 | D49: 车 | E49: 配票/反向 | F49: 配票 | G49: 林凯 | H49: 林凯车队 | I49: 铁水罐压块类 | J49: 铁加压块 | K49: 0.8 | L49: 81.92 | M49: 2510 | N49: 0 | O49: 205619.2
A50: 38 | B50: 46264 | C50: 苏DBE961 | D50: 车 | E50: 配票/反向 | F50: 配票 | H50: 俊兴 | I50: 废钢压块类 | J50: 废钢压块2 | K50: 0.42 | L50: 55.048 | M50: 2320 | N50: 0 | O50: 127711.36
A51: 38 | B51: 46264 | C51: 苏DBE961 | D51: 车 | E51: 配票/反向 | F51: 配票 | H51: 俊兴 | I51: 废钢压块类 | J51: 废钢压块3 | K51: 0.18 | L51: 23.592 | M51: 2280 | N51: 0 | O51: 53789.76
A52: 39 | B52: 46264 | C52: 苏DFB287 | D52: 车 | E52: 配票/反向 | F52: 配票 | H52: 俊兴 | I52: 废钢压块类 | J52: 废钢压块2 | K52: 0.42 | L52: 58.282 | M52: 2320 | N52: 0 | O52: 135214.24
A53: 39 | B53: 46264 | C53: 苏DFB287 | D53: 车 | E53: 配票/反向 | F53: 配票 | H53: 俊兴 | I53: 废钢压块类 | J53: 废钢压块3 | K53: 0.18 | L53: 24.978 | M53: 2280 | N53: 0 | O53: 56949.84
A54: 40 | B54: 46264 | C54: 苏BTQ938 | D54: 车 | E54: 配票/反向 | F54: 配票 | G54: 李涛 | H54: 李涛车队 | I54: 废钢 | J54: 中废2 | K54: 0.5 | L54: 32.42 | M54: 2400 | N54: 0 | O54: 77808
A55: 41 | B55: 46264 | C55: 皖SB2849 | D55: 车 | E55: 配票/反向 | F55: 配票 | G55: 林凯 | H55: 林凯车队 | I55: 废钢压块类 | J55: 废钢压块2 | K55: 0.63 | L55: 30.338 | M55: 2320 | N55: 0 | O55: 70384.16
A56: 41 | B56: 46264 | C56: 皖SB2849 | D56: 车 | E56: 配票/反向 | F56: 配票 | G56: 林凯 | H56: 林凯车队 | I56: 废钢压块类 | J56: 废钢压块1 | K56: 0.27 | L56: 13.002 | M56: 2360 | N56: 0 | O56: 30684.72
A57: 42 | B57: 46264 | C57: 苏DBB772 | D57: 车 | E57: 配票/反向 | F57: 配票 | G57: 林凯 | H57: 林凯车队 | I57: 铁水罐压块类 | J57: 边角料压块1 | K57: 0.4 | L57: 83.78 | M57: 2520 | N57: 0 | O57: 211125.6
A58: 43 | B58: 46264 | C58: 冀A224E6 | D58: 车 | E58: 配票/反向 | F58: 配票 | H58: 俊兴 | I58: 废钢压块类 | J58: 废钢压块2 | K58: 0.35 | L58: 32.396 | M58: 2320 | N58: 0 | O58: 75158.72
A59: 43 | B59: 46264 | C59: 冀A224E6 | D59: 车 | E59: 配票/反向 | F59: 配票 | H59: 俊兴 | I59: 废钢压块类 | J59: 废钢压块1 | K59: 0.15 | L59: 13.884 | M59: 2360 | N59: 0 | O59: 32766.24
A60: 44 | B60: 46264 | C60: 苏DBB772 | D60: 车 | E60: 配票/反向 | F60: 配票 | G60: 林凯 | H60: 林凯车队 | I60: 废钢压块类 | J60: 普通压块 | K60: 0.7 | L60: 67.96 | M60: 2240 | N60: 0 | O60: 152230.4
A61: 45 | B61: 46265 | C61: 苏DFM060 | D61: 车 | E61: 配票/反向 | F61: 配票 | G61: 林凯 | H61: 林凯车队 | I61: 废钢 | J61: 中废2 | K61: 0.5 | L61: 25.12 | M61: 2400 | N61: 0 | O61: 60288
A62: 46 | B62: 46265 | C62: 冀A224E6 | D62: 车 | E62: 配票/反向 | F62: 配票 | G62: 林凯 | H62: 林凯车队 | I62: 废钢 | J62: 中废1 | K62: 0.14 | L62: 20.356 | M62: 2440 | N62: 0 | O62: 49668.64
A63: 46 | B63: 46265 | C63: 冀A224E6 | D63: 车 | E63: 配票/反向 | F63: 配票 | G63: 林凯 | H63: 林凯车队 | I63: 废钢 | J63: 剪切中废1 | K63: 0.06 | L63: 8.724 | M63: 2470 | N63: 0 | O63: 21548.28
A64: 47 | B64: 46265 | C64: 苏DFM060 | D64: 车 | E64: 配票/反向 | F64: 配票 | G64: 林凯 | H64: 林凯车队 | I64: 废钢 | J64: 中废1 | K64: 0.25 | L64: 28.39 | M64: 2440 | N64: 0 | O64: 69271.6
A65: 47 | B65: 46265 | C65: 苏DFM060 | D65: 车 | E65: 配票/反向 | F65: 配票 | G65: 林凯 | H65: 林凯车队 | I65: 废钢 | J65: 中废2 | K65: 0.25 | L65: 28.39 | M65: 2400 | N65: 0 | O65: 68136
A66: 48 | B66: 46265 | C66: 苏DBB772 | D66: 车 | E66: 配票/反向 | F66: 配票 | G66: 林凯 | H66: 林凯车队 | I66: 铁水罐压块类 | J66: 铁加压块 | K66: 0.8 | L66: 80.96 | M66: 2510 | N66: 0 | O66: 203209.6
A67: 49 | B67: 46265 | C67: 苏DBB772 | D67: 车 | E67: 配票/反向 | F67: 配票 | G67: 林凯 | H67: 林凯车队 | I67: 废钢压块类 | J67: 普通压块 | K67: 1.4 | L67: 69.66 | M67: 2240 | N67: 0 | O67: 156038.4
A68: 50 | B68: 46266 | C68: 苏ERS080 | D68: 车 | E68: 配票/反向 | F68: 配票 | G68: 林凯 | H68: 林凯车队 | I68: 废钢 | J68: 中废2 | K68: 0.4 | L68: 49.1 | M68: 2400 | N68: 0 | O68: 117840
A69: 51 | B69: 46266 | C69: 苏DFM060 | D69: 车 | E69: 配票/反向 | F69: 配票 | G69: 林凯 | H69: 林凯车队 | I69: 废钢 | J69: 中废2 | K69: 0.15 | L69: 12.98 | M69: 2400 | N69: 0 | O69: 31152
A70: 51 | B70: 46266 | C70: 苏DFM060 | D70: 车 | E70: 配票/反向 | F70: 配票 | G70: 林凯 | H70: 林凯车队 | I70: 废钢 | J70: 小废 | K70: 0.15 | L70: 12.98 | M70: 2320 | N70: 0 | O70: 30113.6
A71: 52 | B71: 46266 | C71: 苏DBX137 | D71: 车 | E71: 配票/反向 | F71: 配票 | G71: 林凯 | H71: 林凯车队 | I71: 废钢压块类 | J71: 废钢压块2 | K71: 0.245 | L71: 33.257 | M71: 2320 | N71: 0 | O71: 77156.24
... A73: 53 | B73: 46266 | C73: 苏DBB772 | D73: 车 | E73: 配票/反向 | F73: 配票 | G73: 林凯 | H73: 林凯车队 | I73: 废钢压块类 | J73: 普通压块 | K73: 1.4 | L73: 70.76 | M73: 2240 | N73: 0 | O73: 158502.4
A74: 54 | B74: 46266 | C74: 通海机9998 | D74: 船 | E74: 配票/反向 | F74: 配票 | H74: 俊兴 | I74: 历史导入-待归类 | J74: 未注明 | K74: 0 | L74: 481.77 | N74: 0 | O74: 1181813.6
A75: 55 | B75: 46267 | C75: 苏BXT103 | D75: 车 | E75: 配票/反向 | F75: 配票 | G75: 闫东朋 | H75: 闫东朋车队 | I75: 废钢压块类 | J75: 废钢压块1 | K75: 0.35 | L75: 39.298 | M75: 2380 | N75: 0 | O75: 93529.24
A76: 55 | B76: 46267 | C76: 苏BXT103 | D76: 车 | E76: 配票/反向 | F76: 配票 | G76: 闫东朋 | H76: 闫东朋车队 | I76: 废钢压块类 | J76: 废钢压块2 | K76: 0.15 | L76: 16.842 | M76: 2340 | N76: 0 | O76: 39410.28
A77: 56 | B77: 46268 | C77: 苏NER821 | D77: 车 | E77: 配票/反向 | F77: 配票 | G77: 李涛 | H77: 李涛车队 | I77: 废钢 | J77: 中废2 | K77: 0.3 | L77: 35.72 | M77: 2420 | N77: 0 | O77: 86442.4
A78: 57 | B78: 46268 | C78: 苏兴达货8566 | D78: 船 | E78: 配票/反向 | F78: 配票 | H78: 俊兴 | I78: 历史导入-待归类 | J78: 未注明 | K78: 0 | L78: 560.21 | N78: 0 | O78: 1381864.1
A79: 58 | B79: 46269 | C79: 皖SG1123 | D79: 车 | E79: 配票/反向 | F79: 配票 | G79: 李涛 | H79: 李涛车队 | I79: 废钢 | J79: 中废2 | K79: 0.35 | L79: 38.07 | M79: 2410 | N79: 0 | O79: 91748.7
A80: 59 | B80: 46269 | C80: 皖LE9644 | D80: 车 | E80: 配票/反向 | F80: 配票 | G80: 李涛 | H80: 李涛车队 | I80: 废钢 | J80: 中废2 | K80: 0.3 | L80: 35.28 | M80: 2410 | N80: 16310 | O80: 68714.8
A81: 60 | B81: 46269 | C81: 苏K66529 | D81: 车 | E81: 配票/反向 | F81: 配票 | G81: 陈杰 | H81: 陈杰车队 | I81: 废钢压块类 | J81: 废钢压块3 | K81: 1 | L81: 39.12 | M81: 2290 | N81: 0 | O81: 89584.8
A82: 61 | B82: 46270 | C82: 皖城兴货688 | D82: 船 | E82: 配票/反向 | F82: 配票 | G82: 林凯 | H82: 林凯车队 | I82: 历史导入-待归类 | J82: 未注明 | K82: 0 | L82: 719.14 | N82: 0 | O82: 1823625.4
A83: 62 | B83: 46272 | C83: 鲁济宁货1567 | D83: 船 | E83: 配票/反向 | F83: 配票 | G83: 林凯 | H83: 林凯车队 | I83: 历史导入-待归类 | J83: 未注明 | K83: 0 | L83: 613.8 | N83: 0 | O83: 1467823.1
A84: 63 | B84: 46275 | C84: 苏DBE075 | D84: 车 | E84: 带票带货 | F84: 户头通道 | G84: 林凯 | H84: 君盛 | I84: 铁水罐压块类 | J84: 铁加压块 | K84: 0.3 | L84: 82.26 | M84: 2530 | N84: 0 | O84: 208117.8
A85: 64 | B85: 46276 | C85: 苏DBB772 | D85: 车 | E85: 带票带货 | F85: 户头通道 | G85: 林凯 | H85: 君盛 | I85: 铁水罐压块类 | J85: 铁加压块 | K85: 0.4 | L85: 82.2 | M85: 2530 | N85: 0 | O85: 207966
A86: 65 | B86: 46277 | C86: 苏DBE961 | D86: 车 | E86: 带票带货 | F86: 户头通道 | G86: 林凯 | H86: 力拓 | I86: 废钢压块类 | J86: 废钢压块3 | K86: 2.1 | L86: 79.76 | M86: 2280 | N86: 0 | O86: 181852.8
A87: 66 | B87: 46277 | C87: 苏DBE075 | D87: 车 | E87: 带票带货 | F87: 户头通道 | G87: 林凯 | H87: 𠓾景通 | I87: 铁水罐压块类 | J87: 边角料压块1 | K87: 0.6 | L87: 78.04 | M87: 2570 | N87: 500 | O87: 200062.8
A88: 67 | B88: 46277 | C88: 皖F30399 | D88: 车 | E88: 配票/反向 | F88: 配票 | G88: 邓晶焱 | H88: 邓晶焱车队 | I88: 废钢 | J88: 中废2 | K88: 0.55 | L88: 39.17 | M88: 2400 | N88: 0 | O88: 94008
A89: 68 | B89: 46277 | C89: 苏DBE075 | D89: 车 | E89: 带票带货 | F89: 户头通道 | G89: 林凯 | H89: 君盛 | I89: 废钢压块类 | J89: 普通压块 | K89: 2 | L89: 65.44 | M89: 2250 | N89: 0 | O89: 147240
A90: 69 | B90: 46279 | C90: 苏DBB772 | D90: 车 | E90: 配票/反向 | F90: 配票 | G90: 林凯 | H90: 林凯车队 | I90: 废钢压块类 | J90: 普通压块 | K90: 1.7 | L90: 60.9 | M90: 2250 | N90: 0 | O90: 137025
A91: 70 | B91: 46279 | C91: 苏DBE961 | D91: 车 | E91: 带票带货 | F91: 户头通道 | G91: 林凯 | H91: 力拓 | I91: 铁水罐压块类 | J91: 铁加压块 | K91: 0.7 | L91: 75.88 | M91: 2530 | N91: 0 | O91: 191976.4
A92: 71 | B92: 46279 | C92: 鲁DC6106 | D92: 车 | E92: 带票带货 | F92: 户头通道 | G92: 邓晶焱 | H92: 邓晶焱车队 | I92: 废钢 | J92: 小废 | K92: 0.9 | L92: 44.52 | M92: 2320 | N92: 0 | O92: 103286.4
A93: 72 | B93: 46279 | C93: 苏J19371 | D93: 车 | E93: 带票带货 | F93: 户头通道 | G93: 闫东朋 | H93: 闫东朋车队 | I93: 铁水罐压块类 | J93: 铁加压块 | K93: 0.5 | L93: 78.36 | M93: 2530 | N93: 0 | O93: 198250.8
A94: 73 | B94: 46280 | C94: 苏ELU629 | D94: 车 | E94: 配票/反向 | F94: 配票 | H94: 未填供货厂 | I94: 废钢 | J94: 中废2 | K94: 0.3 | L94: 34.42 | M94: 2390 | N94: 0 | O94: 82263.8
A95: 74 | B95: 46280 | C95: 苏DBE075 | D95: 车 | E95: 带票带货 | F95: 直签带票 | G95: 林凯 | H95: 君盛 | I95: 废钢压块类 | J95: 普通压块 | K95: 0.3 | L95: 31.46 | M95: 2250 | N95: 0 | O95: 70785
A96: 75 | B96: 46280 | C96: 苏L80153 | D96: 车 | E96: 配票/反向 | F96: 反向 | G96: 闫东朋 | H96: 闫东朋车队 | I96: 铁水罐压块类 | J96: 边角料压块1 | K96: 0.2 | L96: 47.98 | M96: 2570 | N96: 0 | O96: 123308.6
A97: 76 | B97: 46280 | C97: 苏J19371 | D97: 车 | E97: 配票/反向 | F97: 反向 | G97: 闫东朋 | H97: 闫东朋车队 | I97: 废钢 | J97: 重废3 | K97: 0.4 | L97: 79.58 | M97: 2510 | N97: 0 | O97: 199745.8
A98: 77 | B98: 46280 | C98: 苏CLK667 | D98: 车 | E98: 配票/反向 | F98: 配票 | H98: 未填供货厂 | I98: 废钢 | J98: 小废 | K98: 0.5 | L98: 33.02 | M98: 2320 | N98: 0 | O98: 76606.4
A99: 78 | B99: 46280 | C99: 苏DBB772 | D99: 车 | E99: 带票带货 | F99: 直签带票 | G99: 林凯 | H99: 𠓾景通 | I99: 废钢压块类 | J99: 废钢压块1 | K99: 0.7 | L99: 71.5 | M99: 2370 | N99: 0 | O99: 169455
A100: 79 | B100: 46280 | C100: 苏DBE961 | D100: 车 | E100: 带票带货 | F100: 直签带票 | G100: 林凯 | H100: 君盛 | I100: 废钢压块类 | J100: 普通压块 | K100: 0.8 | L100: 31.38 | M100: 2250 | N100: 0 | O100: 70605
A101: 80 | B101: 46280 | C101: 皖四航6058 | D101: 车 | E101: 配票/反向 | F101: 配票 | H101: 尹鹏飞 | J101: 未分货型(混料) | K101: 6.92 | L101: 589.24 | M101: 0 | N101: 0 | O101: 1444596.1
...

Sheet 票款追踪
A1: 车次ID | B1: 结算日期 | C1: 车号/船号 | D1: 路径 | E1: 开票路径 | F1: 供货厂/车队 | G1: 线 | H1: 环节 | I1: 从 | J1: 到 | K1: 应登记(票额)(元) | L1: 已登记(元) | M1: 待登记(元) | N1: 状态 | O1: 账龄(天) | P1: 批次ID
A2: 1 | B2: 46253 | C2: 苏DBB772 | D2: 配票/反向 | E2: 我们配票（经俊兴） | F2: 林凯车队 | G2: 开票 | H2: 销项→欧冶 | I2: 俊兴 | J2: 欧冶物宝 | K2: 166805.86 | L2: 0 | M2: =IF(OR(N2="已登记",LEFT(N2,2)="按状"),0,K2-L2) | N2: 按状态视为已完成(历史)
A3: 1 | B3: 46253 | C3: 苏DBB772 | D3: 配票/反向 | E3: 我们配票（经俊兴） | F3: 林凯车队 | G3: 回款 | H3: 欧冶回款 | I3: 欧冶物宝 | J3: 俊兴 | K3: 166805.86 | L3: 0 | M3: =IF(OR(N3="已登记",LEFT(N3,2)="按状"),0,K3-L3) | N3: 待登记 | O3: 0
A4: 1 | B4: 46253 | C4: 苏DBB772 | D4: 配票/反向 | E4: 我们配票（经俊兴） | F4: 林凯车队 | G4: 回款 | H4: 到客户账户 | I4: 俊兴 | J4: 林凯车队·客户账户 | K4: 166805.86 | L4: 0 | M4: =IF(OR(N4="已登记",LEFT(N4,2)="按状"),0,K4-L4) | N4: 未开始(前一环节未完成)
A5: 2 | B5: 46254 | C5: 苏DFM060 | D5: 配票/反向 | E5: 我们配票（经俊兴） | F5: 林凯车队 | G5: 开票 | H5: 销项→欧冶 | I5: 俊兴 | J5: 欧冶物宝 | K5: 83763.6 | L5: 0 | M5: =IF(OR(N5="已登记",LEFT(N5,2)="按状"),0,K5-L5) | N5: 按状态视为已完成(历史)
A6: 2 | B6: 46254 | C6: 苏DFM060 | D6: 配票/反向 | E6: 我们配票（经俊兴） | F6: 林凯车队 | G6: 回款 | H6: 欧冶回款 | I6: 欧冶物宝 | J6: 俊兴 | K6: 83763.6 | L6: 0 | M6: =IF(OR(N6="已登记",LEFT(N6,2)="按状"),0,K6-L6) | N6: 待登记 | O6: 32
A7: 2 | B7: 46254 | C7: 苏DFM060 | D7: 配票/反向 | E7: 我们配票（经俊兴） | F7: 林凯车队 | G7: 回款 | H7: 到客户账户 | I7: 俊兴 | J7: 林凯车队·客户账户 | K7: 83763.6 | L7: 0 | M7: =IF(OR(N7="已登记",LEFT(N7,2)="按状"),0,K7-L7) | N7: 未开始(前一环节未完成)
A8: 3 | B8: 46255 | C8: 苏DBB772 | D8: 配票/反向 | E8: 我们配票（经俊兴） | F8: 林凯车队 | G8: 开票 | H8: 销项→欧冶 | I8: 俊兴 | J8: 欧冶物宝 | K8: 199410.12 | L8: 0 | M8: =IF(OR(N8="已登记",LEFT(N8,2)="按状"),0,K8-L8) | N8: 按状态视为已完成(历史)
A9: 3 | B9: 46255 | C9: 苏DBB772 | D9: 配票/反向 | E9: 我们配票（经俊兴） | F9: 林凯车队 | G9: 回款 | H9: 欧冶回款 | I9: 欧冶物宝 | J9: 俊兴 | K9: 199410.12 | L9: 0 | M9: =IF(OR(N9="已登记",LEFT(N9,2)="按状"),0,K9-L9) | N9: 待登记 | O9: 31
A10: 3 | B10: 46255 | C10: 苏DBB772 | D10: 配票/反向 | E10: 我们配票（经俊兴） | F10: 林凯车队 | G10: 回款 | H10: 到客户账户 | I10: 俊兴 | J10: 林凯车队·客户账户 | K10: 199410.12 | L10: 0 | M10: =IF(OR(N10="已登记",LEFT(N10,2)="按状"),0,K10-L10) | N10: 未开始(前一环节未完成)
A11: 4 | B11: 46255 | C11: 皖M2A505 | D11: 配票/反向 | E11: 我们配票（经俊兴） | F11: 俊兴 | G11: 开票 | H11: 销项→欧冶 | I11: 俊兴 | J11: 欧冶物宝 | K11: 82428.12 | L11: 0 | M11: =IF(OR(N11="已登记",LEFT(N11,2)="按状"),0,K11-L11) | N11: 按状态视为已完成(历史)
A12: 4 | B12: 46255 | C12: 皖M2A505 | D12: 配票/反向 | E12: 我们配票（经俊兴） | F12: 俊兴 | G12: 回款 | H12: 欧冶回款 | I12: 欧冶物宝 | J12: 俊兴 | K12: 82428.12 | L12: 0 | M12: =IF(OR(N12="已登记",LEFT(N12,2)="按状"),0,K12-L12) | N12: 待登记 | O12: 31
A13: 4 | B13: 46255 | C13: 皖M2A505 | D13: 配票/反向 | E13: 我们配票（经俊兴） | F13: 俊兴 | G13: 回款 | H13: 到客户账户 | I13: 俊兴 | J13: 俊兴·客户账户 | K13: 82428.12 | L13: 0 | M13: =IF(OR(N13="已登记",LEFT(N13,2)="按状"),0,K13-L13) | N13: 未开始(前一环节未完成)
A14: 5 | B14: 46255 | C14: 苏EQB977 | D14: 配票/反向 | E14: 我们配票（经俊兴） | F14: 俊兴 | G14: 开票 | H14: 销项→欧冶 | I14: 俊兴 | J14: 欧冶物宝 | K14: 74674.98 | L14: 0 | M14: =IF(OR(N14="已登记",LEFT(N14,2)="按状"),0,K14-L14) | N14: 按状态视为已完成(历史)
A15: 5 | B15: 46255 | C15: 苏EQB977 | D15: 配票/反向 | E15: 我们配票（经俊兴） | F15: 俊兴 | G15: 回款 | H15: 欧冶回款 | I15: 欧冶物宝 | J15: 俊兴 | K15: 74674.98 | L15: 0 | M15: =IF(OR(N15="已登记",LEFT(N15,2)="按状"),0,K15-L15) | N15: 待登记 | O15: 31
A16: 5 | B16: 46255 | C16: 苏EQB977 | D16: 配票/反向 | E16: 我们配票（经俊兴） | F16: 俊兴 | G16: 回款 | H16: 到客户账户 | I16: 俊兴 | J16: 俊兴·客户账户 | K16: 74674.98 | L16: 0 | M16: =IF(OR(N16="已登记",LEFT(N16,2)="按状"),0,K16-L16) | N16: 未开始(前一环节未完成)
A17: 6 | B17: 46255 | C17: 苏BUK952 | D17: 配票/反向 | E17: 我们配票（经俊兴） | F17: 林凯车队 | G17: 开票 | H17: 销项→欧冶 | I17: 俊兴 | J17: 欧冶物宝 | K17: 58461.95 | L17: 0 | M17: =IF(OR(N17="已登记",LEFT(N17,2)="按状"),0,K17-L17) | N17: 按状态视为已完成(历史)
A18: 6 | B18: 46255 | C18: 苏BUK952 | D18: 配票/反向 | E18: 我们配票（经俊兴） | F18: 林凯车队 | G18: 回款 | H18: 欧冶回款 | I18: 欧冶物宝 | J18: 俊兴 | K18: 58461.95 | L18: 0 | M18: =IF(OR(N18="已登记",LEFT(N18,2)="按状"),0,K18-L18) | N18: 待登记 | O18: 31
A19: 6 | B19: 46255 | C19: 苏BUK952 | D19: 配票/反向 | E19: 我们配票（经俊兴） | F19: 林凯车队 | G19: 回款 | H19: 到客户账户 | I19: 俊兴 | J19: 林凯车队·客户账户 | K19: 58461.95 | L19: 0 | M19: =IF(OR(N19="已登记",LEFT(N19,2)="按状"),0,K19-L19) | N19: 未开始(前一环节未完成)
A20: 7 | B20: 46256 | C20: 苏DBB772 | D20: 配票/反向 | E20: 我们配票（经俊兴） | F20: 林凯车队 | G20: 开票 | H20: 销项→欧冶 | I20: 俊兴 | J20: 欧冶物宝 | K20: 157556.5 | L20: 0 | M20: =IF(OR(N20="已登记",LEFT(N20,2)="按状"),0,K20-L20) | N20: 按状态视为已完成(历史)
A21: 7 | B21: 46256 | C21: 苏DBB772 | D21: 配票/反向 | E21: 我们配票（经俊兴） | F21: 林凯车队 | G21: 回款 | H21: 欧冶回款 | I21: 欧冶物宝 | J21: 俊兴 | K21: 157556.5 | L21: 0 | M21: =IF(OR(N21="已登记",LEFT(N21,2)="按状"),0,K21-L21) | N21: 待登记 | O21: 30
A22: 7 | B22: 46256 | C22: 苏DBB772 | D22: 配票/反向 | E22: 我们配票（经俊兴） | F22: 林凯车队 | G22: 回款 | H22: 到客户账户 | I22: 俊兴 | J22: 林凯车队·客户账户 | K22: 157556.5 | L22: 0 | M22: =IF(OR(N22="已登记",LEFT(N22,2)="按状"),0,K22-L22) | N22: 未开始(前一环节未完成)
A23: 8 | B23: 46256 | C23: 苏E9W908 | D23: 配票/反向 | E23: 我们配票（经俊兴） | F23: 邓晶焱车队 | G23: 开票 | H23: 销项→欧冶 | I23: 俊兴 | J23: 欧冶物宝 | K23: 90342.12 | L23: 0 | M23: =IF(OR(N23="已登记",LEFT(N23,2)="按状"),0,K23-L23) | N23: 按状态视为已完成(历史)
A24: 8 | B24: 46256 | C24: 苏E9W908 | D24: 配票/反向 | E24: 我们配票（经俊兴） | F24: 邓晶焱车队 | G24: 回款 | H24: 欧冶回款 | I24: 欧冶物宝 | J24: 俊兴 | K24: 90342.12 | L24: 0 | M24: =IF(OR(N24="已登记",LEFT(N24,2)="按状"),0,K24-L24) | N24: 待登记 | O24: 30
A25: 8 | B25: 46256 | C25: 苏E9W908 | D25: 配票/反向 | E25: 我们配票（经俊兴） | F25: 邓晶焱车队 | G25: 回款 | H25: 到客户账户 | I25: 俊兴 | J25: 邓晶焱车队·客户账户 | K25: 90342.12 | L25: 0 | M25: =IF(OR(N25="已登记",LEFT(N25,2)="按状"),0,K25-L25) | N25: 未开始(前一环节未完成)
A26: 9 | B26: 46256 | C26: 苏MAK862 | D26: 配票/反向 | E26: 我们配票（经俊兴） | F26: 俊兴 | G26: 开票 | H26: 销项→欧冶 | I26: 俊兴 | J26: 欧冶物宝 | K26: 77622.08 | L26: 0 | M26: =IF(OR(N26="已登记",LEFT(N26,2)="按状"),0,K26-L26) | N26: 按状态视为已完成(历史)
A27: 9 | B27: 46256 | C27: 苏MAK862 | D27: 配票/反向 | E27: 我们配票（经俊兴） | F27: 俊兴 | G27: 回款 | H27: 欧冶回款 | I27: 欧冶物宝 | J27: 俊兴 | K27: 77622.08 | L27: 0 | M27: =IF(OR(N27="已登记",LEFT(N27,2)="按状"),0,K27-L27) | N27: 待登记 | O27: 30
A28: 9 | B28: 46256 | C28: 苏MAK862 | D28: 配票/反向 | E28: 我们配票（经俊兴） | F28: 俊兴 | G28: 回款 | H28: 到客户账户 | I28: 俊兴 | J28: 俊兴·客户账户 | K28: 77622.08 | L28: 0 | M28: =IF(OR(N28="已登记",LEFT(N28,2)="按状"),0,K28-L28) | N28: 未开始(前一环节未完成)
A29: 10 | B29: 46259 | C29: 苏DBE075 | D29: 配票/反向 | E29: 我们配票（经俊兴） | F29: 林凯车队 | G29: 开票 | H29: 销项→欧冶 | I29: 俊兴 | J29: 欧冶物宝 | K29: 182169 | L29: 0 | M29: =IF(OR(N29="已登记",LEFT(N29,2)="按状"),0,K29-L29) | N29: 按状态视为已完成(历史)
A30: 10 | B30: 46259 | C30: 苏DBE075 | D30: 配票/反向 | E30: 我们配票（经俊兴） | F30: 林凯车队 | G30: 回款 | H30: 欧冶回款 | I30: 欧冶物宝 | J30: 俊兴 | K30: 182169 | L30: 0 | M30: =IF(OR(N30="已登记",LEFT(N30,2)="按状"),0,K30-L30) | N30: 待登记 | O30: 27
A31: 10 | B31: 46259 | C31: 苏DBE075 | D31: 配票/反向 | E31: 我们配票（经俊兴） | F31: 林凯车队 | G31: 回款 | H31: 到客户账户 | I31: 俊兴 | J31: 林凯车队·客户账户 | K31: 182169 | L31: 0 | M31: =IF(OR(N31="已登记",LEFT(N31,2)="按状"),0,K31-L31) | N31: 未开始(前一环节未完成)
A32: 11 | B32: 46261 | C32: 苏淮货16776 | D32: 配票/反向 | E32: 我们配票（经俊兴） | F32: 俊兴 | G32: 开票 | H32: 销项→欧冶 | I32: 俊兴 | J32: 欧冶物宝 | K32: 1331226.9 | L32: 0 | M32: =IF(OR(N32="已登记",LEFT(N32,2)="按状"),0,K32-L32) | N32: 按状态视为已完成(历史)
A33: 11 | B33: 46261 | C33: 苏淮货16776 | D33: 配票/反向 | E33: 我们配票（经俊兴） | F33: 俊兴 | G33: 回款 | H33: 欧冶回款 | I33: 欧冶物宝 | J33: 俊兴 | K33: 1331226.9 | L33: 0 | M33: =IF(OR(N33="已登记",LEFT(N33,2)="按状"),0,K33-L33) | N33: 待登记 | O33: 25
A34: 11 | B34: 46261 | C34: 苏淮货16776 | D34: 配票/反向 | E34: 我们配票（经俊兴） | F34: 俊兴 | G34: 回款 | H34: 到客户账户 | I34: 俊兴 | J34: 俊兴·客户账户 | K34: 1331226.9 | L34: 0 | M34: =IF(OR(N34="已登记",LEFT(N34,2)="按状"),0,K34-L34) | N34: 未开始(前一环节未完成)
A35: 12 | B35: 46261 | C35: 苏NEX375 | D35: 配票/反向 | E35: 我们配票（经俊兴） | F35: 林凯车队 | G35: 开票 | H35: 销项→欧冶 | I35: 俊兴 | J35: 欧冶物宝 | K35: 92500.19 | L35: 0 | M35: =IF(OR(N35="已登记",LEFT(N35,2)="按状"),0,K35-L35) | N35: 按状态视为已完成(历史)
A36: 12 | B36: 46261 | C36: 苏NEX375 | D36: 配票/反向 | E36: 我们配票（经俊兴） | F36: 林凯车队 | G36: 回款 | H36: 欧冶回款 | I36: 欧冶物宝 | J36: 俊兴 | K36: 92500.19 | L36: 0 | M36: =IF(OR(N36="已登记",LEFT(N36,2)="按状"),0,K36-L36) | N36: 待登记 | O36: 25
A37: 12 | B37: 46261 | C37: 苏NEX375 | D37: 配票/反向 | E37: 我们配票（经俊兴） | F37: 林凯车队 | G37: 回款 | H37: 到客户账户 | I37: 俊兴 | J37: 林凯车队·客户账户 | K37: 92500.19 | L37: 0 | M37: =IF(OR(N37="已登记",LEFT(N37,2)="按状"),0,K37-L37) | N37: 未开始(前一环节未完成)
A38: 13 | B38: 46261 | C38: 苏DFM060 | D38: 配票/反向 | E38: 我们配票（经俊兴） | F38: 林凯车队 | G38: 开票 | H38: 销项→欧冶 | I38: 俊兴 | J38: 欧冶物宝 | K38: 83417.6 | L38: 0 | M38: =IF(OR(N38="已登记",LEFT(N38,2)="按状"),0,K38-L38) | N38: 按状态视为已完成(历史)
A39: 13 | B39: 46261 | C39: 苏DFM060 | D39: 配票/反向 | E39: 我们配票（经俊兴） | F39: 林凯车队 | G39: 回款 | H39: 欧冶回款 | I39: 欧冶物宝 | J39: 俊兴 | K39: 83417.6 | L39: 0 | M39: =IF(OR(N39="已登记",LEFT(N39,2)="按状"),0,K39-L39) | N39: 待登记 | O39: 25
A40: 13 | B40: 46261 | C40: 苏DFM060 | D40: 配票/反向 | E40: 我们配票（经俊兴） | F40: 林凯车队 | G40: 回款 | H40: 到客户账户 | I40: 俊兴 | J40: 林凯车队·客户账户 | K40: 83417.6 | L40: 0 | M40: =IF(OR(N40="已登记",LEFT(N40,2)="按状"),0,K40-L40) | N40: 未开始(前一环节未完成)
A41: 14 | B41: 46261 | C41: 苏DBB772 | D41: 配票/反向 | E41: 供货厂自带票（带票带货） | F41: 君盛 | G41: 开票 | H41: 销项→欧冶 | I41: 君盛 | J41: 欧冶物宝 | K41: 146809.74 | L41: 0 | M41: =IF(OR(N41="已登记",LEFT(N41,2)="按状"),0,K41-L41) | N41: 按状态视为已完成(历史)
A42: 14 | B42: 46261 | C42: 苏DBB772 | D42: 配票/反向 | E42: 供货厂自带票（带票带货） | F42: 君盛 | G42: 回款 | H42: 欧冶回款 | I42: 欧冶物宝 | J42: 君盛 | K42: 146809.74 | L42: 0 | M42: =IF(OR(N42="已登记",LEFT(N42,2)="按状"),0,K42-L42) | N42: 待登记 | O42: 25
A43: 15 | B43: 46261 | C43: 苏BDK567 | D43: 配票/反向 | E43: 我们配票（经俊兴） | F43: 林凯车队 | G43: 开票 | H43: 销项→欧冶 | I43: 俊兴 | J43: 欧冶物宝 | K43: 77945.6 | L43: 0 | M43: =IF(OR(N43="已登记",LEFT(N43,2)="按状"),0,K43-L43) | N43: 按状态视为已完成(历史)
A44: 15 | B44: 46261 | C44: 苏BDK567 | D44: 配票/反向 | E44: 我们配票（经俊兴） | F44: 林凯车队 | G44: 回款 | H44: 欧冶回款 | I44: 欧冶物宝 | J44: 俊兴 | K44: 77945.6 | L44: 0 | M44: =IF(OR(N44="已登记",LEFT(N44,2)="按状"),0,K44-L44) | N44: 待登记 | O44: 25
A45: 15 | B45: 46261 | C45: 苏BDK567 | D45: 配票/反向 | E45: 我们配票（经俊兴） | F45: 林凯车队 | G45: 回款 | H45: 到客户账户 | I45: 俊兴 | J45: 林凯车队·客户账户 | K45: 77945.6 | L45: 0 | M45: =IF(OR(N45="已登记",LEFT(N45,2)="按状"),0,K45-L45) | N45: 未开始(前一环节未完成)
A46: 16 | B46: 46261 | C46: 苏BZP839 | D46: 配票/反向 | E46: 我们配票（经俊兴） | F46: 林凯车队 | G46: 开票 | H46: 销项→欧冶 | I46: 俊兴 | J46: 欧冶物宝 | K46: 67914.83 | L46: 0 | M46: =IF(OR(N46="已登记",LEFT(N46,2)="按状"),0,K46-L46) | N46: 按状态视为已完成(历史)
A47: 16 | B47: 46261 | C47: 苏BZP839 | D47: 配票/反向 | E47: 我们配票（经俊兴） | F47: 林凯车队 | G47: 回款 | H47: 欧冶回款 | I47: 欧冶物宝 | J47: 俊兴 | K47: 67914.83 | L47: 0 | M47: =IF(OR(N47="已登记",LEFT(N47,2)="按状"),0,K47-L47) | N47: 待登记 | O47: 25
A48: 16 | B48: 46261 | C48: 苏BZP839 | D48: 配票/反向 | E48: 我们配票（经俊兴） | F48: 林凯车队 | G48: 回款 | H48: 到客户账户 | I48: 俊兴 | J48: 林凯车队·客户账户 | K48: 67914.83 | L48: 0 | M48: =IF(OR(N48="已登记",LEFT(N48,2)="按状"),0,K48-L48) | N48: 未开始(前一环节未完成)
A49: 17 | B49: 46261 | C49: 苏NEV615 | D49: 配票/反向 | E49: 我们配票（经俊兴） | F49: 俊兴 | G49: 开票 | H49: 销项→欧冶 | I49: 俊兴 | J49: 欧冶物宝 | K49: 89077.66 | L49: 0 | M49: =IF(OR(N49="已登记",LEFT(N49,2)="按状"),0,K49-L49) | N49: 按状态视为已完成(历史)
A50: 17 | B50: 46261 | C50: 苏NEV615 | D50: 配票/反向 | E50: 我们配票（经俊兴） | F50: 俊兴 | G50: 回款 | H50: 欧冶回款 | I50: 欧冶物宝 | J50: 俊兴 | K50: 89077.66 | L50: 0 | M50: =IF(OR(N50="已登记",LEFT(N50,2)="按状"),0,K50-L50) | N50: 待登记 | O50: 25
A51: 17 | B51: 46261 | C51: 苏NEV615 | D51: 配票/反向 | E51: 我们配票（经俊兴） | F51: 俊兴 | G51: 回款 | H51: 到客户账户 | I51: 俊兴 | J51: 俊兴·客户账户 | K51: 89077.66 | L51: 0 | M51: =IF(OR(N51="已登记",LEFT(N51,2)="按状"),0,K51-L51) | N51: 未开始(前一环节未完成)
A52: 18 | B52: 46261 | C52: 苏ERS080 | D52: 配票/反向 | E52: 我们配票（经俊兴） | F52: 林凯车队 | G52: 开票 | H52: 销项→欧冶 | I52: 俊兴 | J52: 欧冶物宝 | K52: 114999.26 | L52: 0 | M52: =IF(OR(N52="已登记",LEFT(N52,2)="按状"),0,K52-L52) | N52: 按状态视为已完成(历史)
A53: 18 | B53: 46261 | C53: 苏ERS080 | D53: 配票/反向 | E53: 我们配票（经俊兴） | F53: 林凯车队 | G53: 回款 | H53: 欧冶回款 | I53: 欧冶物宝 | J53: 俊兴 | K53: 114999.26 | L53: 0 | M53: =IF(OR(N53="已登记",LEFT(N53,2)="按状"),0,K53-L53) | N53: 待登记 | O53: 25
A54: 18 | B54: 46261 | C54: 苏ERS080 | D54: 配票/反向 | E54: 我们配票（经俊兴） | F54: 林凯车队 | G54: 回款 | H54: 到客户账户 | I54: 俊兴 | J54: 林凯车队·客户账户 | K54: 114999.26 | L54: 0 | M54: =IF(OR(N54="已登记",LEFT(N54,2)="按状"),0,K54-L54) | N54: 未开始(前一环节未完成)
A55: 19 | B55: 46261 | C55: 鲁济宁货4095 | D55: 配票/反向 | E55: 我们配票（经俊兴） | F55: 俊兴 | G55: 开票 | H55: 销项→欧冶 | I55: 俊兴 | J55: 欧冶物宝 | K55: 1259333.9 | L55: 0 | M55: =IF(OR(N55="已登记",LEFT(N55,2)="按状"),0,K55-L55) | N55: 按状态视为已完成(历史)
A56: 19 | B56: 46261 | C56: 鲁济宁货4095 | D56: 配票/反向 | E56: 我们配票（经俊兴） | F56: 俊兴 | G56: 回款 | H56: 欧冶回款 | I56: 欧冶物宝 | J56: 俊兴 | K56: 1259333.9 | L56: 0 | M56: =IF(OR(N56="已登记",LEFT(N56,2)="按状"),0,K56-L56) | N56: 待登记 | O56: 25
A57: 19 | B57: 46261 | C57: 鲁济宁货4095 | D57: 配票/反向 | E57: 我们配票（经俊兴） | F57: 俊兴 | G57: 回款 | H57: 到客户账户 | I57: 俊兴 | J57: 俊兴·客户账户 | K57: 1259333.9 | L57: 0 | M57: =IF(OR(N57="已登记",LEFT(N57,2)="按状"),0,K57-L57) | N57: 未开始(前一环节未完成)
A58: 20 | B58: 46262 | C58: 苏DBE075 | D58: 配票/反向 | E58: 我们配票（经俊兴） | F58: 林凯车队 | G58: 开票 | H58: 销项→欧冶 | I58: 俊兴 | J58: 欧冶物宝 | K58: 87745.4 | L58: 0 | M58: =IF(OR(N58="已登记",LEFT(N58,2)="按状"),0,K58-L58) | N58: 按状态视为已完成(历史)
A59: 20 | B59: 46262 | C59: 苏DBE075 | D59: 配票/反向 | E59: 我们配票（经俊兴） | F59: 林凯车队 | G59: 回款 | H59: 欧冶回款 | I59: 欧冶物宝 | J59: 俊兴 | K59: 87745.4 | L59: 0 | M59: =IF(OR(N59="已登记",LEFT(N59,2)="按状"),0,K59-L59) | N59: 待登记 | O59: 24
A60: 20 | B60: 46262 | C60: 苏DBE075 | D60: 配票/反向 | E60: 我们配票（经俊兴） | F60: 林凯车队 | G60: 回款 | H60: 到客户账户 | I60: 俊兴 | J60: 林凯车队·客户账户 | K60: 87745.4 | L60: 0 | M60: =IF(OR(N60="已登记",LEFT(N60,2)="按状"),0,K60-L60) | N60: 未开始(前一环节未完成)
A61: 21 | B61: 46262 | C61: 苏DBX137 | D61: 配票/反向 | E61: 我们配票（经俊兴） | F61: 林凯车队 | G61: 开票 | H61: 销项→欧冶 | I61: 俊兴 | J61: 欧冶物宝 | K61: 44022.04 | L61: 0 | M61: =IF(OR(N61="已登记",LEFT(N61,2)="按状"),0,K61-L61) | N61: 按状态视为已完成(历史)
A62: 21 | B62: 46262 | C62: 苏DBX137 | D62: 配票/反向 | E62: 我们配票（经俊兴） | F62: 林凯车队 | G62: 回款 | H62: 欧冶回款 | I62: 欧冶物宝 | J62: 俊兴 | K62: 44022.04 | L62: 0 | M62: =IF(OR(N62="已登记",LEFT(N62,2)="按状"),0,K62-L62) | N62: 待登记 | O62: 24
A63: 21 | B63: 46262 | C63: 苏DBX137 | D63: 配票/反向 | E63: 我们配票（经俊兴） | F63: 林凯车队 | G63: 回款 | H63: 到客户账户 | I63: 俊兴 | J63: 林凯车队·客户账户 | K63: 44022.04 | L63: 0 | M63: =IF(OR(N63="已登记",LEFT(N63,2)="按状"),0,K63-L63) | N63: 未开始(前一环节未完成)
A64: 22 | B64: 46262 | C64: 苏DFB287 | D64: 配票/反向 | E64: 我们配票（经俊兴） | F64: 林凯车队 | G64: 开票 | H64: 销项→欧冶 | I64: 俊兴 | J64: 欧冶物宝 | K64: 189762.3 | L64: 0 | M64: =IF(OR(N64="已登记",LEFT(N64,2)="按状"),0,K64-L64) | N64: 按状态视为已完成(历史)
A65: 22 | B65: 46262 | C65: 苏DFB287 | D65: 配票/反向 | E65: 我们配票（经俊兴） | F65: 林凯车队 | G65: 回款 | H65: 欧冶回款 | I65: 欧冶物宝 | J65: 俊兴 | K65: 189762.3 | L65: 0 | M65: =IF(OR(N65="已登记",LEFT(N65,2)="按状"),0,K65-L65) | N65: 待登记 | O65: 24
A66: 22 | B66: 46262 | C66: 苏DFB287 | D66: 配票/反向 | E66: 我们配票（经俊兴） | F66: 林凯车队 | G66: 回款 | H66: 到客户账户 | I66: 俊兴 | J66: 林凯车队·客户账户 | K66: 189762.3 | L66: 0 | M66: =IF(OR(N66="已登记",LEFT(N66,2)="按状"),0,K66-L66) | N66: 未开始(前一环节未完成)
A67: 23 | B67: 46262 | C67: 苏DFM060 | D67: 配票/反向 | E67: 我们配票（经俊兴） | F67: 林凯车队 | G67: 开票 | H67: 销项→欧冶 | I67: 俊兴 | J67: 欧冶物宝 | K67: 128955.66 | L67: 0 | M67: =IF(OR(N67="已登记",LEFT(N67,2)="按状"),0,K67-L67) | N67: 按状态视为已完成(历史)
A68: 23 | B68: 46262 | C68: 苏DFM060 | D68: 配票/反向 | E68: 我们配票（经俊兴） | F68: 林凯车队 | G68: 回款 | H68: 欧冶回款 | I68: 欧冶物宝 | J68: 俊兴 | K68: 128955.66 | L68: 0 | M68: =IF(OR(N68="已登记",LEFT(N68,2)="按状"),0,K68-L68) | N68: 待登记 | O68: 24
A69: 23 | B69: 46262 | C69: 苏DFM060 | D69: 配票/反向 | E69: 我们配票（经俊兴） | F69: 林凯车队 | G69: 回款 | H69: 到客户账户 | I69: 俊兴 | J69: 林凯车队·客户账户 | K69: 128955.66 | L69: 0 | M69: =IF(OR(N69="已登记",LEFT(N69,2)="按状"),0,K69-L69) | N69: 未开始(前一环节未完成)
A70: 24 | B70: 46262 | C70: 苏DBB772 | D70: 配票/反向 | E70: 我们配票（经俊兴） | F70: 林凯车队 | G70: 开票 | H70: 销项→欧冶 | I70: 俊兴 | J70: 欧冶物宝 | K70: 151899.8 | L70: 0 | M70: =IF(OR(N70="已登记",LEFT(N70,2)="按状"),0,K70-L70) | N70: 按状态视为已完成(历史)
A71: 24 | B71: 46262 | C71: 苏DBB772 | D71: 配票/反向 | E71: 我们配票（经俊兴） | F71: 林凯车队 | G71: 回款 | H71: 欧冶回款 | I71: 欧冶物宝 | J71: 俊兴 | K71: 151899.8 | L71: 0 | M71: =IF(OR(N71="已登记",LEFT(N71,2)="按状"),0,K71-L71) | N71: 待登记 | O71: 24
A72: 24 | B72: 46262 | C72: 苏DBB772 | D72: 配票/反向 | E72: 我们配票（经俊兴） | F72: 林凯车队 | G72: 回款 | H72: 到客户账户 | I72: 俊兴 | J72: 林凯车队·客户账户 | K72: 151899.8 | L72: 0 | M72: =IF(OR(N72="已登记",LEFT(N72,2)="按状"),0,K72-L72) | N72: 未开始(前一环节未完成)
A73: 25 | B73: 46262 | C73: 苏BDK567 | D73: 配票/反向 | E73: 我们配票（经俊兴） | F73: 林凯车队 | G73: 开票 | H73: 销项→欧冶 | I73: 俊兴 | J73: 欧冶物宝 | K73: 82709.74 | L73: 0 | M73: =IF(OR(N73="已登记",LEFT(N73,2)="按状"),0,K73-L73) | N73: 按状态视为已完成(历史)
A74: 25 | B74: 46262 | C74: 苏BDK567 | D74: 配票/反向 | E74: 我们配票（经俊兴） | F74: 林凯车队 | G74: 回款 | H74: 欧冶回款 | I74: 欧冶物宝 | J74: 俊兴 | K74: 82709.74 | L74: 0 | M74: =IF(OR(N74="已登记",LEFT(N74,2)="按状"),0,K74-L74) | N74: 待登记 | O74: 24
A75: 25 | B75: 46262 | C75: 苏BDK567 | D75: 配票/反向 | E75: 我们配票（经俊兴） | F75: 林凯车队 | G75: 回款 | H75: 到客户账户 | I75: 俊兴 | J75: 林凯车队·客户账户 | K75: 82709.74 | L75: 0 | M75: =IF(OR(N75="已登记",LEFT(N75,2)="按状"),0,K75-L75) | N75: 未开始(前一环节未完成)
A76: 26 | B76: 46262 | C76: 苏BUK952 | D76: 配票/反向 | E76: 我们配票（经俊兴） | F76: 林凯车队 | G76: 开票 | H76: 销项→欧冶 | I76: 俊兴 | J76: 欧冶物宝 | K76: 65790.74 | L76: 0 | M76: =IF(OR(N76="已登记",LEFT(N76,2)="按状"),0,K76-L76) | N76: 按状态视为已完成(历史)
A77: 26 | B77: 46262 | C77: 苏BUK952 | D77: 配票/反向 | E77: 我们配票（经俊兴） | F77: 林凯车队 | G77: 回款 | H77: 欧冶回款 | I77: 欧冶物宝 | J77: 俊兴 | K77: 65790.74 | L77: 0 | M77: =IF(OR(N77="已登记",LEFT(N77,2)="按状"),0,K77-L77) | N77: 待登记 | O77: 24
A78: 26 | B78: 46262 | C78: 苏BUK952 | D78: 配票/反向 | E78: 我们配票（经俊兴） | F78: 林凯车队 | G78: 回款 | H78: 到客户账户 | I78: 俊兴 | J78: 林凯车队·客户账户 | K78: 65790.74 | L78: 0 | M78: =IF(OR(N78="已登记",LEFT(N78,2)="按状"),0,K78-L78) | N78: 未开始(前一环节未完成)
A79: 27 | B79: 46262 | C79: 皖KQ1052 | D79: 配票/反向 | E79: 我们配票（经俊兴） | F79: 俊兴 | G79: 开票 | H79: 销项→欧冶 | I79: 俊兴 | J79: 欧冶物宝 | K79: 79637.41 | L79: 0 | M79: =IF(OR(N79="已登记",LEFT(N79,2)="按状"),0,K79-L79) | N79: 按状态视为已完成(历史)
A80: 27 | B80: 46262 | C80: 皖KQ1052 | D80: 配票/反向 | E80: 我们配票（经俊兴） | F80: 俊兴 | G80: 回款 | H80: 欧冶回款 | I80: 欧冶物宝 | J80: 俊兴 | K80: 79637.41 | L80: 0 | M80: =IF(OR(N80="已登记",LEFT(N80,2)="按状"),0,K80-L80) | N80: 待登记 | O80: 24
A81: 27 | B81: 46262 | C81: 皖KQ1052 | D81: 配票/反向 | E81: 我们配票（经俊兴） | F81: 俊兴 | G81: 回款 | H81: 到客户账户 | I81: 俊兴 | J81: 俊兴·客户账户 | K81: 79637.41 | L81: 0 | M81: =IF(OR(N81="已登记",LEFT(N81,2)="按状"),0,K81-L81) | N81: 未开始(前一环节未完成)
A82: 28 | B82: 46262 | C82: 苏DBE075 | D82: 配票/反向 | E82: 我们配票（经俊兴） | F82: 林凯车队 | G82: 开票 | H82: 销项→欧冶 | I82: 俊兴 | J82: 欧冶物宝 | K82: 150312.6 | L82: 0 | M82: =IF(OR(N82="已登记",LEFT(N82,2)="按状"),0,K82-L82) | N82: 按状态视为已完成(历史)
A83: 28 | B83: 46262 | C83: 苏DBE075 | D83: 配票/反向 | E83: 我们配票（经俊兴） | F83: 林凯车队 | G83: 回款 | H83: 欧冶回款 | I83: 欧冶物宝 | J83: 俊兴 | K83: 150312.6 | L83: 0 | M83: =IF(OR(N83="已登记",LEFT(N83,2)="按状"),0,K83-L83) | N83: 待登记 | O83: 24
A84: 28 | B84: 46262 | C84: 苏DBE075 | D84: 配票/反向 | E84: 我们配票（经俊兴） | F84: 林凯车队 | G84: 回款 | H84: 到客户账户 | I84: 俊兴 | J84: 林凯车队·客户账户 | K84: 150312.6 | L84: 0 | M84: =IF(OR(N84="已登记",LEFT(N84,2)="按状"),0,K84-L84) | N84: 未开始(前一环节未完成)
A85: 29 | B85: 46262 | C85: 冀A224E6 | D85: 配票/反向 | E85: 我们配票（经俊兴） | F85: 林凯车队 | G85: 开票 | H85: 销项→欧冶 | I85: 俊兴 | J85: 欧冶物宝 | K85: 70702 | L85: 0 | M85: =IF(OR(N85="已登记",LEFT(N85,2)="按状"),0,K85-L85) | N85: 按状态视为已完成(历史)
A86: 29 | B86: 46262 | C86: 冀A224E6 | D86: 配票/反向 | E86: 我们配票（经俊兴） | F86: 林凯车队 | G86: 回款 | H86: 欧冶回款 | I86: 欧冶物宝 | J86: 俊兴 | K86: 70702 | L86: 0 | M86: =IF(OR(N86="已登记",LEFT(N86,2)="按状"),0,K86-L86) | N86: 待登记 | O86: 24
A87: 29 | B87: 46262 | C87: 冀A224E6 | D87: 配票/反向 | E87: 我们配票（经俊兴） | F87: 林凯车队 | G87: 回款 | H87: 到客户账户 | I87: 俊兴 | J87: 林凯车队·客户账户 | K87: 70702 | L87: 0 | M87: =IF(OR(N87="已登记",LEFT(N87,2)="按状"),0,K87-L87) | N87: 未开始(前一环节未完成)
A88: 30 | B88: 46262 | C88: 苏BWX568 | D88: 配票/反向 | E88: 我们配票（经俊兴） | F88: 林凯车队 | G88: 开票 | H88: 销项→欧冶 | I88: 俊兴 | J88: 欧冶物宝 | K88: 77300.04 | L88: 0 | M88: =IF(OR(N88="已登记",LEFT(N88,2)="按状"),0,K88-L88) | N88: 按状态视为已完成(历史)
A89: 30 | B89: 46262 | C89: 苏BWX568 | D89: 配票/反向 | E89: 我们配票（经俊兴） | F89: 林凯车队 | G89: 回款 | H89: 欧冶回款 | I89: 欧冶物宝 | J89: 俊兴 | K89: 77300.04 | L89: 0 | M89: =IF(OR(N89="已登记",LEFT(N89,2)="按状"),0,K89-L89) | N89: 待登记 | O89: 24
A90: 30 | B90: 46262 | C90: 苏BWX568 | D90: 配票/反向 | E90: 我们配票（经俊兴） | F90: 林凯车队 | G90: 回款 | H90: 到客户账户 | I90: 俊兴 | J90: 林凯车队·客户账户 | K90: 77300.04 | L90: 0 | M90: =IF(OR(N90="已登记",LEFT(N90,2)="按状"),0,K90-L90) | N90: 未开始(前一环节未完成)
A91: 31 | B91: 46263 | C91: 苏DBB772 | D91: 配票/反向 | E91: 我们配票（经俊兴） | F91: 林凯车队 | G91: 开票 | H91: 销项→欧冶 | I91: 俊兴 | J91: 欧冶物宝 | K91: 202342.32 | L91: 0 | M91: =IF(OR(N91="已登记",LEFT(N91,2)="按状"),0,K91-L91) | N91: 按状态视为已完成(历史)
A92: 31 | B92: 46263 | C92: 苏DBB772 | D92: 配票/反向 | E92: 我们配票（经俊兴） | F92: 林凯车队 | G92: 回款 | H92: 欧冶回款 | I92: 欧冶物宝 | J92: 俊兴 | K92: 202342.32 | L92: 0 | M92: =IF(OR(N92="已登记",LEFT(N92,2)="按状"),0,K92-L92) | N92: 待登记 | O92: 23
A93: 31 | B93: 46263 | C93: 苏DBB772 | D93: 配票/反向 | E93: 我们配票（经俊兴） | F93: 林凯车队 | G93: 回款 | H93: 到客户账户 | I93: 俊兴 | J93: 林凯车队·客户账户 | K93: 202342.32 | L93: 0 | M93: =IF(OR(N93="已登记",LEFT(N93,2)="按状"),0,K93-L93) | N93: 未开始(前一环节未完成)
A94: 32 | B94: 46263 | C94: 苏ERS080 | D94: 配票/反向 | E94: 我们配票（经俊兴） | F94: 林凯车队 | G94: 开票 | H94: 销项→欧冶 | I94: 俊兴 | J94: 欧冶物宝 | K94: 115878.75 | L94: 0 | M94: =IF(OR(N94="已登记",LEFT(N94,2)="按状"),0,K94-L94) | N94: 按状态视为已完成(历史)
A95: 32 | B95: 46263 | C95: 苏ERS080 | D95: 配票/反向 | E95: 我们配票（经俊兴） | F95: 林凯车队 | G95: 回款 | H95: 欧冶回款 | I95: 欧冶物宝 | J95: 俊兴 | K95: 115878.75 | L95: 0 | M95: =IF(OR(N95="已登记",LEFT(N95,2)="按状"),0,K95-L95) | N95: 待登记 | O95: 23
A96: 32 | B96: 46263 | C96: 苏ERS080 | D96: 配票/反向 | E96: 我们配票（经俊兴） | F96: 林凯车队 | G96: 回款 | H96: 到客户账户 | I96: 俊兴 | J96: 林凯车队·客户账户 | K96: 115878.75 | L96: 0 | M96: =IF(OR(N96="已登记",LEFT(N96,2)="按状"),0,K96-L96) | N96: 未开始(前一环节未完成)
A97: 33 | B97: 46263 | C97: 苏DBE075 | D97: 配票/反向 | E97: 我们配票（经俊兴） | F97: 林凯车队 | G97: 开票 | H97: 销项→欧冶 | I97: 俊兴 | J97: 欧冶物宝 | K97: 198164.16 | L97: 0 | M97: =IF(OR(N97="已登记",LEFT(N97,2)="按状"),0,K97-L97) | N97: 按状态视为已完成(历史)
A98: 33 | B98: 46263 | C98: 苏DBE075 | D98: 配票/反向 | E98: 我们配票（经俊兴） | F98: 林凯车队 | G98: 回款 | H98: 欧冶回款 | I98: 欧冶物宝 | J98: 俊兴 | K98: 198164.16 | L98: 0 | M98: =IF(OR(N98="已登记",LEFT(N98,2)="按状"),0,K98-L98) | N98: 待登记 | O98: 23
A99: 33 | B99: 46263 | C99: 苏DBE075 | D99: 配票/反向 | E99: 我们配票（经俊兴） | F99: 林凯车队 | G99: 回款 | H99: 到客户账户 | I99: 俊兴 | J99: 林凯车队·客户账户 | K99: 198164.16 | L99: 0 | M99: =IF(OR(N99="已登记",LEFT(N99,2)="按状"),0,K99-L99) | N99: 未开始(前一环节未完成)
A100: 34 | B100: 46263 | C100: 冀A224E6 | D100: 配票/反向 | E100: 我们配票（经俊兴） | F100: 俊兴 | G100: 开票 | H100: 销项→欧冶 | I100: 俊兴 | J100: 欧冶物宝 | K100: 48340 | L100: 0 | M100: =IF(OR(N100="已登记",LEFT(N100,2)="按状"),0,K100-L100) | N100: 按状态视为已完成(历史)
...

Sheet 批次记录
A1: 批次ID | B1: 日期 | C1: 类型 | D1: 环节 | E1: 从 | F1: 到 | G1: 单号/流水号 | H1: 收款账户 | I1: 车次数 | J1: 批次金额(元) | K1: 备注 | M1: 明细：批次ID | N1: 车次ID | O1: 车号 | P1: 分摊金额(元)
A2: 还没有登记过批次（在系统「回款追踪」页勾选车次登记）

Sheet 票源额度
A1: 票源方 | B1: 类型 | C1: 额度周期 | D1: 周期起 | E1: 额度上限(元) | F1: 预警线(元) | G1: 已用(元) | H1: 占用比例 | I1: 剩余额度(元) | J1: 状态
A2: 反向-闫东朋 | B2: 反向自然人 | C2: 年度 | D2: 2026-01-01 | E2: 3500000 | F2: 1800000 | G2: 1035736.6 | H2: =IF(N(E2)=0,0,G2/E2) | I2: =IF(N(E2)=0,0,E2-G2) | J2: =IF(N(E2)=0,"未设额度",IF(G2>=E2,"已超额度",IF(AND(N(F2)>0,G2>=F2),"超预警线",IF(H2>=0.9,"接近额度","正常"))))
A3: 俊兴 | B3: 前端公司 | C3: 月度 | D3: 2026-09-01 | E3: 5000000 | G3: 2743286.9 | H3: =IF(N(E3)=0,0,G3/E3) | I3: =IF(N(E3)=0,0,E3-G3) | J3: =IF(N(E3)=0,"未设额度",IF(G3>=E3,"已超额度",IF(AND(N(F3)>0,G3>=F3),"超预警线",IF(H3>=0.9,"接近额度","正常"))))
A4: 益周 | B4: 前端公司 | C4: 月度 | D4: 2026-09-01 | E4: 5000000 | G4: 2498501.4 | H4: =IF(N(E4)=0,0,G4/E4) | I4: =IF(N(E4)=0,0,E4-G4) | J4: =IF(N(E4)=0,"未设额度",IF(G4>=E4,"已超额度",IF(AND(N(F4)>0,G4>=F4),"超预警线",IF(H4>=0.9,"接近额度","正常"))))
A5: 煌烽 | B5: 前端公司 | C5: 月度 | D5: 2026-09-01 | E5: 5000000 | G5: 4842789.2 | H5: =IF(N(E5)=0,0,G5/E5) | I5: =IF(N(E5)=0,0,E5-G5) | J5: =IF(N(E5)=0,"未设额度",IF(G5>=E5,"已超额度",IF(AND(N(F5)>0,G5>=F5),"超预警线",IF(H5>=0.9,"接近额度","正常"))))
A6: 反向-尹鹏飞 | B6: 反向自然人 | C6: 年度 | D6: 2026-01-01 | E6: 3500000 | F6: 1800000 | G6: 1563945.8 | H6: =IF(N(E6)=0,0,G6/E6) | I6: =IF(N(E6)=0,0,E6-G6) | J6: =IF(N(E6)=0,"未设额度",IF(G6>=E6,"已超额度",IF(AND(N(F6)>0,G6>=F6),"超预警线",IF(H6>=0.9,"接近额度","正常"))))
A8: 已用 = 本周期内该票源车次的票额(结算金额 − 吨位×垫资费单价)，与系统首页「票源额度水位」同口径。
